<?xml version="1.0" encoding="UTF-8"?><i><chatserver>chat.bilibili.com</chatserver><chatid>205300324</chatid><mission>0</mission><maxlimit>1000</maxlimit><state>0</state><real_name>0</real_name><source>e-r</source><d p="96.38000,1,25,16777215,1593224874,0,6a597e58,34646366592434183">拉低中奖率</d><d p="158.35900,1,25,16777215,1593224930,0,d416d310,34646395869724675">拉低中奖率</d><d p="176.76000,1,25,16777215,1593224956,0,d416d310,34646409234350085">兔兔！！！！</d><d p="209.17900,1,25,16777215,1593224993,0,d416d310,34646428559605765">啊啊啊啊啊啊啊啊啊啊啊啊啊</d><d p="121.49900,1,25,16777215,1593225031,0,bf6dca9,34646448883630083">。。。</d><d p="101.06800,1,25,16777215,1593225086,0,3c01eeea,34646477721042949">拉低中奖率</d><d p="155.55900,1,25,16777215,1593225144,0,3c01eeea,34646508144951303">拉低中奖率</d><d p="257.52000,1,25,16777215,1593225254,0,3c01eeea,34646565354209283">哈哈哈哈哈哈哈哈哈哈哈哈哈哈哈哈</d><d p="91.40000,1,25,16777215,1593225503,0,ac88da7d,34646695989477379">wow</d><d p="157.07600,1,25,16777215,1593225528,0,67f44c84,34646709037957125">我的我的</d><d p="123.40000,1,25,16777215,1593225538,0,ac88da7d,34646714619527175">wow</d><d p="145.03900,1,25,16777215,1593225566,0,ac88da7d,34646729166946311">啊啊啊啊啊啊我可以！</d><d p="269.72000,1,25,16777215,1593225706,0,ac88da7d,34646802430427139">我可以三个字臣妾都说倦了！</d><d p="239.09900,1,25,16777215,1593225723,0,f844eb86,34646811194425349">抽我抽我</d><d p="112.15200,1,25,16777215,1593225783,0,d980f564,34646843152400389">原来小破站还帮小王和八蛋设置了可移动字幕</d><d p="72.05300,1,25,16777215,1593225957,0,57aa91b3,34646934101164035">浓重介绍</d><d p="265.36100,1,25,16777215,1593226012,0,8d842b49,34646962810650627">拉低拉低</d><d p="280.49500,1,25,16777215,1593226027,0,8d842b49,34646970770915335">什么时候送榨汁机</d><d p="140.11600,1,25,16777215,1593226278,0,c207d59d,34647102613618691">喜欢</d><d p="206.01900,1,25,16777215,1593226298,0,4daf5dce,34647112873934855">我心动了！！！</d><d p="49.44800,1,25,16777215,1593226320,0,20cffc42,34647124672512007">拉低中奖率</d><d p="136.98600,1,25,16777215,1593226428,0,a58e8292,34647181087997955">想要想要</d><d p="291.07700,1,25,16777215,1593226429,0,c207d59d,34647181801029639">我要明信片</d><d p="52.95200,1,25,16777215,1593226853,0,aac1741b,34647403818123267">哈哈哈哈哈哈哈</d><d p="96.48200,1,25,16777215,1593226916,0,b01554c3,34647436816809989">想要啊啊啊啊啊啊啊啊啊啊啊啊啊啊啊啊啊啊啊啊啊啊啊啊啊啊啊</d><d p="114.64200,1,25,16777215,1593226936,0,b01554c3,34647447237558277">好想要啊啊啊啊啊啊啊啊啊啊啊啊啊啊阿啊啊啊啊啊阿</d><d p="122.52600,1,25,16777215,1593226953,0,b01554c3,34647456249020421">我可以我可以我可以</d><d p="149.42800,1,25,16777215,1593226962,0,aac1741b,34647460859084807">中奖率拉低</d><d p="166.06900,1,25,16777215,1593227005,0,b01554c3,34647483607416835">我的我的我的</d><d p="247.49300,1,25,16777215,1593227007,0,25d0625c,34647484442083335">我我我我</d><d p="251.21800,1,25,16777215,1593227010,0,25d0625c,34647486377754631">我可以</d><d p="256.31700,1,25,16777215,1593227015,0,25d0625c,34647489037467655">我喜欢这个</d><d p="265.38500,1,25,16777215,1593227024,0,25d0625c,34647493814779907">我好喜欢呀</d><d p="270.68000,1,25,16777215,1593227030,0,25d0625c,34647496590884867">我我我可以</d><d p="279.31700,1,25,16777215,1593227038,0,25d0625c,34647501117063173">爱你们，抽我吧</d><d p="63.02000,1,25,16777215,1593227042,0,c82feff1,34647502825193479">拉低中奖率</d><d p="287.30200,1,25,16777215,1593227046,0,25d0625c,34647505307172869">太可爱了，想要</d><d p="213.39600,1,25,16707842,1593227048,0,aac1741b,34647506335825923">[!!!!!!!!!]</d><d p="309.34800,1,25,16777215,1593227068,0,25d0625c,34647516868771843">好可爱</d><d p="102.25000,1,25,16777215,1593227091,0,a2b16693,34647528698806275">666</d><d p="17.32100,1,25,16777215,1593227408,0,578556f7,34647694694154245">排面</d><d p="56.51000,1,25,16777215,1593227595,0,9b72ccbb,34647792848732165">这啥呀</d><d p="12.43600,1,25,16777215,1593227991,0,b42e54c7,34648000555384839">芜湖</d><d p="79.89300,1,25,16777215,1593228001,0,840dcbac,34648005938774021">拉低  拉低</d><d p="51.54000,1,25,16777215,1593228051,0,b42e54c7,34648032218185731">哈哈哈哈哈哈哈</d><d p="69.28900,1,25,16777215,1593228099,0,b42e54c7,34648057186353157">来来来！当分母！</d><d p="150.14300,1,25,16777215,1593228207,0,b42e54c7,34648113733959687">好滴hhh</d><d p="95.74000,1,25,16777215,1593228440,0,67ecf401,34648236206063623">是不是我</d><d p="141.01700,1,25,16777215,1593228476,0,722f3d8,34648255044255749">拉低中奖率</d><d p="269.10100,1,25,16777215,1593228630,0,c879d582,34648335655108611">我也要啊啊啊</d><d p="124.00000,1,25,16777215,1593228631,0,1ed28bb9,34648335973875715">哦吼</d><d p="152.73500,1,25,16777215,1593228642,0,60f78160,34648341838561285">我我我我我！</d><d p="81.91300,1,25,16777215,1593228870,0,2248adf2,34648461594853381">阿巴阿巴</d><d p="271.67300,1,25,16777215,1593229065,0,2248adf2,34648563651706883">我看到了</d><d p="56.94000,1,25,16777215,1593229191,0,7e29f454,34648629527445507">拉低拉低</d><d p="175.36900,1,25,16777215,1593229250,0,2109ffb5,34648660653899781">能给我==嘛</d><d p="144.25800,1,25,16777215,1593229348,0,27fcdb3c,34648712038318085">想要 给我</d><d p="14.41900,1,25,16777215,1593229471,0,ca3e9568,34648776539373575">来来</d><d p="67.60500,1,25,16777215,1593230226,0,a9832fc4,34649172481146883">拉低中奖率</d><d p="129.12000,1,25,16777215,1593230391,0,5cd8e51a,34649258606460931">我呀我呀我呀</d><d p="206.43900,1,25,16777215,1593230476,0,5cd8e51a,34649303509106691">啊啊啊，我想要！！！</d><d p="255.66200,1,25,16777215,1593230547,0,d61d5555,34649340761866245">我我我我</d><d p="149.96700,1,25,16777215,1593230686,0,dc62b113,34649413677219907">拉低中奖几率</d><d p="93.37300,1,25,16777215,1593230734,0,eb7ce99a,34649438462935043">拉迪种地昂立</d><d p="191.79800,1,25,16777215,1593230772,0,dc62b113,34649458664275973">拉低中奖机概率</d><d p="0.43700,1,25,16777215,1593230790,0,15b91b93,34649467943124995">拉低中奖率</d><d p="119.87500,1,25,16777215,1593231099,0,b65deca,34649630119034887">好呆啊，好可爱</d><d p="75.39300,1,25,16777215,1593231186,0,419892d7,34649675747819523">我我我</d><d p="80.72400,1,25,16777215,1593231191,0,419892d7,34649678549090309">古古怪怪</d><d p="120.44600,1,25,16777215,1593231231,0,419892d7,34649699370663943">买买买买买买</d><d p="98.70800,1,25,16777215,1593231241,0,2a5f84d8,34649704301592579">想要</d><d p="110.66700,1,25,16777215,1593231275,0,2a5f84d8,34649722509590531">我我要中</d><d p="173.52700,1,25,16777215,1593231321,0,f0c15330,34649746629984259">我i想要这个！！！！</d><d p="28.83500,1,25,16777215,1593231333,0,8e3a8895,34649752863768581">我看到了</d><d p="55.78800,1,25,16777215,1593231345,0,a6c7faef,34649759101222915">奖奖奖</d><d p="107.58800,1,25,16777215,1593231414,0,a6c7faef,34649795288629251">好可爱！</d><d p="315.17000,1,25,16777215,1593231430,0,f0c15330,34649803369480195">动了</d><d p="149.73900,1,25,16777215,1593231474,0,6c7607c6,34649826419277829">美男子们抽我（挠头）</d><d p="116.09500,1,25,16777215,1593231538,0,da25ba41,34649860389994501">我来拉低中奖几率了！！！</d><d p="296.98800,1,25,16777215,1593231610,0,a6c7faef,34649898013949955">我我我！</d><d p="77.58900,1,25,16777215,1593231681,0,870fee5,34649934985691143">拉低中奖率</d><d p="243.76000,1,25,16777215,1593231698,0,aad8888d,34649944182226951">抽俺</d><d p="34.59800,1,25,16777215,1593231705,0,2f8ec30e,34649947686043651">来一个</d><d p="36.13800,1,25,16777215,1593231709,0,2f8ec30e,34649949791059971">来一个</d><d p="153.17900,1,25,16777215,1593231715,0,7eea729c,34649953068384263">哇哇哇哇哇，好像要</d><d p="206.24700,1,25,16777215,1593231715,0,dd39847,34649953163280391">我要这个啊啊啊啊啊啊啊啊啊啊啊啊啊啊啊！！！！！！！！！！！！！！！！！！！！！！！！</d><d p="106.80700,1,25,16777215,1593231734,0,a92fd4eb,34649962966941703">肯定是我中奖</d><d p="47.09400,1,25,16777215,1593231740,0,1265bb86,34649966341783555">哈哈哈哈哈哈哈哈哈哈哈哈</d><d p="256.99300,1,25,16777215,1593231755,0,bf33857c,34649974171500547">哈哈哈哈</d><d p="95.21800,1,25,16777215,1593231773,0,2f8ec30e,34649983297781765">拉低中奖率</d><d p="207.00300,1,25,16777215,1593231787,0,1cf2058f,34649990768361477">我的</d><d p="116.71800,1,25,16777215,1593231798,0,2f8ec30e,34649996262375429">拉低中奖率</d><d p="184.81200,1,25,16777215,1593231798,0,f83801fe,34649996766216195">害怕</d><d p="127.05800,1,25,16777215,1593231811,0,2f8ec30e,34650003196608515">拉低中奖率</d><d p="128.51200,5,25,16646914,1593231822,0,1265bb86,34650009024593927">不用看了是我的</d><d p="310.97600,1,25,16777215,1593231826,0,908a46aa,34650011382841351">啊啊啊啊拉抵中奖率</d><d p="151.95800,1,25,16777215,1593231841,0,2f8ec30e,34650019160653829">拉低中奖率</d><d p="153.89800,1,25,16777215,1593231845,0,2f8ec30e,34650021309186051">我的我的</d><d p="178.85800,1,25,16777215,1593231874,0,2f8ec30e,34650036255064071">？？？？？</d><d p="206.65800,1,25,16777215,1593231904,0,2f8ec30e,34650051877797893">啊啊啊</d><d p="209.41800,1,25,16777215,1593231910,0,2f8ec30e,34650055464976389">中</d><d p="211.95800,1,25,16777215,1593231918,0,2f8ec30e,34650059590598661">想要星耀</d><d p="219.98700,1,25,16777215,1593231950,0,f2634f00,34650076449603587">奖品金额差距巨大</d><d p="266.11800,1,25,16777215,1593231975,0,2f8ec30e,34650089462431747">拉低中奖率</d><d p="292.23800,1,25,16777215,1593232005,0,2f8ec30e,34650104923684867">拉滴</d><d p="294.63800,1,25,16777215,1593232012,0,2f8ec30e,34650108663431173">啦啦啦老啦啦啦老</d><d p="99.91800,1,25,16777215,1593232024,0,44bcaf6f,34650115243769863">我想中奖</d><d p="44.95300,1,25,16777215,1593232069,0,fd032585,34650138782728197">哈哈哈</d><d p="11.13000,5,25,15138834,1593232107,0,d0db0711,34650158595571715">拉低中奖率</d><d p="56.62000,1,25,16777215,1593232113,0,e6f0c69,34650161636966405">把我奖品摔坏了，你们赔</d><d p="69.34200,1,25,16777215,1593232121,0,ec8fb238,34650165728509955">拉低中奖率</d><d p="287.14000,1,25,16777215,1593232156,0,6c0178db,34650184447164419">我我</d><d p="116.67300,1,25,16777215,1593232175,0,c936442,34650194336284675">拉低</d><d p="153.97500,1,25,16777215,1593232186,0,da355c0e,34650199911038979">拉低中奖概率</d><d p="147.39300,1,25,16777215,1593232186,0,fd032585,34650200089821191">金色传说</d><d p="163.58700,1,25,16777215,1593232196,0,da355c0e,34650204949970951">啊啊啊啊啊啊</d><d p="138.16000,1,25,16777215,1593232196,0,d47b145d,34650204959932419">你吹牛逼别抽到我了</d><d p="199.18200,1,25,16777215,1593232250,0,da355c0e,34650233761169415">我要</d><d p="211.47300,1,25,16777215,1593232270,0,c936442,34650244220715013">抽不到我的</d><d p="295.23300,1,25,16777215,1593232347,0,da355c0e,34650284120080389">爱了爱了</d><d p="169.26100,5,25,16777215,1593232369,0,d0db0711,34650295804362755">拉低中奖率</d><d p="68.58500,1,25,16777215,1593232373,0,d3ccf32c,34650298044121093">拉低中奖率</d><d p="169.26100,5,25,15138834,1593232375,0,d0db0711,34650298789658629">拉低中奖率</d><d p="169.26100,5,25,16707842,1593232385,0,d0db0711,34650304185106435">拉低中奖率</d><d p="169.26100,5,25,38979,1593232392,0,d0db0711,34650307779100677">拉低中奖率</d><d p="169.26100,5,25,41194,1593232400,0,d0db0711,34650311934083075">拉低中奖率</d><d p="169.26100,5,25,14811775,1593232407,0,d0db0711,34650315701616643">拉低中奖率</d><d p="169.26100,5,25,9487136,1593232414,0,d0db0711,34650319415672837">拉低中奖率</d><d p="169.26100,5,25,9487136,1593232420,0,d0db0711,34650322503204869">拉低中奖率</d><d p="169.26100,5,25,11890,1593232430,0,d0db0711,34650327702568967">拉低中奖率</d><d p="169.26100,5,25,15772458,1593232437,0,d0db0711,34650331663040519">拉低中奖率</d><d p="169.26100,5,25,6830715,1593232444,0,d0db0711,34650335386009607">拉低中奖率</d><d p="169.26100,5,25,8700107,1593232450,0,d0db0711,34650338221359111">拉低中奖率</d><d p="102.98100,1,25,16777215,1593232454,0,f1b9f9c3,34650340195303429">非酋路过</d><d p="115.90100,1,25,16777215,1593232456,0,a631eca8,34650341379145735">啊啊啊啊啊</d><d p="169.26100,5,25,9599289,1593232457,0,d0db0711,34650341795430407">拉低中奖率</d><d p="301.09900,1,25,16777215,1593232526,0,a217cfc2,34650378389684231">冲冲冲！</d><d p="308.29900,5,25,15138834,1593232547,0,a217cfc2,34650389210464259">冲！</d><d p="96.91600,4,25,15138834,1593232572,0,18443399,34650402550972421">拉低中奖率</d><d p="144.44700,4,25,15138834,1593232627,0,18443399,34650431219040261">这个我可以！！</d><d p="170.90000,4,25,15138834,1593232664,0,18443399,34650450406932485">我的我的我的</d><d p="170.90000,4,25,15138834,1593232673,0,18443399,34650455364075527">我的我的我的</d><d p="124.00800,1,25,16777215,1593232676,0,cb01420f,34650456731942915">来了来了冲冲冲！</d><d p="170.90000,4,25,15138834,1593232679,0,18443399,34650458541785091">我的我的我的</d><d p="170.90000,4,25,15138834,1593232685,0,18443399,34650461356163075">我的我的我的</d><d p="170.90000,4,25,15138834,1593232693,0,18443399,34650465832534019">我的我的我的</d><d p="206.82600,4,25,16707842,1593232746,0,18443399,34650493614030855">我的我的我的！！想要</d><d p="197.01900,1,25,16777215,1593232801,0,e350d6e3,34650522633895943">拉低拉低</d><d p="56.19900,5,25,15138834,1593232849,0,6c970f69,34650547364560899">小王和八蛋！</d><d p="88.27000,1,25,16777215,1593232909,0,5bede1f7,34650579272728583">........</d><d p="55.06300,1,25,16777215,1593232931,0,99406c11,34650590755684355">拉低中奖率</d><d p="110.15000,1,25,16777215,1593232934,0,5bede1f7,34650592257769479">我要</d><d p="82.18800,1,25,16777215,1593232944,0,708f0afd,34650597200756739">啊啊啊啊啊，拉低中奖率！！@</d><d p="117.65000,1,25,16777215,1593232946,0,5bede1f7,34650598466387975">呵呵呵呵这质量</d><d p="100.84500,1,25,16777215,1593233106,0,82b5c05f,34650682104479751">冲冲冲！</d><d p="113.07500,1,25,16777215,1593233118,0,82b5c05f,34650688470908935">全都要！</d><d p="152.25200,1,25,16777215,1593233157,0,82b5c05f,34650709009367047">我可以我可以！！！</d><d p="199.91800,1,25,16777215,1593233224,0,9923f56f,34650744066408453">拉低中奖几率</d><d p="84.91600,1,25,16777215,1593233269,0,5e7eb6b4,34650767741681671">拉低中奖率</d><d p="206.86500,1,25,16777215,1593233431,0,5e7eb6b4,34650852862984197">ohhhh</d><d p="217.01500,1,25,16777215,1593233492,0,c80a1843,34650884637982727">我要二等奖！！</d><d p="101.01500,1,25,16777215,1593233556,0,5fe60428,34650918449315909">额</d><d p="101.29900,1,25,15138834,1593233669,0,4a800ba2,34650977343635463">拉低中奖率</d><d p="100.99800,1,25,16777215,1593233868,0,c5359ef2,34651081702113287">抽我</d><d p="31.88800,1,25,16777215,1593233910,0,5c617ee5,34651104051462151">拉低中奖率</d><d p="206.82000,1,25,16777215,1593233917,0,593eee3b,34651107359195143">哇塞！</d><d p="182.51800,1,25,16777215,1593233955,0,c5359ef2,34651127258021891">好可爱啊啊啊啊啊啊啊</d><d p="115.27700,1,25,16777215,1593234045,0,8a6ad2ce,34651174488506371">冲冲冲</d><d p="130.60800,1,25,16777215,1593234066,0,8a6ad2ce,34651185441407047">拉低中奖率</d><d p="98.03300,1,25,16777215,1593234075,0,25a6130d,34651190539583493">拉低中奖率</d><d p="75.28800,1,25,16777215,1593234092,0,3aaec218,34651199170412549">np</d><d p="175.25500,1,25,16777215,1593234116,0,8a6ad2ce,34651212096208899">我的我的我的!</d><d p="163.15800,1,25,16777215,1593234329,0,2b40cf33,34651323580809221">fuuuuuuuuu！！</d><d p="116.75000,1,25,16777215,1593234480,0,e830da05,34651402859446277">给我中</d><d p="75.08000,1,25,16777215,1593234926,0,3b0e6ce6,34651636594900999">拉低</d><d p="155.49500,1,25,16777215,1593235040,0,f23a245a,34651696296099845">我要</d><d p="151.80900,1,25,16777215,1593235052,0,82679886,34651702509436931">我也要</d><d p="210.15800,1,25,16777215,1593235116,0,f23a245a,34651736009342983">我刚付了预付款，不过抽我</d><d p="98.05000,1,25,16777215,1593235142,0,30632f1,34651749875187715">我来了嘎！，</d><d p="102.92200,1,25,16777215,1593235147,0,30632f1,34651752309456899">我去⊙∀⊙！</d><d p="108.50500,1,25,16777215,1593235151,0,4ff94042,34651754611081223">哈嘿速度</d><d p="107.30300,1,25,16777215,1593235151,0,30632f1,34651754617372675">我要</d><d p="163.09600,1,25,16777215,1593235161,0,1ea6a3b9,34651759657353219">拉低</d><d p="126.12900,1,25,16777215,1593235170,0,30632f1,34651764467171331">拉低了嘎</d><d p="137.81200,1,25,16777215,1593235182,0,30632f1,34651770592952323">我中了嘎！</d><d p="265.11800,1,25,16777215,1593235206,0,f23a245a,34651783166427143">背---心---</d><d p="97.03000,1,25,16777215,1593235216,0,6f20c348,34651788368412675">拉低</d><d p="205.42800,1,25,16777215,1593235249,0,30632f1,34651806045306883">啊啊啊啊啊啊啊</d><d p="210.66100,1,25,16777215,1593235255,0,30632f1,34651808783663109">冲啊</d><d p="133.75400,1,25,16777215,1593235263,0,62658f1c,34651813235916807">我想要</d><d p="140.25400,1,25,16777215,1593235269,0,62658f1c,34651816509571079">我想要</d><d p="155.75400,1,25,16777215,1593235285,0,62658f1c,34651824749805575">老哥谢谢</d><d p="186.75300,1,25,16777215,1593235316,0,62658f1c,34651840986480645">我要</d><d p="297.70200,1,25,16777215,1593235335,0,6f20c348,34651850814783491">不要了 不要了</d><d p="113.74000,1,25,16777215,1593235341,0,c8fc6a7a,34651854199062531">这真好看</d><d p="136.82700,1,25,16777215,1593235363,0,164cd0ac,34651865750175751">拉低中奖率</d><d p="75.00800,1,25,16777215,1593235375,0,46a4ea3a,34651871644745731">1</d><d p="207.38000,1,25,16777215,1593235413,0,692d1c50,34651891924729927">拉低中奖率！！！！</d><d p="298.41600,1,25,16777215,1593235415,0,7972d76b,34651893132165125">中奖</d><d p="290.15200,1,25,16777215,1593235416,0,cb3689fd,34651893642297351">hhhhhhh</d><d p="139.93100,1,25,16777215,1593235462,0,b966866e,34651917414039555">我要fufu</d><d p="127.22700,1,25,16777215,1593235598,0,d0cb3726,34651988877115395">我来了</d><d p="154.26500,1,25,16777215,1593235625,0,d0cb3726,34652003007725571">我来做分母了，各位，互相伤害吧</d><d p="113.47800,1,25,16777215,1593235631,0,524dd6c9,34652006091587587">拉低中奖率</d><d p="94.02000,1,25,16777215,1593235637,0,c5bb1ac4,34652009414000645">中中中！</d><d p="115.58400,1,25,16777215,1593235741,0,528946a,34652063891718149">拉低中奖率</d><d p="17.30000,1,25,16777215,1593235755,0,531e7bd8,34652071352336387">我我我！！！</d><d p="21.56600,1,25,16777215,1593235769,0,531e7bd8,34652078422360071">我我我！</d><d p="82.07800,1,25,16777215,1593235776,0,a7769be1,34652082233409541">拉底中奖率</d><d p="293.19300,1,25,16777215,1593235804,0,cf4794bf,34652096850034695">我要——明信片——</d><d p="101.95100,1,25,16777215,1593235829,0,c233bbab,34652110112423943">给我中</d><d p="96.77900,1,25,16777215,1593235915,0,2eced64c,34652155156103175">拉低中奖率</d><d p="113.22100,1,25,16777215,1593235931,0,471257c5,34652163467640835">想要</d><d p="93.01200,1,25,16777215,1593235975,0,531e7bd8,34652186527924231">我我我</d><d p="177.25700,1,25,15138834,1593236225,0,459bbdab,34652317331488775">我的我的我的！</d><d p="201.21300,1,25,16777215,1593236292,0,f2d2b0f1,34652352589856771">都是我的 都是我的</d><d p="169.21600,1,25,16777215,1593236316,0,a933afde,34652365028065283">啊啊啊啊啊啊啊啊啊啊啊啊</d><d p="175.51300,1,25,16777215,1593236322,0,a933afde,34652368320593925">未到未到未到未到未到未到</d><d p="170.26600,1,25,16777215,1593236433,0,320ea90f,34652426597826563">是阿米娅啊啊啊啊啊啊啊啊啊啊啊啊啊啊</d><d p="153.49200,1,25,16777215,1593236452,0,81759d16,34652436734935043">求中！</d><d p="133.90600,1,25,16777215,1593236469,0,74949c11,34652445666181125">害怕</d><d p="70.72600,1,25,16777215,1593236474,0,ed570a80,34652448004505603">好多fufu！</d><d p="152.54100,4,25,16707842,1593236488,0,74949c11,34652455406927879">害怕害怕害怕</d><d p="64.55000,1,25,16777215,1593236508,0,c5d05b5c,34652466070945797">来啦</d><d p="138.27600,1,25,16777215,1593236549,0,ed570a80,34652487207616517">我要fufu！</d><d p="296.56600,1,25,16777215,1593236742,0,35832d82,34652588547768323">我</d><d p="89.74500,1,25,16777215,1593236791,0,84f410ea,34652614505267205">哦吼</d><d p="114.41000,1,25,16777215,1593236826,0,84f410ea,34652632777752583">来啊来啊</d><d p="152.97000,1,25,16777215,1593236871,0,84f410ea,34652656415801347">哈哈哈哈</d><d p="165.04900,1,25,16777215,1593236885,0,84f410ea,34652663746920453">卧槽</d><d p="18.24900,1,25,16777215,1593236900,0,a4547e22,34652671279890435">小王和八蛋</d><d p="196.89000,1,25,16777215,1593236920,0,84f410ea,34652681864216581">有有有</d><d p="60.78000,1,25,16777215,1593236930,0,285ae70a,34652687369764867">拉低中奖率</d><d p="73.61900,1,25,16777215,1593237044,0,94605821,34652746847617031">拉低中奖率</d><d p="34.35200,1,25,16777215,1593237057,0,466d180e,34652753599922181">拉低中奖概率中……</d><d p="118.85200,1,25,16777215,1593237141,0,466d180e,34652797913792515">如果我一直发弹幕，中奖几率是不是会高！</d><d p="150.51200,1,25,16777215,1593237173,0,466d180e,34652814499119109">想要这个</d><d p="19.67000,1,25,16777215,1593237175,0,f9311ea0,34652815857549317">拉低中奖率</d><d p="206.48300,1,25,16777215,1593237195,0,94605821,34652825878265861">卧槽 拉低中奖率 想要</d><d p="178.32000,1,25,16777215,1593237201,0,466d180e,34652829112074243">我要这个~！！！</d><d p="189.86600,1,25,16777215,1593237212,0,466d180e,34652835135094789">吼吼看</d><d p="222.08900,1,25,16777215,1593237244,0,466d180e,34652852066975751">看我看我~</d><d p="269.11700,1,25,16777215,1593237262,0,94605821,34652861018144775">不错</d><d p="253.17400,1,25,16777215,1593237276,0,466d180e,34652868332486659">我要大毛绒就行~！！！真的~！！！</d><d p="304.40800,1,25,16777215,1593237327,0,466d180e,34652895191236611">我想要的蜡像已经被你们做成瓜子机了</d><d p="24.38300,1,25,16777215,1593237436,0,20a3f7b4,34652952347017219">中奖</d><d p="60.62900,1,25,16777215,1593237472,0,20a3f7b4,34652971350360067">拉低中奖率</d><d p="189.24600,1,25,16777215,1593237644,0,c093eda,34653061349638147">我可以！</d><d p="211.61900,1,25,16777215,1593237656,0,1dfbb37b,34653067640045575">想要</d><d p="252.65200,1,25,16777215,1593237664,0,20a3f7b4,34653072036200451">俺也想要</d><d p="268.15400,1,25,16777215,1593237680,0,20a3f7b4,34653080168955907">给我也整一个</d><d p="291.98500,1,25,16777215,1593237703,0,20a3f7b4,34653092665360391">这个我要</d><d p="304.01700,1,25,16777215,1593237715,0,20a3f7b4,34653098979885059">明信片啊~~~~</d><d p="255.25900,1,25,16777215,1593237785,0,710d65f2,34653135538487303">硬核音效</d><d p="292.57500,5,18,6830715,1593238091,0,5278c983,34653296030384131">八可能!</d><d p="116.21900,1,25,9599289,1593238244,0,532ffc2c,34653375853756421">拉低</d><d p="277.94800,1,25,16777215,1593238308,0,ea55e916,34653409557610501">拉低中奖率</d><d p="214.35500,1,25,16777215,1593238312,0,f008d60a,34653411770105859">我要，嘿嘿嘿</d><d p="124.41700,1,25,16777215,1593238403,0,c5868c7a,34653459264831495">冲冲冲！</d><d p="150.43900,1,25,16777215,1593238429,0,c5868c7a,34653472907329543">想要！！</d><d p="7.29500,1,25,16777215,1593238449,0,f5d46236,34653483427168263">哈哈哈哈哈哈</d><d p="190.48400,1,25,16777215,1593238469,0,c5868c7a,34653493901918215">！！想要！！阿米驴</d><d p="2.40600,1,25,16777215,1593238526,0,1f0c6397,34653523849248771">点赞20万能白嫖奖品</d><d p="265.87600,1,25,16777215,1593238544,0,c5868c7a,34653533438476293">哈哈哈哈哈哈</d><d p="59.01000,5,25,15138834,1593238557,0,5e3894c4,34653540097982467">好多公主陛下！</d><d p="134.33900,1,25,16777215,1593238562,0,31716adf,34653542634487811">我要</d><d p="299.92000,1,25,16777215,1593238578,0,c5868c7a,34653551286812677">我可以！</d><d p="120.37200,5,25,15138834,1593238627,0,5e3894c4,34653576709537797">拉低中奖率</d><d p="34.91000,1,25,16777215,1593238977,0,941b969c,34653760473530373">哈哈哈哈哈哈或或或或或或或或</d><d p="124.20300,1,25,16777215,1593239079,0,941b969c,34653813745385479">可可爱爱！！</d><d p="131.11600,1,25,16777215,1593239087,0,941b969c,34653817938116613">好可爱！！</d><d p="143.55500,1,25,16777215,1593239099,0,941b969c,34653824463929347">miku！！！！！！</d><d p="171.63200,1,25,16777215,1593239144,0,941b969c,34653847997644805">阿米驴！！！</d><d p="171.63200,1,25,16777215,1593239156,0,941b969c,34653854224613381">兔兔兔兔！！！</d><d p="171.63200,1,25,16777215,1593239170,0,941b969c,34653861338152965">刀客塔报道！</d><d p="204.26600,1,25,16777215,1593239216,0,941b969c,34653885912055811">集中一点，登峰造极！！</d><d p="204.26600,1,25,16777215,1593239229,0,941b969c,34653892769742851">我是为了获得幸福才来到这个世界上的！</d><d p="273.42400,1,25,16777215,1593239311,0,941b969c,34653935399600133">我我我我我我哦</d><d p="92.82000,1,25,16777215,1593239469,0,1d083878,34654018301591559">拉低中奖率</d><d p="318.61400,1,25,16777215,1593239473,0,a9966da5,34654020487872515">我的我都</d><d p="306.71300,1,25,16777215,1593239645,0,3d765eb4,34654110789664835">拉低中奖率</d><d p="67.72000,1,25,16777215,1593239671,0,eec72141,34654124415385607">我想白嫖一个</d><d p="293.65900,1,25,16777215,1593239861,0,7ec9253c,34654223917907971">我要我要</d><d p="92.93900,1,25,16777215,1593239897,0,70651e68,34654242658058245">，我又来了，想要，</d><d p="58.47700,1,25,16777215,1593239951,0,3f341554,34654271212355591">拉低中奖率</d><d p="34.06700,1,25,16777215,1593240069,0,b1c60cb9,34654333126049799">哈哈哈哈哈哈</d><d p="87.59300,1,25,16777215,1593240108,0,ce7b70a6,34654353118199811">雷霆巴嘎</d><d p="161.70500,1,25,16777215,1593240428,0,41b0bcdd,34654521156698115">我，要帕克</d><d p="53.11300,1,25,16777215,1593240601,0,aab9e478,34654611993788423">狡诈恶徒</d><d p="189.33900,1,25,16777215,1593240688,0,ef0bb653,34654657249280003">来了来了</d><d p="95.46000,1,25,16777215,1593240734,0,a66f1669,34654681427345413">我来了</d><d p="317.27800,1,25,16777215,1593240757,0,c84dd4d8,34654693657935877">三等奖想要</d><d p="277.78000,1,25,16777215,1593240793,0,194b360c,34654712435834883">我我问我</d><d p="279.68000,1,25,16777215,1593240809,0,194b360c,34654720790364163">哪里中奖纪律律</d><d p="144.94000,1,25,16777215,1593240901,0,f62437d1,34654769195253765">我来组成分母！</d><d p="107.42200,1,25,16777215,1593241018,0,7273d116,34654830470365189">拉低拉低</d><d p="101.17400,1,25,16777215,1593241070,0,a9f9e74f,34654857573957635">都是我的</d><d p="108.83900,1,25,16777215,1593241259,0,bc2df3b7,34654956902416391">啊啊啊啊啊啊我啊我我我我</d><d p="107.32700,1,25,16777215,1593241348,0,e3268e84,34655003473346567">拉低中奖率</d><d p="130.02500,1,25,16777215,1593241413,0,f10922fc,34655037451403267">抽</d><d p="248.40600,1,25,16777215,1593241531,0,f10922fc,34655099483062275">我我我</d><d p="262.23300,1,25,16777215,1593241545,0,f10922fc,34655106676817927">有本事别抽到我</d><d p="117.54900,1,25,16777215,1593241610,0,46c09a24,34655140952145927">我也好像要33</d><d p="167.23400,1,25,16777215,1593241646,0,55c1e702,34655159890477059">拉低中奖率</d><d p="55.85900,1,25,16777215,1593241676,0,592ca16e,34655175349108739">冲冲冲！</d><d p="149.59900,1,25,16777215,1593241687,0,89603a47,34655181071187971">成为分子</d><d p="121.47500,1,25,16777215,1593241763,0,4c539679,34655220815364101">拉低中奖率。</d><d p="95.63500,1,25,16777215,1593241801,0,aa848e5b,34655241143058499">我我我！</d><d p="72.41800,1,25,16777215,1593241990,0,f813adc7,34655340120244231">啊哈</d><d p="189.86100,1,25,16777215,1593242002,0,76b95c10,34655346144837637">啊啊啊想要</d><d p="58.46600,1,25,16777215,1593242061,0,28a1d535,34655377530290243">拉低中奖率</d><d p="279.19200,1,25,16777215,1593242091,0,76b95c10,34655392926531589">看看孩子吧</d><d p="152.87900,1,25,16777215,1593242184,0,28a1d535,34655442012471299">中奖</d><d p="209.54100,1,25,16777215,1593242241,0,28a1d535,34655471716007943">想要</d><d p="293.32000,1,25,16777215,1593242368,0,d7d5d92c,34655538304778243">想要了</d><d p="146.08400,1,25,16777215,1593242734,0,f3369c19,34655730367201283">想要！！！！！！！！</d><d p="118.25100,1,25,16777215,1593242844,0,610a71c4,34655787730599943">抽奖呀</d><d p="130.75000,1,25,16777215,1593242856,0,610a71c4,34655794151555079">来了来了</d><d p="297.43500,5,25,15772458,1593243539,0,7f64371c,34656152221908999">我可以哈哈哈</d><d p="295.52500,1,25,16777215,1593243711,0,50513f46,34656242533662723">啊啊啊啊啊啊</d><d p="113.75300,1,25,16777215,1593243740,0,338c3345,34656257567096835">拉低中奖率</d><d p="124.49700,1,25,16777215,1593243863,0,f06bdd84,34656321851621383">拉低中奖率</d><d p="288.59600,1,25,16777215,1593243868,0,aa1c523d,34656324732059653">拉低中奖率啦</d><d p="54.21600,1,25,16777215,1593243989,0,b4e2a3ca,34656387904045061">哈哈哈哈哈</d><d p="289.30400,1,25,16777215,1593244260,0,b4e2a3ca,34656530226741255">低</d><d p="140.91400,1,25,16777215,1593244452,0,1e41dc52,34656630942990339">ppt警告</d><d p="47.00900,1,25,16777215,1593244700,0,a83d7315,34656761104826375">低</d><d p="165.21900,1,25,16777215,1593245130,0,ccfdfe04,34656986362019847">我笑到炸裂</d><d p="147.62300,1,25,16777215,1593245319,0,73e049ad,34657085665837059">中个奖.... ?</d><d p="180.52200,1,25,16777215,1593245365,0,f1c5beb4,34657109357887495">好卡哇伊</d><d p="70.57500,1,25,16777215,1593245367,0,751415e6,34657110621945863">小王和八蛋</d><d p="94.37500,1,25,16777215,1593245391,0,751415e6,34657123113107463">哇</d><d p="175.42300,1,25,16777215,1593245416,0,47d5767a,34657136426352643">我也要</d><d p="130.35200,1,25,16777215,1593245431,0,6c8e3354,34657143986585603">吼吼吼</d><d p="270.92200,1,25,16777215,1593245459,0,f1c5beb4,34657158864306181">我要</d><d p="167.69700,1,25,16777215,1593245464,0,751415e6,34657161557573637">太好看了把</d><d p="287.60200,1,25,16777215,1593245479,0,f1c5beb4,34657169372610565">我可以</d><d p="206.21700,1,25,16777215,1593245503,0,751415e6,34657181755244549">哦我我我我我</d><d p="240.96500,1,25,16777215,1593245537,0,751415e6,34657199966912515">俺要俺要</d><d p="57.57800,1,25,16777215,1593245549,0,88ee762c,34657206095314947">拉低中奖率</d><d p="275.67000,1,25,16777215,1593245572,0,751415e6,34657218161278979">ohhhhhhhh</d><d p="288.00200,1,25,16777215,1593245584,0,751415e6,34657224626274307">呕呕呕</d><d p="73.92200,1,25,16777215,1593245630,0,27587f37,34657248674840581">拉低中奖率</d><d p="238.65400,1,25,16777215,1593245640,0,1858fe1d,34657253746802691">追过一段时间番剧：指不认识祢豆子</d><d p="129.36500,1,25,16777215,1593245686,0,27587f37,34657277732454407">我也想要要</d><d p="111.03500,1,25,8700107,1593245794,0,ca1c002b,34657334484008963">提高老子的中奖率</d><d p="72.75000,1,25,16777215,1593245858,0,cff99dc5,34657367785734147">拉低中奖率</d><d p="136.16700,1,25,16777215,1593246391,0,7307ae3d,34657647392718853">？</d><d p="123.91700,1,25,16777215,1593246564,0,19ee0abd,34657737984442375">中奖</d><d p="201.08700,1,25,16777215,1593246650,0,a3503319,34657783270866949">哒哒哒</d><d p="160.34500,1,25,16777215,1593246688,0,8e3c44f,34657803130896389">我</d><d p="135.78000,1,25,16777215,1593246798,0,3e80f8ab,34657860819877891">你看我行吗</d><d p="123.47900,1,25,16777215,1593246971,0,44f8cd63,34657951637569541">拉低中奖率</d><d p="126.28000,1,25,16777215,1593246979,0,44f8cd63,34657955787309059">拉低中奖率</d><d p="141.10000,1,25,16777215,1593247250,0,4d5638a3,34658098035556355">给我来一个</d><d p="156.64600,1,25,16777215,1593247605,0,3a36a6e1,34658283774017541">老婆！</d><d p="163.80000,1,25,16777215,1593247638,0,77ae72d2,34658301208690695">中？</d><d p="154.34000,1,25,16777215,1593247741,0,54232cea,34658355284803591">拉低</d><d p="146.88500,1,25,16777215,1593247899,0,4a632ae6,34658438147997699">啊啊啊啊啊，这个我爱了</d><d p="149.14000,1,25,16777215,1593247906,0,bb469b27,34658441548005379">这个卡哇伊</d><d p="125.84000,1,25,16777215,1593248097,0,306c9ab3,34658541625671685">拉低中奖率</d><d p="70.80000,1,25,16777215,1593248221,0,2aa36f1d,34658606764785671">拉低中奖率</d><d p="91.29800,1,25,16777215,1593248645,0,d48560c8,34658829018857477">拉低中奖率</d><d p="81.52500,1,25,16777215,1593248656,0,b6b2aaa2,34658835127861253">送我。</d><d p="87.79500,1,25,16777215,1593248668,0,b6b2aaa2,34658841349062663">我要</d><d p="115.73300,1,25,16777215,1593248683,0,d48560c8,34658848920305671">拉低中奖率</d><d p="129.38800,1,25,16777215,1593248716,0,6692c028,34658866273714183">拉低中奖率</d><d p="55.17500,1,25,16777215,1593248719,0,f31fb5b5,34658867794149381">拉低中奖率吧！！！！</d><d p="62.84900,1,25,16777215,1593248737,0,f31fb5b5,34658877193584647">这也太多了吧 发出了想要的声音</d><d p="165.74800,1,25,16777215,1593248747,0,fc263031,34658882864807943">不是针对谁，在座的各位都是分母</d><d p="113.19700,1,25,16777215,1593248793,0,f31fb5b5,34658906622918659">我可以我可以</d><d p="127.62900,1,25,16777215,1593248817,0,f31fb5b5,34658919318028291">拉低中奖率！！！</d><d p="147.67800,1,25,16777215,1593248842,0,f31fb5b5,34658932549484547">可以 都很厉害</d><d p="103.94100,1,25,16777215,1593248882,0,b6abc5a3,34658953354805255">来来来</d><d p="169.93800,1,25,16777215,1593248885,0,f31fb5b5,34658954821763077">我想要 好想</d><d p="117.39100,1,25,16777215,1593248958,0,127321ed,34658993315512323">拉低</d><d p="15.83400,1,25,16777215,1593248975,0,f2295482,34659002313342983">哈哈哈哈哈</d><d p="18.71400,1,25,16777215,1593249012,0,f2295482,34659021684736005">哈哈哈哈哈现在买的好聪明啊</d><d p="205.52600,1,25,16777215,1593249035,0,f31fb5b5,34659033914802179">啊啊啊啊卧槽！！！！</d><d p="49.73700,1,25,16777215,1593249062,0,f2295482,34659047937409031">哈哈哈哈哈胡老师</d><d p="255.97100,1,25,16777215,1593249090,0,f31fb5b5,34659062307094535">哈哈哈哈哈哈哈哈哈哈</d><d p="61.18700,1,25,16777215,1593249114,0,f2295482,34659074934046723">没听清阿灿说啥</d><d p="97.50800,1,25,16777215,1593249189,0,910988a9,34659114323279875">拉低中奖概率</d><d p="199.07500,1,25,16777215,1593249260,0,f2295482,34659151411937285">有有有</d><d p="150.79200,1,25,16777215,1593249594,0,86204882,34659326575509511">拉低</d><d p="118.96800,1,25,16777215,1593249690,0,411c8b1c,34659377205477379">拉低中奖率</d><d p="133.13100,1,25,16777215,1593250091,0,4b19306d,34659587477471235">我我我我去</d><d p="132.17900,1,25,16777215,1593250231,0,d7f5cc84,34659660665454595">拉低中奖率</d><d p="114.58000,1,25,16777215,1593250464,0,22f56606,34659782817218563">我想要</d><d p="152.80300,1,25,16777215,1593250686,0,c7848db8,34659899476541447">拉低</d><d p="113.89900,1,25,16777215,1593250842,0,3d0d9801,34659980925206531">拉低中奖率</d><d p="136.22000,1,25,16777215,1593250999,0,72b292f5,34660063161876485">可可爱爱</d><d p="156.42000,1,25,16777215,1593251024,0,72b292f5,34660076554813445">蕾姆！</d><d p="164.81900,1,25,16777215,1593251331,0,e0cc78fe,34660237233356807">我全都要</d><d p="93.65800,1,25,16777215,1593251822,0,6386e9c,34660494861664263">我来</d><d p="97.06500,1,25,16777215,1593251882,0,246ff6cb,34660526275952645">我要</d><d p="118.50600,1,25,16777215,1593251945,0,ada75b65,34660559433498627">手办手办！</d><d p="54.82500,4,25,16777215,1593252153,0,836a6a8d,34660668376350725">哈哈哈哈</d><d p="109.34600,1,25,16777215,1593252484,0,b329644a,34660841797189635">我我我我我我我我我我我我</d><d p="40.86000,1,25,16777215,1593252596,0,23b3bdb6,34660900627546119">哈哈哈哈哈哈哈哈哈哈哈哈不亏是你</d><d p="58.62000,1,25,16777215,1593252618,0,23b3bdb6,34660912269361155">小王和八蛋</d><d p="45.27800,1,25,16777215,1593252920,0,e18e03c7,34661070344814599">哈哈哈哈哈个</d><d p="251.82000,1,25,16777215,1593253146,0,bd4b4078,34661189142183941">哈哈哈哈哈哈</d><d p="300.00500,1,25,16777215,1593253899,0,68b16e4c,34661583860269059">肯定有我冲冲冲</d><d p="140.57900,1,25,16777215,1593254290,0,2225d1e5,34661788790816775">拉低中奖率</d><d p="149.26700,1,25,16777215,1593254668,0,1f923807,34661987082305543">看看就好了</d><d p="96.43600,1,25,16777215,1593255145,0,ed859fed,34662237283549187">a</d><d p="101.58600,1,25,16777215,1593255151,0,ed859fed,34662240255737861">aa</d><d p="108.81900,1,25,16777215,1593255158,0,ed859fed,34662244085661701">aaa</d><d p="113.75100,1,25,16777215,1593255172,0,dc63f6d2,34662251284660295">是我的了</d><d p="143.75100,1,25,16777215,1593255202,0,dc63f6d2,34662266786283523">我就收下了</d><d p="168.53600,1,25,16777215,1593255218,0,ed859fed,34662275416064003">aop</d><d p="175.39500,1,25,16777215,1593255225,0,ed859fed,34662279083458563">ooooo</d><d p="167.25100,1,25,16777215,1593255225,0,dc63f6d2,34662279204044807">看来是我了</d><d p="254.25100,1,25,16777215,1593255312,0,dc63f6d2,34662324723253253">你们已经没机会了</d><d p="138.79300,1,25,16777215,1593255325,0,946dcfeb,34662331590901765">好厉害</d><d p="258.82000,1,25,16777215,1593255501,0,39f6d5ac,34662423715119107">呵呵哈哈哈</d><d p="107.24000,1,25,16777215,1593256163,0,f69ebfd6,34662770603982853">拉低中奖率</d><d p="201.53000,1,25,16777215,1593256235,0,2113e8d2,34662808483266565">我2222222</d><d p="213.33800,1,25,16777215,1593256247,0,2113e8d2,34662814675107845">啊啊啊啊啊啊啊啊啊啊啊好的美</d><d p="246.29700,1,25,16777215,1593256280,0,2113e8d2,34662831947251719">嗷嗷嗷嗷嗷嗷嗷嗷嗷嗷嗷</d><d p="253.40000,1,25,16777215,1593256287,0,2113e8d2,34662835690143749">哈哈哈哈哈哈哈</d><d p="274.44600,1,25,16777215,1593256308,0,2113e8d2,34662846707531783">啊啊啊啊啊啊啊啊啊啊啊啊啊啊啊啊啊啊啊啊啊啊啊啊啊啊啊啊啊啊啊啊啊啊啊啊啊啊啊啊啊啊啊啊啊啊啊啊啊啊啊啊</d><d p="289.86500,1,25,16777215,1593256722,0,2e4ecfb3,34663063633788933">来了来了来了</d><d p="206.19900,1,25,16777215,1593257057,0,cc80f231,34663239732690949">啊啊啊啊啊啊鬼灭之刃</d><d p="55.02800,1,25,16777215,1593257118,0,65a81b92,34663271347781637">重在参与~~~~~</d><d p="83.76000,1,25,16777215,1593257399,0,e4d2aaa0,34663418729332739">拉低中奖率</d><d p="96.26000,1,25,16777215,1593257411,0,e4d2aaa0,34663425242562567">冲冲冲</d><d p="110.99600,1,25,16777215,1593257432,0,e4d2aaa0,34663435978932231">谢谢</d><d p="188.90600,1,25,16777215,1593257455,0,d38e6f6d,34663448017633283">拉低中奖率</d><d p="167.74200,1,25,16777215,1593257493,0,e4d2aaa0,34663467896537095">哇哇哇</d><d p="198.80400,1,25,16777215,1593257528,0,e4d2aaa0,34663486533402631">排面啊</d><d p="89.43600,1,25,16777215,1593257568,0,db82725c,34663507523796999">秋梨膏 给我整一个</d><d p="129.38800,1,25,16777215,1593257632,0,db82725c,34663541042053127">啊~！wsl</d><d p="174.31100,1,25,16777215,1593257677,0,db82725c,34663564580487173">我可以~</d><d p="103.50400,1,25,16777215,1593257758,0,7388d20,34663606786719749">来了来阿里</d><d p="131.34500,1,25,16777215,1593257785,0,7388d20,34663621385519107">非洲人前来偷渡。</d><d p="312.21700,1,25,16777215,1593257789,0,c3e12dd9,34663623300743171">中中中</d><d p="92.56400,1,25,16777215,1593257828,0,efb06f4b,34663643991244805">哦豁</d><d p="30.99400,1,25,6830715,1593257854,0,4ce57d63,34663657549332487">睡一起的吗</d><d p="118.42000,1,25,16777215,1593257860,0,efb06f4b,34663660508413957">抽我抽我</d><d p="133.60900,1,25,16777215,1593257906,0,3f45b28f,34663684472045571">我我我</d><d p="214.89900,1,25,16777215,1593257969,0,5be226d3,34663717742313475">我可以</d><d p="259.66000,1,25,16777215,1593258029,0,3a2a6a01,34663749203787783">抽我！！</d><d p="101.55400,1,25,16777215,1593258040,0,3a8884c0,34663755184865287">拉低中奖率</d><d p="129.84800,1,25,16777215,1593258184,0,466c975c,34663830263431173">拉低中奖率</d><d p="135.37600,1,25,16777215,1593258428,0,8f298c02,34663958498508807">拉低中奖率</d><d p="169.92500,1,25,41194,1593258469,0,3fafe86f,34663980004278279">拉低中奖率</d><d p="125.55500,1,25,16777215,1593258503,0,2b733ba1,34663997614063621">丑萌</d><d p="143.51000,1,25,16777215,1593259395,0,c0998713,34664465145790469">许愿</d><d p="180.57900,1,25,16777215,1593259617,0,b387dae8,34664581732761607">我的</d><d p="117.09900,1,25,16777215,1593259631,0,51903124,34664589177651207">拉低中奖率</d><d p="147.15700,5,25,16646914,1593259978,0,581d4f27,34664771206774791">拉低中奖率</d><d p="180.01100,1,25,16777215,1593260271,0,f8c11b27,34664924748185605">想要</d><d p="220.93200,1,25,16777215,1593260289,0,9b20fea1,34664934220496903">靓仔看我！</d><d p="126.09900,1,25,16777215,1593260604,0,dc43824d,34665099156783107">拉低中奖率</d><d p="24.21200,1,25,16777215,1593260636,0,dd3c8bc9,34665116044623877">拉低中奖率</d><d p="163.50200,1,25,16777215,1593261140,0,6a03504e,34665380270571527">啊啊啊啊啊啊想要呢</d><d p="214.09800,1,25,16777215,1593261140,0,9c89e2a7,34665380415275011">哇哇哇哇哇</d><d p="212.71900,1,25,16777215,1593261323,0,81ece999,34665476223139845">冲冲冲</d><d p="158.99900,4,25,9599289,1593261543,0,a2cbd420,34665591241965575">拉低中奖率</d><d p="135.99800,1,25,38979,1593261992,0,16111473,34665827090825223">我要</d><d p="65.54500,1,25,16777215,1593262084,0,b22357da,34665875115606023">拉低中奖率</d><d p="32.17200,1,25,16777215,1593262127,0,b698a804,34665897508470791">我爱型男</d><d p="70.21900,1,25,16777215,1593262172,0,b698a804,34665921309573127">我要我要我要</d><d p="56.34900,5,25,16646914,1593262207,0,487ed837,34665939695828995">缸妹和灿姐</d><d p="171.46000,1,25,16777215,1593262307,0,18d73246,34665992181252099">拉低中奖率</d><d p="168.08300,1,25,16777215,1593262689,0,547324b7,34666192193454085">啊啊啊啊，我的我的</d><d p="158.82500,1,25,16777215,1593262701,0,b6b18e9f,34666198833037379">小王和巴蛋最帅</d><d p="209.72600,4,25,14811775,1593262812,0,547324b7,34666256783638531">我的我的我的</d><d p="93.66000,1,25,16777215,1593262904,0,b892cdd2,34666305185382405">666</d><d p="100.89900,1,25,16777215,1593262917,0,b892cdd2,34666311898365959">666666</d><d p="162.14000,1,25,16777215,1593262984,0,b892cdd2,34666346701127685">蕾姆</d><d p="122.15500,1,25,16777215,1593263120,0,ae547b30,34666418221350915">缸灿最帅</d><d p="21.44800,1,25,16777215,1593263366,0,a3d832bc,34666547277463623">拉低中奖率</d><d p="124.52000,1,25,16777215,1593263378,0,60fd1e1,34666553300484167">啊啊啊啊啊我喜欢</d><d p="126.34000,1,25,16777215,1593263383,0,60fd1e1,34666556248031237">啊啊啊啊啊啊啊啊啊</d><d p="128.10000,1,25,16777215,1593263388,0,60fd1e1,34666558878908421">我可以</d><d p="101.40800,1,25,16777215,1593264276,0,29dc082a,34667024242180101">？</d><d p="115.42500,1,25,16777215,1593264738,0,c12e241b,34667266685534213">要要</d><d p="212.31000,1,25,16777215,1593264823,0,c12e241b,34667311192342535">这个</d><d p="102.69400,1,25,16777215,1593264885,0,15967179,34667343756394499">我我我我我我</d><d p="213.48400,1,25,16777215,1593265073,0,15967179,34667442155814915">啊啊啊啊啊啊啊啊啊啊啊啊啊！</d><d p="232.17900,1,25,16777215,1593265092,0,15967179,34667451960000517">好想拥有!</d><d p="129.23600,1,25,16777215,1593265483,0,8b7887a8,34667656947695621">拉低中奖率！！！！！！！！！！！！！！！！！！！！！！</d><d p="168.16500,1,25,16777215,1593265584,0,8b7887a8,34667710361108487">选我选我！</d><d p="179.99000,1,25,16777215,1593265596,0,8b7887a8,34667716535123971">拉低中奖率！！！！</d><d p="289.63400,1,25,16777215,1593265754,0,74404c45,34667799154524163">11</d><d p="93.21900,1,25,16777215,1593265868,0,5c869832,34667858917588997">想要</d><d p="40.51000,1,25,16777215,1593265937,0,8746f9d1,34667895242883079">哈哈哈</d><d p="161.42800,1,25,16777215,1593266380,0,7b850cb,34668127539691525">想要！</d><d p="121.52000,1,25,16777215,1593266819,0,264c89c8,34668357643403267">拉低中奖率</d><d p="64.89900,1,25,16777215,1593267093,0,388cd8f7,34668501412085765">拉低中奖率</d><d p="73.07600,1,25,16777215,1593267187,0,43f8522f,34668550539968519">拉低中奖率</d><d p="93.69200,1,25,52480,1593267208,0,43f8522f,34668561369137157">拉低中奖率</d><d p="136.05900,1,25,52480,1593267250,0,43f8522f,34668583562248199">想要</d><d p="205.15500,1,18,52480,1593267319,0,43f8522f,34668619797364741">想要</d><d p="304.70100,1,25,16646914,1593267593,0,8eff3a73,34668763212152839">拉低中奖率</d><d p="310.46500,1,25,16740868,1593267598,0,8eff3a73,34668766225235973">拉低中奖率</d><d p="316.10500,1,25,16755202,1593267604,0,8eff3a73,34668769190084615">拉低中奖率</d><d p="321.76000,1,25,16765698,1593267610,0,8eff3a73,34668772273422339">拉低中奖率</d><d p="92.42900,1,25,16777215,1593268474,0,d0e12fc2,34669225137668101">拉低中奖率！！呜呜</d><d p="122.62400,1,25,16777215,1593268965,0,13070095,34669482579853317">丑</d><d p="142.25100,1,25,16777215,1593268989,0,13070095,34669495082549253">丑</d><d p="305.74000,1,25,16777215,1593269125,0,76830f15,34669566579703815">10w都么得</d><d p="199.34000,1,25,16777215,1593269207,0,af4419cc,34669609686663175">拉低中奖率</d><d p="128.12300,1,25,16777215,1593269261,0,9958779e,34669638012370951">拉低中奖率</d><d p="156.92700,1,25,16777215,1593269290,0,9958779e,34669653079883781">拉低中奖率！</d><d p="66.41600,1,25,16777215,1593269307,0,ecbf7ef7,34669662156881925">小缸和阿灿中中中</d><d p="272.53900,1,25,16777215,1593269536,0,ecbf7ef7,34669781884862467">我我我我我我我</d><d p="63.17900,1,25,16777215,1593269674,0,f5ed78af,34669854573199365">需要</d><d p="190.36100,1,25,16777215,1593269847,0,d421fb73,34669945347375107">啊咧</d><d p="321.34200,1,25,16777215,1593270156,0,e3ea6210,34670106958102533">拉低中奖率</d><d p="253.01400,1,25,16777215,1593270189,0,d0be0704,34670124701057029">哈哈哈哈哈哈</d><d p="98.02000,1,25,16777215,1593270352,0,78c65bca,34670210025783299">拉低中奖率</d><d p="148.23700,1,25,16777215,1593270497,0,cb113d29,34670285700464707">拉低中奖率</d><d p="151.41100,1,25,16777215,1593270574,0,e8b0c829,34670326158196739">拉低中奖率</d><d p="114.64100,1,25,16777215,1593270862,0,f01804a9,34670477426819079">来来</d><d p="122.04400,1,25,16777215,1593270870,0,f01804a9,34670481315987459">我中将拉</d><d p="76.25600,1,25,16777215,1593270950,0,c2baf4c0,34670523483947015">拉低中奖率</d><d p="96.32400,1,25,16777215,1593271318,0,2f3d2231,34670716238430211">我要</d><d p="212.19200,1,25,16777215,1593271345,0,67dc92a6,34670730723983365">想要！！！看我！！</d><d p="127.43800,1,25,16777215,1593271353,0,54d1bdc3,34670734513012739">！！！！我可以！！！</d><d p="296.22900,1,25,16777215,1593271458,0,67dc92a6,34670789687508995">我我我我我我我我我！</d><d p="188.79900,1,25,16777215,1593271476,0,a79b2885,34670799466004483">我可以我可以我可以</d><d p="206.82000,1,25,16777215,1593271500,0,a79b2885,34670811626340357">哇想要</d><d p="94.32800,1,25,16777215,1593271518,0,b468f636,34670821420040199">我要 我要</d><d p="29.75900,1,25,16707842,1593272304,0,4afd2419,34671233198981125">？？？？？</d><d p="302.67600,1,25,16777215,1593272860,0,a1c03baa,34671525022924803">拉低中奖率！！！</d><d p="164.69200,1,25,16777215,1593272929,0,688830e1,34671561057763335">拉低中奖率</d><d p="147.30000,1,25,16777215,1593273024,0,1270244a,34671610753449989">所以这么厉害要怎么才能拥有呢？</d><d p="225.33900,1,25,16777215,1593273215,0,b1030f97,34671711241109511">芜湖！！！？</d><d p="150.38000,1,25,16777215,1593273718,0,69b3ffe,34671974601981959">我也想要</d><d p="55.98000,1,25,16777215,1593274261,0,b6ab0a05,34672259509518339">拉低中奖率</d><d p="78.93200,1,25,16777215,1593274419,0,e914171b,34672342124199943">拉低中奖率</d><d p="272.43800,1,25,16777215,1593274907,0,853ff72,34672598146613253">我要了也没用</d><d p="114.06800,1,25,16777215,1593275940,0,b5ccf9b1,34673139396902917">抽</d><d p="141.54600,1,25,16777215,1593275972,0,b5ccf9b1,34673156475584519">抽</d><d p="149.51900,1,25,16777215,1593276752,0,23601eaa,34673565205266439">那就不好意思收下了</d><d p="25.59900,1,25,16777215,1593278512,0,1191589d,34674488144035843">冲冲冲</d><d p="189.46000,1,25,16777215,1593278657,0,2da145be,34674564028956675">给我也整一个</d><d p="73.30000,1,25,16777215,1593279322,0,5914c3f7,34674912952582149">拉低中奖率</d><d p="79.22000,1,25,38979,1593279338,0,5914c3f7,34674921269886983">拉低中奖率</d><d p="156.21900,1,25,38979,1593279419,0,5914c3f7,34674963801178119">拉低中奖率</d><d p="162.14000,1,25,38979,1593279454,0,5914c3f7,34674981896978437">中奖我就就全部三连</d><d p="182.05900,1,25,38979,1593279477,0,5914c3f7,34674994133336069">拉低中奖率</d><d p="189.29900,1,25,38979,1593279498,0,5914c3f7,34675005295427587">中奖＝三连</d><d p="88.93600,1,25,16777215,1593279682,0,b054fe9c,34675101716709379">拉低中奖率</d><d p="209.15200,1,25,16777215,1593279696,0,4442c179,34675108714381315">！！！！</d><d p="127.78000,1,25,16777215,1593280386,0,63895d1a,34675470434304003">拉低中奖率</d><d p="115.65900,1,25,16777215,1593281682,0,29881930,34676149887959043">抽奖？</d><d p="83.70000,1,25,16777215,1593282253,0,95e26aea,34676449500200963">拉低</d><d p="77.66000,1,25,16777215,1593282393,0,8fe9611,34676522942988293">想要</d><d p="45.37400,1,25,16777215,1593282521,0,5dd95366,34676589940703237">拉低就完事</d><d p="105.52600,1,25,16777215,1593283567,0,d8854277,34677138617532421">111</d><d p="54.09900,1,25,16777215,1593283851,0,6447b5a7,34677287421476871">排面</d><d p="314.69100,1,25,16777215,1593285881,0,f5047f6c,34678351607627781">我要！！！！！！！！！！！！！！！！！</d><d p="308.09900,1,25,16777215,1593289550,0,4da4cb52,34680275040993287">白嫖好</d><d p="223.51200,1,25,16777215,1593289924,0,ee95c4c8,34680471397859331">我想要！！！！！</d><d p="97.68000,1,25,16777215,1593295634,0,3234b761,34683464839069699">我我我，万一中了呢，嘿嘿</d><d p="287.42000,1,25,16777215,1593295834,0,3234b761,34683570069438467">我要三我要三</d><d p="35.94000,1,25,16777215,1593296843,0,d50d2470,34684098909831175">笑死我了</d><d p="60.22000,1,25,16777215,1593296870,0,d50d2470,34684113075044357">兔兔！！</d><d p="122.33900,1,25,16777215,1593296943,0,d50d2470,34684151476518917">再贩fan吧……</d><d p="64.94500,1,25,16777215,1593298925,0,cf2da16d,34685190558711811">万一</d><d p="288.87100,1,25,16777215,1593302191,0,8a7b1fb6,34686902812540935">不可能抽到我</d><d p="67.18000,1,25,16777215,1593302534,0,db75912f,34687082372268037">我也已要</d><d p="9.96700,1,25,16777215,1593302545,0,c19a702a,34687088124755975">更想考上</d><d p="278.05900,1,25,16777215,1593302838,0,d7834f68,34687241829744643">拉          低              中                 奖                率  </d><d p="67.62700,1,25,16777215,1593303563,0,848a7582,34687621826347013">我要一个惊喜</d><d p="69.50800,1,25,16777215,1593303582,0,848a7582,34687631885336583">我要一个就行</d><d p="124.80000,1,25,16777215,1593305554,0,75ce4e67,34688665686900739">我来拉低中奖率了</d><d p="149.66100,1,25,16777215,1593306776,0,5169f662,34689306593853443">拉低中奖率</d><d p="186.49900,1,25,16777215,1593308025,0,26114b4f,34689961295872007">233</d><d p="96.13900,1,25,16777215,1593309349,0,3f2630b8,34690655672860679">想要</d><d p="94.85900,1,25,16777215,1593309444,0,48754a0a,34690705652187143">给我整一个</d><d p="79.03900,1,25,16777215,1593310207,0,7aafdf8c,34691105648279559">拉低中奖率</d><d p="276.80800,1,25,16777215,1593310303,0,3fa94f23,34691156006666243">我我我想中奖</d><d p="212.96500,1,25,16777215,1593310330,0,46cb24ae,34691170121023491">拉低</d><d p="74.91300,1,25,16777215,1593312409,0,63a8c51f,34692260105289731">o h h h h h h h h h h h h h h</d><d p="164.67500,1,25,16777215,1593312535,0,63a8c51f,34692326145654791">ohhhhhhhh</d><d p="203.46100,1,25,16777215,1593313138,0,9d3971a0,34692642236792835">拉低中奖率</d><d p="283.58000,1,25,16777215,1593313218,0,9d3971a0,34692684292554759">拉低中奖率</d><d p="97.78000,1,25,16777215,1593313228,0,b849f70,34692689303699459">拉低中奖率</d><d p="294.87600,1,25,16777215,1593313230,0,9d3971a0,34692690175066119">拉低中奖率</d><d p="107.29700,1,25,16777215,1593314092,0,819e4de1,34693142543859719">拉低中奖率</d><d p="63.88100,1,25,16777215,1593314238,0,c1d85184,34693218755411973">拉低中奖率</d><d p="12.38100,1,25,16777215,1593316205,0,c3922043,34694250089676807">白嫖？</d><d p="285.01300,1,25,16777215,1593317306,0,d7d4b9d4,34694827104272391">看到这里忍不住了，我要明信片！！！</d><d p="292.94900,1,25,16777215,1593317338,0,d7d4b9d4,34694844361736199">我要我要！</d><d p="293.97300,1,25,16777215,1593317362,0,d7d4b9d4,34694856458108933">请问抽不到的话，哪里可以买到呢</d><d p="302.16500,1,25,16777215,1593317393,0,d7d4b9d4,34694872941723655">明信片明信片明信片！</d><d p="303.10400,1,25,16777215,1593317411,0,d7d4b9d4,34694882487435271">我就要明信片</d><d p="0.76600,5,25,16646914,1593317476,0,51b1800d,34694916471783431">本期BGM已更新至网易云歌单</d><d p="0.76600,1,25,16776960,1593317483,0,51b1800d,34694920170635271">本期BGM已更新至网易云歌单</d><d p="321.25800,1,25,16777215,1593317491,0,d7d4b9d4,34694924388007941">明信片明信片想要明信片！</d><d p="196.37200,1,25,52480,1593317496,0,51b1800d,34694927022030853">本期BGM已更新至网易云歌单</d><d p="197.60400,4,25,16776960,1593317506,0,51b1800d,34694932355088391">本期BGM已更新至网易云歌单</d><d p="307.35900,5,25,16646914,1593317541,0,51b1800d,34694950793248775">本期BGM已更新至网易云歌单~</d><d p="8.69100,1,25,16777215,1593317695,0,9db03eb5,34695031343808517">中奖</d><d p="291.09900,1,25,16777215,1593317777,0,df3ee77a,34695074038677509">好不要脸的，他们两个老是偷东西。</d><d p="95.21200,1,25,16777215,1593317782,0,9db03eb5,34695076704157699">字幕呢</d><d p="141.67900,1,25,4351678,1593317828,0,9db03eb5,34695101061005319">水电费法国队死哦</d><d p="60.05900,1,25,16777215,1593317874,0,42db1d5e,34695124926595077">fufu！</d><d p="67.05900,1,25,16777215,1593317885,0,42db1d5e,34695130890371077">拉低中奖率</d><d p="195.77900,1,25,16777215,1593318026,0,42db1d5e,34695204979081219">排面！</d><d p="170.24000,1,25,16777215,1593318115,0,b5d59b25,34695251277381635">拉低中奖率 我可以</d><d p="143.98000,1,25,16777215,1593318124,0,2c85cf2a,34695255974477827">缸好帅啊</d><d p="217.05600,1,25,16777215,1593318161,0,b5d59b25,34695275822448643">这个我可以</d><d p="291.79600,1,25,16777215,1593318437,0,c8219c7d,34695420425797639">我要一个</d><d p="151.33700,1,25,16777215,1593318438,0,e3a38d01,34695420605104131">我我我我可</d><d p="123.84000,1,25,16777215,1593318450,0,31549e7e,34695426890268677">我想要</d><d p="130.23900,1,25,14811775,1593318479,0,31549e7e,34695442157010951">给我吧</d><d p="36.70000,1,25,16777215,1593318873,0,f42f9eb4,34695648864894983">万一中了呢？</d><d p="70.66000,1,25,16777215,1593318984,0,f42f9eb4,34695707087077383">拉低中奖率</d><d p="73.69900,1,25,16777215,1593318992,0,f42f9eb4,34695711294488583">康康我</d><d p="120.41900,1,25,16777215,1593319041,0,f42f9eb4,34695737143984131">选我</d><d p="138.65900,1,25,16777215,1593319119,0,5fd87bcf,34695777806188547">我要</d><d p="290.76000,1,25,16777215,1593319629,0,40642375,34696045403308035">冲冲冲</d><d p="118.82000,1,25,16777215,1593320212,0,e723d9ee,34696350787960839">拉低中奖率</d><d p="317.46000,1,25,16777215,1593320259,0,3f105459,34696375550607365">爱了爱了</d><d p="115.35900,1,25,16777215,1593320672,0,21f1d28f,34696591860301829">啊啊啊啊好可爱</d><d p="153.07500,1,25,16777215,1593320710,0,21f1d28f,34696612092575747">害，真可爱</d><d p="203.28000,1,25,52479,1593320762,0,9a1be1a4,34696639423709189">啊啊啊啊啊啊啊啊啊啊啊啊啊啊啊啊啊啊啊啊啊啊</d><d p="227.89100,1,25,16777215,1593320785,0,21f1d28f,34696651302502407">！！！！！拉低</d><d p="130.60700,1,25,16777215,1593321229,0,cbc52d0,34696884220067845">拉低中奖率</d><d p="70.58000,1,25,16777215,1593321472,0,d671c68,34697011463716867">我来惹</d><d p="155.66000,1,25,16777215,1593321561,0,d671c68,34697058372288517">想要！！！</d><d p="147.27900,1,25,16777215,1593322350,0,e815d085,34697471895535623">拉低中奖率</d><d p="73.41900,1,25,16777215,1593322520,0,98c5ced5,34697561252036615">我要</d><d p="118.25900,1,25,16777215,1593322577,0,98c5ced5,34697591063052291">我要</d><d p="200.54000,1,25,16777215,1593322663,0,98c5ced5,34697635999252485">排面</d><d p="208.34400,1,25,16777215,1593323655,0,ce1c5fc4,34698156351422471">啊啊啊啊啊啊啊啊啊啊啊啊啊啊啊啊啊啊啊啊啊啊啊啊啊啊啊啊啊啊啊啊啊啊啊啊啊啊</d><d p="215.89600,1,25,16777215,1593323671,0,ce1c5fc4,34698164551286789">我要欧起来</d><d p="238.97800,1,25,16777215,1593323713,0,ce1c5fc4,34698186404659203">虽然我看完了</d><d p="30.92600,1,25,16777215,1593324466,0,71f04bbb,34698581307293701">拉低</d><d p="143.76300,1,25,16777215,1593324579,0,71f04bbb,34698640402939911">我想要！！！</d><d p="44.79600,1,25,16777215,1593325086,0,8bdc0c6,34698906474381319">拉低中奖率</d><d p="124.85000,1,25,16777215,1593325281,0,d6a7b0f2,34699008713162755">试试手气</d><d p="112.29900,1,25,16777215,1593327824,0,ab19f8e8,34700341960245255">我全都要</d><d p="114.46000,1,25,16777215,1593327835,0,ab19f8e8,34700347735277571">我来领奖了</d><d p="204.45900,1,25,16777215,1593327972,0,ab19f8e8,34700419155361799">想要</d><d p="292.12000,5,25,15138834,1593328261,0,74b710d0,34700571145404421">我要我要我要我要我要我要我要我要我要我要我要我要我要我要</d><d p="211.59400,1,25,16777215,1593328752,0,9ac149dc,34700828391505923">我想要！！！！！！！</d><d p="217.29000,1,25,16777215,1593328759,0,9ac149dc,34700832055754759">啊啊啊啊</d><d p="113.19600,1,25,16777215,1593329383,0,486411b6,34701159299022855">拉低</d><d p="122.77600,1,25,16777215,1593329397,0,486411b6,34701166384775175">拉低</d><d p="74.83700,1,25,16777215,1593329453,0,87f4308e,34701195853430789">没错，就是我的</d><d p="207.37500,1,25,16777215,1593329487,0,486411b6,34701213621551111">这个牛！！！</d><d p="17.29900,1,25,16777215,1593329518,0,8fd8d4a6,34701230164934659">哈哈哈哈哈</d><d p="75.87500,1,25,16777215,1593330612,0,a0e8fc14,34701803321294855">拉低中奖率</d><d p="160.81900,1,25,16777215,1593330704,0,a0e8fc14,34701851826847751">拉低中奖率</d><d p="137.27800,1,25,16777215,1593330916,0,8c0efdcd,34701962722148355">我来组成分母</d><d p="290.86800,1,25,16777215,1593331070,0,f8dd55ed,34702043701575683">积极</d><d p="123.32200,1,25,16777215,1593331560,0,d5830ee,34702300808740869">嘿嘿</d><d p="101.54600,1,25,16777215,1593332300,0,2f4d3a5b,34702688409092101">芜湖</d><d p="143.21300,1,25,16777215,1593332630,0,9cc45ee2,34702861281001477">抽</d><d p="78.22700,1,25,16777215,1593332700,0,817ac213,34702898494963719">错过了吗</d><d p="70.66000,1,25,16777215,1593332705,0,3242bb8d,34702900777189381">加油丫</d><d p="307.31200,1,25,16777215,1593333584,0,818b43d1,34703361968177157">哇哇哇！！！！</d><d p="132.24300,1,25,16777215,1593333937,0,364032d0,34703546572603395">好像要！！</d><d p="128.58800,1,25,16777215,1593334597,0,3200c1fe,34703892640432131">拉低中奖率</d><d p="114.07100,1,25,16777215,1593334815,0,a24d5cec,34704007246643203">我我哦我我哦</d><d p="12.37600,1,25,16777215,1593335606,0,17660a73,34704421692112903">美丽黑眼圈</d><d p="123.05900,1,25,16777215,1593335661,0,84eaa66,34704450845147139">背了多久啊这是</d><d p="198.07800,1,25,16777215,1593336946,0,2a0b2c1f,34705124405280771">我我我我我！！！</d><d p="282.59800,1,25,16777215,1593337037,0,2a0b2c1f,34705172033699843">我要明信片哈哈哈哈哈哈哈哈哈哈哈哈哈哈哈哈哈哈哈哈哈哈哈哈哈哈哈哈哈哈哈哈哈哈哈哈哈哈哈哈</d><d p="174.15600,1,25,15138834,1593337140,0,225c633f,34705226232496133">我的我的我的</d><d p="126.82900,1,25,16777215,1593337197,0,591d6d48,34705255788707843">1111</d><d p="281.68400,1,25,16777215,1593337241,0,591d6d48,34705278837981187">11111</d><d p="97.49900,1,25,16777215,1593337759,0,90b4bfaa,34705550757855239">拉低中奖率。</d><d p="75.55800,1,25,16777215,1593340256,0,fd6d793c,34706859522785351">拉低拉低</d><d p="71.08400,1,25,16777215,1593340308,0,74c594b5,34706886931513349">拉低中奖率</d><d p="48.83100,1,25,16777215,1593340325,0,16beae2f,34706895807709189">小王和八蛋</d><d p="26.26000,1,25,16777215,1593340353,0,b6641583,34706910505598981">1</d><d p="166.82000,1,25,16777215,1593340394,0,2f72dc7d,34706931882393607">很喜欢</d><d p="214.19900,1,25,16777215,1593340569,0,1c311244,34707023800041475">芜湖</d><d p="261.60800,1,25,16777215,1593340597,0,b6641583,34707038688772099">吵死了！哈哈哈哈无路赛！</d><d p="96.29900,1,25,16777215,1593340710,0,655d6993,34707097526992901">拉低中奖率</d><d p="36.54000,1,25,16777215,1593341017,0,669564a1,34707258526924807">233333</d><d p="35.43000,1,25,16777215,1593341088,0,4486d4c9,34707296146161671">哈哈哈哈哈哈哈</d><d p="65.17100,1,25,16777215,1593341120,0,4486d4c9,34707312971612165">来了来了</d><d p="72.93400,1,25,16777215,1593341136,0,4486d4c9,34707321165185027">来了</d><d p="91.83800,1,25,16777215,1593341161,0,4486d4c9,34707334322716679">拉低中奖率</d><d p="157.58500,1,25,16777215,1593341230,0,4486d4c9,34707370354933763">艾米莉亚</d><d p="208.78600,1,25,16777215,1593341287,0,4486d4c9,34707400087830533">啊啊啊啊啊啊啊啊</d><d p="261.65300,1,25,16777215,1593341332,0,4486d4c9,34707423835455493">哈哈哈哈哈哈哈哈</d><d p="157.89900,1,25,16777215,1593341678,0,bbd7b57c,34707605043544067">可还行</d><d p="168.40900,1,25,16777215,1593341785,0,ccddca0d,34707661543440389">三个老婆</d><d p="134.11800,1,25,15138834,1593341796,0,574c0792,34707667248218119">我来拉低中奖率！！！！！</d><d p="38.25600,1,25,16777215,1593342713,0,be686db1,34708147739295747">中奖绝缘体</d><d p="107.15500,1,25,16777215,1593343032,0,aa680cf0,34708315259273223">可可爱爱 想要 想要</d><d p="108.52100,1,25,16777215,1593343248,0,1fd02525,34708428544278533">拉低中奖率</d><d p="97.43600,1,25,16777215,1593344452,0,4aa1a7dd,34709059428417541">666</d><d p="102.67500,1,25,16777215,1593344475,0,4aa1a7dd,34709071617589253">冲冲冲</d><d p="154.51500,1,25,16777215,1593344994,0,5e0141fc,34709343627640835">i了</d><d p="155.66600,1,25,16777215,1593345295,0,4f02b7d0,34709501799038983">拉低中奖率</d><d p="94.89900,1,25,16777215,1593345627,0,6e9fea11,34709675578490885">拉低中奖率</d><d p="182.94200,1,25,16777215,1593345793,0,3993fdc2,34709762878734339">好可爱</d><d p="184.90200,1,25,16777215,1593345815,0,3993fdc2,34709774221705221">我想要想要想要</d><d p="35.98600,1,25,16777215,1593346322,0,bc5e3f67,34710040235999239">啊这</d><d p="122.58200,1,25,16777215,1593346378,0,bc5e3f67,34710069708324867">我要</d><d p="106.49900,1,25,16777215,1593347578,0,c72ab52f,34710698428203013">拉低！！！！非酋路过！！！！</d><d p="199.95700,1,25,16777215,1593348977,0,41c2eb1c,34711431971602435">拉低中奖率</d><d p="113.55500,1,25,16777215,1593349165,0,7df9d11,34711530412965893">啊</d><d p="152.61900,1,25,16777215,1593349414,0,ec3c1a23,34711661389021187">拉低中奖率</d><d p="54.17900,1,25,16777215,1593349421,0,df92e5c6,34711664683122691">哈哈哈哈哈哈哈哈哈哈哈哈哈哈哈哈哈</d><d p="161.10000,1,25,16777215,1593349532,0,df92e5c6,34711723064164357">我我我我我我</d><d p="114.54500,1,25,16777215,1593349612,0,9b554e8,34711765216395269">老分母了</d><d p="154.92800,1,25,16777215,1593349966,0,17d96dc5,34711950572650499">拉低中奖率</d><d p="161.83400,1,25,16777215,1593350025,0,1c649712,34711981539721223">哈哈哈哈哈哈</d><d p="314.77200,1,25,16777215,1593350155,0,72db60b7,34712049894293511">？</d><d p="68.28200,1,25,16777215,1593350542,0,c0e751fd,34712252558344195">抽奖</d><d p="35.73200,1,25,16777215,1593350910,0,afbe2648,34712445711810563">我发现了什么</d><d p="185.20000,1,25,16777215,1593351568,0,78595438,34712790395518979">不行  我要这个兔兔 </d><d p="76.86300,1,25,16777215,1593351805,0,de9baddb,34712914735136837">先手谢谢、</d><d p="114.53900,1,25,16777215,1593351812,0,d0a2dd02,34712918219554819">拉低中奖率</d><d p="77.99500,1,25,16777215,1593351884,0,24eb469,34712956369371143">来了来了</d><d p="156.85500,1,25,16777215,1593351963,0,24eb469,34712997756665859">好可爱！！！！</d><d p="175.08100,1,25,16777215,1593353233,0,24355a9b,34713663600852997">拉低中奖率</d><d p="19.30700,1,25,16777215,1593353530,0,5c20f9d8,34713819067449349">我要中奖</d><d p="290.01900,1,25,16777215,1593353928,0,8348b381,34714027815337991">拉低中奖率</d><d p="298.77900,1,25,16777215,1593353948,0,8348b381,34714038290087943">我不要我不要不要抽中我</d><d p="246.93200,1,25,16777215,1593354505,0,37e768c1,34714330365689859">哈哈哈 </d><d p="175.27200,1,25,16777215,1593355202,0,dcd2da09,34714695847903239">拉低</d><d p="206.18400,1,25,16777215,1593355235,0,dcd2da09,34714712964333573">啊啊啊啊啊啊！</d><d p="292.62100,1,25,16777215,1593355695,0,9be8d517,34714954223845381">我我我我我我我</d><d p="301.77800,1,25,16777215,1593355705,0,9be8d517,34714959293710343">超想要！</d><d p="108.90200,1,25,16777215,1593356038,0,d12bacd1,34715134265393157">我要</d><d p="10.83200,1,25,16777215,1593356185,0,f4edbca5,34715211105042435">可以</d><d p="174.29900,1,25,16777215,1593356562,0,d89ece6d,34715408776298501">拉低中奖率</d><d p="194.45600,1,25,16777215,1593356884,0,5b122dbc,34715577694027781">我我我！</d><d p="247.38000,1,25,16777215,1593356934,0,4af8f183,34715603838173189">我要</d><d p="287.60000,1,25,16777215,1593357783,0,12b65595,34716048967598083">我要三等奖</d><d p="210.35900,1,25,16777215,1593358592,0,bba51e22,34716473290129415">啊啊啊啊啊</d><d p="101.51400,1,25,16777215,1593360594,0,5f0fc9bb,34717522674581511">来了来了</d><d p="114.49500,1,25,16777215,1593361289,0,a9f6ceff,34717887326322693">看看我熬</d><d p="146.15200,1,25,16777215,1593362416,0,794e9fe8,34718477992853511">拉低中奖率</d><d p="5.48000,1,25,16777215,1593362450,0,1e46b0d7,34718495851675651">小恰和阿饭</d><d p="16.18000,1,25,16777215,1593362946,0,379b4d3a,34718756071014405">中中中</d><d p="296.69000,1,25,16777215,1593363985,0,17b20fbd,34719300804149253">我要明信片！！！</d><d p="321.81300,1,25,16777215,1593364635,0,e2c0d01c,34719641630146563">拉低中奖率！！！！！！！！</d><d p="290.31000,1,25,16777215,1593365043,0,ddb28035,34719855098200069">我要</d><d p="117.75600,1,25,16777215,1593365238,0,22bc3bc1,34719957362671623">中</d><d p="130.78900,1,25,16777215,1593365250,0,22bc3bc1,34719963949826053">抽奖必中</d><d p="168.14800,1,25,16777215,1593365288,0,22bc3bc1,34719983545090055">来了</d><d p="80.38000,1,25,16777215,1593365799,0,88144e5,34720251776073735">中</d><d p="101.41900,1,25,16777215,1593365825,0,88144e5,34720265211478021">冲鸭</d><d p="97.33900,5,25,15138834,1593366100,0,5656c2d1,34720409423708167">我也来</d><d p="114.03000,1,25,16777215,1593367040,0,e086d27,34720902488784901">拉低中奖率</d><d p="116.75000,1,25,16777215,1593367048,0,e086d27,34720906242686979">是我的</d><d p="173.35000,1,25,16777215,1593367110,0,e086d27,34720938950393859">拉低中奖率</d><d p="76.18000,1,25,16777215,1593370284,0,a17c5522,34722602841276421">全部榨汁</d><d p="101.01200,1,25,16777215,1593378136,0,299a3b03,34726719635587079">我也要</d><d p="305.19000,1,25,16777215,1593382311,0,9ebaf487,34728908513345541">我要我要我要我要我要我要我要我要我要我要我要</d><d p="127.52700,1,25,16777215,1593388333,0,d6e1e76e,34732065921433605">拉低中奖率</d><d p="177.97900,1,25,16777215,1593389977,0,911caa70,34732927908052999">哈哈哈</d><d p="104.17000,1,25,16777215,1593390574,0,653ec977,34733240806801415">抽我</d><d p="110.16200,1,25,16777215,1593395286,0,cbacd90e,34735711523438597">拉低中奖率</d><d p="111.23300,1,25,16777215,1593395989,0,63506329,34736080138797061">拉低中奖率</d><d p="184.46000,1,25,16777215,1593396384,0,b856b047,34736287087853571">拉低中奖率</d><d p="42.96100,1,25,16777215,1593397605,0,9929772e,34736926993940483">我我我我我我！</d><d p="119.57800,1,25,16777215,1593397813,0,3397bb8d,34737036349407237">拉低中奖率</d><d p="123.39700,1,25,16777215,1593398777,0,6ba4a899,34737541383454723">机器人</d><d p="11.76000,1,25,16777215,1593399152,0,1582932d,34737738347446277">我可以</d><d p="28.93100,5,25,41194,1593399273,0,e4553271,34737801583919109">看见阿米兔了</d><d p="103.70200,1,25,16777215,1593402240,0,22c1b711,34739357246554115">我要</d><d p="221.16900,1,25,16777215,1593403222,0,98773bda,34739871977308167">拉就完事了</d><d p="18.73000,1,25,16777215,1593403414,0,56037400,34739972663148551">hhh</d><d p="54.05200,1,25,16777215,1593403463,0,56037400,34739998440292357">哈哈哈哈哈哈哈</d><d p="252.47900,1,25,16777215,1593403748,0,a6deeb3d,34740147971424261">n b</d><d p="80.01900,1,25,16777215,1593404028,0,bf408d03,34740294609534979">冲冲冲</d><d p="3.97900,1,25,16777215,1593404195,0,bf843a7e,34740382049763335">小王和八蛋</d><d p="68.63800,1,25,16777215,1593404642,0,e7c6202a,34740616389197831">我来了</d><d p="127.01700,1,25,16777215,1593406651,0,ea599e9b,34741669883019271">拉低中奖率</d><d p="68.27300,1,25,16777215,1593408445,0,7aa6edcc,34742610280054787">拉低中奖率！！！！</d><d p="96.55000,1,25,16777215,1593409631,0,ab101465,34743232355106819">拉低</d><d p="60.45600,1,25,16777215,1593413572,0,6387b30a,34745298236473349">拉低中奖率</d><d p="157.97900,1,25,16777215,1593414453,0,b9d069a7,34745760476037125">艾米雅丽</d><d p="113.58000,1,25,16777215,1593414638,0,d9f8aa0,34745857554776071">非酋</d><d p="78.48300,1,25,16777215,1593415925,0,2d2ea02,34746532289314823">啦啦啦低中奖率</d><d p="122.17400,1,25,16777215,1593415975,0,2d2ea02,34746558316019717">抽抽抽</d><d p="167.40100,1,25,16777215,1593416029,0,2d2ea02,34746586705690631">全带回家 嘿嘿嘿嘿</d><d p="55.72300,1,25,16777215,1593416912,0,a309161,34747049524592647">啦啦啦啦</d><d p="103.96100,1,25,16777215,1593416960,0,a309161,34747074817294343">啦啦啦啦拉低</d><d p="150.81100,1,25,16777215,1593417007,0,a309161,34747099356069891">要要</d><d p="286.76000,1,25,16777215,1593417396,0,3209d8e3,34747303314587655">我要我要我要</d><d p="51.41900,1,25,16777215,1593419456,0,b2fd10da,34748383328993285">等你才能吃坚持己见</d><d p="209.34000,1,25,16777215,1593420421,0,45ec2b58,34748889180930051">woc</d><d p="214.02100,1,25,16777215,1593420425,0,45ec2b58,34748891656617989">疯了疯了</d><d p="187.05900,1,25,16777215,1593420926,0,bb9ba973,34749154221096967">中奖！</d><d p="77.51100,1,25,16777215,1593421648,0,a685549b,34749532495413251">拉低拉低了</d><d p="189.24000,1,25,16777215,1593421690,0,a685549b,34749554573705221">兔兔我可以</d><d p="36.29300,1,25,16777215,1593422229,0,2fb543ef,34749837477412867">1</d><d p="88.61500,1,25,16777215,1593422487,0,108a938b,34749972668219395">拉低中奖率</d><d p="152.46000,1,25,16777215,1593422714,0,3e171089,34750091408965635">拉低中奖率</d><d p="140.19600,1,25,16777215,1593424090,0,2fbc4e87,34750813135962115">吨吨吨吨吨吨吨吨吨吨</d><d p="127.34100,1,25,16777215,1593424299,0,7166b6ad,34750922396008455">来来来，拉低中奖率</d><d p="97.15700,1,25,16777215,1593425824,0,cd940803,34751722023813123">拉低中奖率</d><d p="182.71900,1,25,16777215,1593426402,0,7da7f6b1,34752024951652355">拉低中奖率</d><d p="54.99800,1,25,16777215,1593426477,0,10d7d06,34752064375488519">选我选我</d><d p="120.50000,1,25,16777215,1593427403,0,f58bc3ef,34752550103678981">可爱啊</d><d p="297.44500,1,25,16777215,1593427429,0,576dc9d0,34752563475120133">来来</d><d p="300.46000,1,25,16777215,1593427978,0,98df1b21,34752851272007687">我已经有了，对吧，阿蛋小王（狗头）</d><d p="154.32100,5,25,16776960,1593430011,0,61473f38,34753917107044357">哈哈哈哈哈哈艾米压力可还行</d><d p="143.14000,1,25,16777215,1593430108,0,126ae579,34753967824568325">包邮吗</d><d p="130.26700,1,25,16777215,1593430888,0,6b1f7dd2,34754377071198211">都是我的</d><d p="166.82900,1,25,16777215,1593431406,0,416a3f28,34754648710053891">中</d><d p="150.82700,1,25,16777215,1593434379,0,70da90e3,34756207542534151">拉低中奖率</d><d p="124.63200,1,25,16777215,1593434678,0,c9f54f21,34756363856904195">拉低中奖率</d><d p="168.05900,1,25,16777215,1593436614,0,197c8d84,34757379306815491">我非酋</d><d p="31.23000,1,25,16777215,1593436827,0,d5727a8f,34757490893651971">万一是我呢</d><d p="113.72600,1,25,16777215,1593437427,0,37b5542b,34757805200113669">拉低中奖率</d><d p="290.76400,1,25,16777215,1593437816,0,fbf42f9d,34758009116688391">哈哈哈哈哈哈哈哈</d><d p="140.21600,1,25,16777215,1593438012,0,abb0ee55,34758112055918597">拉低中奖概率</d><d p="114.11300,1,25,16777215,1593438685,0,7491643d,34758464893353991">我全都要</d><d p="63.77600,1,25,16777215,1593438992,0,d292c3f1,34758626081505285">公主殿下！</d><d p="97.38000,1,25,16777215,1593439987,0,455b235f,34759147408850949">怎么个送法</d><d p="72.82000,1,25,16777215,1593440024,0,3a7c2fbc,34759166841061379">拉低中奖率</d><d p="164.45900,1,25,16777215,1593442295,0,a535053c,34760357404737543">我我我哈哈</d><d p="128.42300,1,25,16777215,1593442651,0,aedbb3d0,34760544131481603">拉低中奖率</d><d p="271.93400,1,25,16777215,1593444238,0,4b94943e,34761376094748679">？！</d><d p="27.64800,1,25,16777215,1593445254,0,9864dadd,34761909150416901">拉低中奖率</d><d p="124.73400,1,25,16777215,1593446598,0,13ff86f8,34762613394505731">阿巴阿巴</d><d p="27.68600,1,25,16777215,1593446707,0,9010c211,34762670883733511">靠</d><d p="35.24900,1,25,16777215,1593446715,0,9010c211,34762674850496519">白嫖</d><d p="44.12900,1,25,16777215,1593446724,0,9010c211,34762679529242629">拉低</d><d p="53.44800,1,25,16777215,1593446733,0,9010c211,34762684402499589">哈哈哈啊哈哈哈哈</d><d p="73.40200,1,25,16777215,1593446753,0,9010c211,34762694870433795">小王和八蛋</d><d p="56.42800,5,25,38979,1593446790,0,9010c211,34762714481950725">小王和八蛋</d><d p="20.06000,1,25,16777215,1593446972,0,4b113e56,34762809625018373">冲冲冲rushb</d><d p="66.62300,1,25,16777215,1593448596,0,6cb33a8,34763661226016775">拉低中奖率</d><d p="95.82000,1,25,16777215,1593449789,0,26536507,34764286388600835">拉低中奖率</d><d p="108.48000,1,25,16777215,1593449805,0,26536507,34764294935543811">拉低中奖率</d><d p="157.10000,1,25,16777215,1593449911,0,26536507,34764350541529095">不想只做分母</d><d p="174.01900,1,25,16777215,1593450514,0,4f8d2113,34764666820362245">啊！！！！！！！！我要我要我要我要我要</d><d p="181.94000,1,25,16777215,1593450528,0,4f8d2113,34764673992097797">三等奖</d><d p="105.84300,1,25,16777215,1593451056,0,1e09ca52,34764950828220421">呃</d><d p="168.47800,1,25,16777215,1593451698,0,61a74f24,34765287260684293">拉低冲冲冲</d><d p="194.27600,1,25,16777215,1593452326,0,6a93e839,34765616618930181">我的</d><d p="211.46000,1,25,16777215,1593452588,0,5c82eba,34765753881722887">ohhhhhh</d><d p="296.40100,1,25,16777215,1593452673,0,5c82eba,34765798400589829">冲鸭</d><d p="190.73500,1,25,16777215,1593460254,0,203b0cc5,34769773196738563">降低中奖率，小肛和阿灿冲冲冲</d><d p="204.60300,1,25,16777215,1593460268,0,203b0cc5,34769780467564547">冲冲冲</d><d p="4.08100,1,25,16777215,1593464995,0,557cf6ff,34772259110387717">这期恰饭吗？</d><d p="171.62000,1,25,16777215,1593465346,0,57720849,34772443048443911">拉</d><d p="186.51500,1,25,16777215,1593476289,0,1a2e8af1,34778179999105031">啊啊啊啊啊喜欢</d><d p="294.03000,1,25,16777215,1593476789,0,3c9fa5df,34778442426744835">我玩</d><d p="78.77900,1,25,16777215,1593481124,0,6fa65418,34780715216797701">拉低中奖率</d><d p="126.25900,1,25,16777215,1593481177,0,6fa65418,34780742983614469">我可以的</d><d p="134.29900,1,25,16777215,1593481195,0,6fa65418,34780752162324487">归我，都归我</d><d p="147.87900,1,25,16777215,1593481223,0,6fa65418,34780767196807171">这个是我的了！</d><d p="287.50000,1,25,16777215,1593481995,0,7ee7b04f,34781171992756227">拉低</d><d p="290.18000,1,25,16777215,1593482000,0,7ee7b04f,34781174554427399">我要</d><d p="286.74000,1,25,16777215,1593485923,0,d7a58a3e,34783231067291655">明信片</d><d p="306.53700,1,25,16777215,1593485952,0,d7a58a3e,34783246358675459">赶紧的</d><d p="65.99700,1,25,16777215,1593486995,0,58cd46f8,34783793176903683">拉低中奖率</d><d p="194.72900,1,25,16777215,1593490293,0,d60dda00,34785522206375943">我也要</d><d p="202.62200,1,25,16777215,1593490301,0,d60dda00,34785526351396867">我我我我我我我</d><d p="148.11600,1,25,16777215,1593490317,0,762ac50,34785534845911045">拉低中奖率</d><d p="193.01900,1,25,16777215,1593490545,0,bba1e798,34785654700769285">我想要得到得不到，我都不知道</d><d p="213.72400,1,25,16777215,1593490889,0,b5b4f15e,34785834872340483">阿巴阿巴阿巴阿巴阿巴阿巴</d><d p="255.22600,1,25,16777215,1593490930,0,b5b4f15e,34785856567902215">想拥有想拥有</d><d p="51.35300,1,25,16777215,1593492372,0,5e183767,34786612397735939">胡老湿NB</d><d p="135.29900,1,25,16777215,1593493295,0,665b5b2d,34787096133107717">都是我的</d><d p="174.14000,1,25,16777215,1593493339,0,665b5b2d,34787119447670791">都是我的</d><d p="203.68800,1,25,16777215,1593494150,0,2a86356e,34787544670404611">啊啊啊啊啊啊啊啊啊啊啊啊啊啊啊啊啊啊啊</d><d p="278.37600,1,25,16777215,1593494247,0,2a86356e,34787595138367493">我要鬼灭!～</d><d p="184.64100,1,25,16777215,1593495169,0,66ff5023,34788078532427779">哈哈哈哈</d><d p="57.42900,1,25,16777215,1593495977,0,2079769f,34788502357934083">111</d><d p="108.71200,1,25,16777215,1593496071,0,54edbf65,34788551536148483">我我我</d><d p="61.77800,1,25,16777215,1593496318,0,f903f1f2,34788681070411783">小王和巴淡</d><d p="118.28700,1,25,16777215,1593496374,0,f903f1f2,34788710668566595">哈啊哈哈</d><d p="291.55500,1,25,16777215,1593496817,0,c5c2d503,34788942974287879">拉低中奖率</d><d p="68.82000,1,25,16777215,1593497074,0,d2997c09,34789077773975555">来了来了</d><d p="47.75400,1,25,16777215,1593497993,0,e0a74dbc,34789559549558791">woshibushiwanle</d><d p="56.26100,1,25,16777215,1593499764,0,5da07405,34790487976574983">哈哈哈哈哈哈</d><d p="70.47300,4,25,16707842,1593499778,0,5da07405,34790495426183175">笑死我了╯∀╰</d><d p="189.26400,4,25,16707842,1593499897,0,5da07405,34790557670703109">哇哦</d><d p="283.11300,4,25,16707842,1593500001,0,5da07405,34790612411613191">嘿嘿嘿</d><d p="149.58900,1,25,16777215,1593501317,0,79d455c1,34791302358368259">我来组成分子/嘿</d><d p="188.35900,1,25,16777215,1593502426,0,c653bfde,34791883412078597">哦豁</d><d p="85.04400,1,25,16777215,1593503046,0,fa2bd236,34792208811425799">拉低中奖率</d><d p="99.04900,1,25,16777215,1593504579,0,6ef68398,34793012467335171">我的我的！</d><d p="184.63800,1,25,16777215,1593504682,0,6ef68398,34793066192175109">不是驴吗？（滑稽保命）</d><d p="232.64800,1,25,16777215,1593505435,0,1354a934,34793461246853125">都是分母罢了</d><d p="188.60000,1,25,16777215,1593506089,0,924884a1,34793803927257091">拉低中奖率</d><d p="60.25900,1,25,16777215,1593506115,0,67634cc1,34793817655738373">拉低中奖率</d><d p="212.20000,1,25,16777215,1593506601,0,2d13adcf,34794072483823621">小缸的胸在动</d><d p="213.71700,1,25,16777215,1593507254,0,bb9488bd,34794414734311429">来一套</d><d p="259.49300,1,25,16777215,1593508320,0,1e77c3ae,34794973707108355">我是帅哥，给我吧、</d><d p="118.64300,1,25,16777215,1593508461,0,c0b593b9,34795047766458375">拉低中奖率</d><d p="200.33900,1,25,16777215,1593511077,0,1d21080e,34796419325362181">我想要灿姐缸妹的签名照怎么办</d><d p="85.25900,1,25,16777215,1593511996,0,be9f867f,34796901049565187">拉低中奖率</d><d p="88.85900,1,25,16777215,1593513144,0,b8705e7,34797502795874311">啊</d><d p="64.23300,1,25,16777215,1593515110,0,4e37de94,34798533628919815">我也来看小王和八蛋啦</d><d p="102.29200,1,25,16777215,1593515157,0,4e37de94,34798558310301701">没有我就自己买</d><d p="44.95900,1,25,16777215,1593515171,0,eb04c920,34798565361451011">拉低中奖率</d><d p="198.20600,1,25,16777215,1593515260,0,4e37de94,34798612516962309">我只想要一个</d><d p="285.07600,1,25,16777215,1593515363,0,4e37de94,34798666349805575">啊啊啊啊啊啊我只要三等奖谢谢</d><d p="136.31900,1,25,16777215,1593515386,0,eb04c920,34798678256386051">我我我我我</d><d p="110.16000,1,25,16777215,1593516637,0,55c9bd24,34799334035816455">选我</d><d p="145.40000,1,25,16777215,1593516675,0,55c9bd24,34799354121289735">我来了</d><d p="53.47800,1,25,16777215,1593517797,0,baf54425,34799942097174531">拉低中奖率</d><d p="100.70000,1,25,16777215,1593517995,0,d8a4378f,34800045915635715">拉低拉低</d><d p="98.57300,1,25,16777215,1593519399,0,6272b62a,34800782346813447">拉低中奖率</d><d p="296.84400,1,25,16777215,1593520419,0,da10da6,34801316822253575">我要三</d><d p="65.78000,1,25,16777215,1593524098,0,661a9e26,34803245673611267">全部寄给我</d><d p="136.14000,1,25,16777215,1593524523,0,170a8222,34803468767068165">拉低！！！！</d><d p="41.26800,1,25,16777215,1593526326,0,7cb3fe1d,34804413950853123">分享</d><d p="183.35000,1,25,16777215,1593526505,0,1982801b,34804508063694853">我我我我我我我我我我我</d><d p="67.62600,1,25,16777215,1593527430,0,d59d0e28,34804992848166919">我来啦！！！</d><d p="198.58900,1,25,16777215,1593527773,0,a12d4594,34805172795342855">拉低中奖率</d><d p="124.58900,1,25,16777215,1593527866,0,ffd72b68,34805221245845507">哦</d><d p="128.40300,1,25,16777215,1593528958,0,35d2808b,34805794001649667">我要我要</d><d p="135.85300,1,25,16777215,1593528966,0,35d2808b,34805797887672325">我要想要</d><d p="294.54800,1,25,16777215,1593529380,0,44af68a1,34806015109627909">我来拉低获奖绿</d><d p="112.69900,1,25,16777215,1593530444,0,f250d75b,34806572973031427">啊啊啊啊啊</d><d p="286.86000,1,25,16777215,1593530624,0,f250d75b,34806667566645251">？</d><d p="305.10000,1,25,16777215,1593530647,0,f250d75b,34806679547674629">冲冲冲冲冲冲</d><d p="211.31200,1,25,16777215,1593530740,0,4a442f92,34806728022818821">我我我我</d><d p="290.44700,1,25,16777215,1593530819,0,4a442f92,34806769521262599">我我我我我我</d><d p="118.69900,1,25,16777215,1593531944,0,f6411a24,34807359409750023">拉低中奖率</d><d p="73.94000,1,25,16777215,1593533036,0,2113f8de,34807931993587715">我我我我也想要</d><d p="148.82100,1,25,16777215,1593533307,0,ef6f5ad3,34808074044178435">想要想要想要</d><d p="164.26600,1,25,16777215,1593533328,0,ef6f5ad3,34808085270757383">想要</d><d p="101.35500,1,25,16777215,1593533797,0,4a43a033,34808330749214723">送我送我</d><d p="124.05900,1,25,16777215,1593535240,0,bd34f87f,34809087735103491">拉低中奖率</d><d p="160.43200,1,25,16777215,1593535926,0,423e3e85,34809446986678277">拉低中奖率</d><d p="164.15800,1,25,16777215,1593535947,0,90c42849,34809458215878663">拉低拉低</d><d p="105.60600,1,25,16777215,1593560448,0,7723539b,34822304011124741">中～？？？</d><d p="137.82000,1,25,16777215,1593562651,0,569cde74,34823458999238661">拉低中奖率</d><d p="56.97900,1,25,16777215,1593567757,0,a5d043f6,34826135665115141">拉低中奖率</d><d p="122.64100,1,25,16777215,1593567829,0,a5d043f6,34826173372432387">啊啊啊啊好可爱</d><d p="135.61100,5,25,16777215,1593567861,0,a5d043f6,34826190504067077">啊啊啊啊啊啊想要归我了！</d><d p="180.96600,5,25,15138834,1593567923,0,a5d043f6,34826222995243013">兔兔！兔兔！兔兔！</d><d p="122.17900,1,25,16777215,1593568433,0,79a8bb32,34826490214350853">我要</d><d p="143.94000,1,25,16777215,1593568457,0,79a8bb32,34826502948782083">我我我</d><d p="146.10000,1,25,16777215,1593568465,0,79a8bb32,34826506956963843">我可以</d><d p="204.27100,1,25,16777215,1593568568,0,24231a80,34826560906199043">拉低中奖率</d><d p="98.79000,1,25,16777215,1593570081,0,864fc608,34827354235207685"> 缸 想要</d><d p="136.67500,1,25,16777215,1593570089,0,4b5f82e4,34827358364499971">拉低概率！</d><d p="134.59800,1,25,16777215,1593570218,0,1f53a416,34827426078916615">拉低中奖率</d><d p="285.16200,1,25,16777215,1593570237,0,4b5f82e4,34827436173033479">拉低中奖概率</d><d p="183.23800,1,25,16777215,1593570286,0,1f53a416,34827461582127109">歪比吧不</d><d p="295.87800,1,25,16777215,1593570408,0,1f53a416,34827525644877829">给俺也整一个</d><d p="66.25800,1,25,16777215,1593571258,0,f76e61a3,34827971426516995">拉低中奖率</d><d p="158.51000,1,25,16777215,1593571678,0,f76e61a3,34828191322865669">拉低中奖率</d><d p="295.30800,1,25,16777215,1593571882,0,f76e61a3,34828298452205573">拉低中奖率 ？？？</d><d p="298.98400,1,25,16777215,1593572234,0,a055cdfc,34828482803400707">啊啊啊啊啊啊啊我要我可以啊啊啊啊啊</d><d p="69.14300,1,25,16777215,1593572460,0,403d4b64,34828601587662855">拉低中奖率</d><d p="294.74000,1,25,16777215,1593573123,0,18acb89d,34828949376729095">我要三等奖</d><d p="112.14000,1,25,16777215,1593573582,0,dfe239c1,34829189529468933">我的我的</d><d p="126.52600,1,25,16707842,1593575369,0,8c6d13e2,34830126640791555">拉低中奖率</d><d p="114.02600,1,25,16777215,1593575847,0,599b5fc4,34830377103654915">拉低中奖率</d><d p="72.64400,1,25,16707842,1593579631,0,e90d7421,34832361430974467">拉低中奖率</d><d p="294.73900,1,25,16777215,1593580157,0,3f64f25,34832637060186115">反正我中不了了（想要）</d><d p="192.83100,1,25,16777215,1593581772,0,64e06907,34833483542560773">拉低中奖率</d><d p="66.75200,1,25,16777215,1593582714,0,bffba8f,34833977518325767">。</d><d p="68.38800,1,25,16777215,1593582718,0,bffba8f,34833979911176199">。</d><d p="94.05800,1,25,16777215,1593582750,0,bffba8f,34833996545261571">我</d><d p="56.21900,1,25,16777215,1593585771,0,2703c494,34835580277751815">哈哈哈</d><d p="18.94300,1,25,16777215,1593587612,0,939194ce,34836545630371845">亲爱的？</d><d p="60.35400,1,25,16777215,1593588549,0,ed1378c3,34837036833701893">拉低中奖率！！！</d><d p="19.60000,1,25,16777215,1593591620,0,87c4a29f,34838646640082947">我要我要</d><d p="21.46000,1,25,16777215,1593591635,0,87c4a29f,34838654718312453">抽我抽我</d><d p="65.04000,1,25,16777215,1593591685,0,87c4a29f,34838680849350663">我我我我我要我要</d><d p="73.62000,1,25,16777215,1593591701,0,87c4a29f,34838689420410883">拉低中奖率</d><d p="77.78000,1,25,16777215,1593591716,0,87c4a29f,34838697085501447">给我给我我要哇啊啊啊啊啊</d><d p="90.48000,1,25,16777215,1593591736,0,87c4a29f,34838707698663429">啊啊啊啊我要我喜欢这个</d><d p="104.06000,1,25,16777215,1593591764,0,87c4a29f,34838722590539783">哇啊啊啊啊啊好可爱给我我要了</d><d p="116.74000,1,25,16777215,1593591797,0,87c4a29f,34838739675512839">啊啊啊啊啊老婆</d><d p="143.34000,1,25,16777215,1593591854,0,87c4a29f,34838769565696003">miku啊啊啊啊啊啊啊啊啊骑士团参见公主殿下</d><d p="163.61900,5,25,41194,1593591894,0,87c4a29f,34838790391463941">我我我我我我我我我我</d><d p="183.66000,5,25,41194,1593591919,0,87c4a29f,34838803663814661">好可爱</d><d p="289.98000,5,25,41194,1593592097,0,87c4a29f,34838896880648199">我朋友她说她想要</d><d p="312.14900,1,25,16777215,1593592653,0,ed1378c3,34839188487536647">嫖啊！</d><d p="76.01400,1,25,16777215,1593594212,0,a42d74a,34840005879267333">我我</d><d p="93.56400,1,25,16777215,1593594230,0,a42d74a,34840015078948867">我</d><d p="102.54600,1,25,16777215,1593594239,0,a42d74a,34840019773947911">我可嘛</d><d p="126.69000,1,25,16777215,1593594263,0,a42d74a,34840032444940291">想要</d><d p="136.25800,1,25,16777215,1593594272,0,a42d74a,34840037449269255">要</d><d p="142.71000,1,25,16777215,1593594279,0,a42d74a,34840040849801221">我我我</d><d p="151.72200,1,25,16777215,1593594288,0,a42d74a,34840045558431751">bilibili</d><d p="168.12900,1,25,16777215,1593594304,0,a42d74a,34840054169862147">bilibili十一年生日快乐哟吼</d><d p="98.52000,1,25,16777215,1593595536,0,40d11ed5,34840700035006467">拉低中奖率</d><d p="174.73500,1,25,16777215,1593596717,0,db9e7c8f,34841319334477827">111</d><d p="105.82000,1,25,16777215,1593599082,0,11e86f2,34842559028658181">绝缘体报道</d><d p="267.86800,1,25,16777215,1593599955,0,760693ee,34843016725266439">我的我的，都是我的</d><d p="254.28000,1,25,16777215,1593600113,0,6a43daca,34843099596849155">您搁那儿招魂呢</d><d p="119.62400,1,25,16777215,1593601265,0,25adac24,34843703433494531">选我</d><d p="134.73800,1,25,16777215,1593601280,0,25adac24,34843711392710663">拉低中奖率</d><d p="143.97800,1,25,16777215,1593601289,0,25adac24,34843716198334469">拉低中奖率~~~</d><d p="105.71900,1,25,16777215,1593602230,0,5ebd789b,34844209571168259">6666666</d><d p="58.67300,1,25,16777215,1593603915,0,d7530b8f,34845093251776519">拉低中奖率</d><d p="95.01600,1,25,16777215,1593603957,0,d7530b8f,34845115276066823">拉低中奖率</d><d p="180.52300,1,25,16777215,1593604065,0,d7530b8f,34845171659571207">拉低中奖率</d><d p="66.70000,1,25,16777215,1593604370,0,64d14b14,34845331427426311">啊兔兔兔兔</d><d p="68.50000,1,25,16777215,1593604377,0,64d14b14,34845335420928005">兔兔！</d><d p="139.78000,1,25,16777215,1593605059,0,22f09e59,34845692857417733">ohhh</d></i>