<?xml version="1.0" encoding="UTF-8"?><i><chatserver>chat.bilibili.com</chatserver><chatid>204833170</chatid><mission>0</mission><maxlimit>1000</maxlimit><state>0</state><real_name>0</real_name><source>e-r</source><d p="204.64600,1,25,16777215,1593081597,0,77a743bc,34571248146579463">01必吃过</d><d p="233.33800,1,25,16777215,1593081626,0,77a743bc,34571263156944901">01吃过类似的</d><d p="265.81300,1,25,16777215,1593081658,0,77a743bc,34571280185819139">01吃过 确实上流的赶脚</d><d p="41.27100,1,25,16777215,1593081856,0,218f7a84,34571383872684039">04吃过</d><d p="46.35700,1,25,16777215,1593081959,0,fea9bd08,34571437578649607">00吃过</d><d p="98.55600,1,25,16777215,1593081983,0,fea9bd08,34571450575224839">05吃过</d><d p="111.77400,1,25,16777215,1593082260,0,c8e8d9b2,34571595292868613">00后吃过</d><d p="139.57200,1,25,16777215,1593082287,0,c8e8d9b2,34571609918406663">吃过</d><d p="192.56300,1,25,16777215,1593082340,0,c8e8d9b2,34571637707767815">有白色的</d><d p="201.22000,1,25,16777215,1593082359,0,c8e8d9b2,34571647332646917">我超爱奶片哈哈哈哈</d><d p="225.08900,1,25,16777215,1593082384,0,c8e8d9b2,34571660663717895">锅巴，我饿了</d><d p="258.74700,1,25,16777215,1593082425,0,c8e8d9b2,34571682080358403">00后吃过</d><d p="136.70600,1,25,16777215,1593082457,0,789b236e,34571698907906055">00吃过</d><d p="20.25900,1,25,16777215,1593083189,0,1298539f,34572082475958279">你胖了你胖了你胖了</d><d p="42.81900,1,25,16777215,1593083795,0,78c1db3a,34572400138911751">00吃过</d><d p="7.40100,1,25,16777215,1593083824,0,cc34e8a5,34572415356370949">叫兽</d><d p="70.16000,1,25,16777215,1593083830,0,78c1db3a,34572418947743749">00没吃过</d><d p="103.60000,1,25,16777215,1593083881,0,78c1db3a,34572445314711559">00没吃过</d><d p="223.23900,1,25,16777215,1593083938,0,2c4d105a,34572475130445831">03没见过，没吃过</d><d p="114.92000,1,25,41194,1593083951,0,78c1db3a,34572482238218247">00吃过</d><d p="128.77900,1,25,41194,1593083976,0,78c1db3a,34572495486976005">00没吃过</d><d p="74.04700,5,25,16777215,1593084004,0,34b60e54,34572510143971335">00吃过！</d><d p="157.24000,1,25,41194,1593084012,0,78c1db3a,34572513867464711">00没吃过</d><d p="180.87900,1,25,41194,1593084067,0,78c1db3a,34572542713266181">00吃过我小时候觉得这个是仙丹</d><d p="199.71900,1,25,41194,1593084097,0,78c1db3a,34572558423031811">00吃过</d><d p="226.52300,1,25,41194,1593084124,0,78c1db3a,34572572846194759">00没吃过</d><d p="250.18000,1,25,41194,1593084158,0,78c1db3a,34572590454407175">00吃过</d><d p="144.29700,1,25,16777215,1593084783,0,e05af95f,34572918539157507">还有飞行棋！！！</d><d p="38.09800,1,25,16777215,1593085073,0,22794b21,34573070532345859">90</d><d p="69.93200,1,25,16777215,1593085113,0,22794b21,34573091536371719">99最爱吃这个！昨天还吃的！</d><d p="95.21200,1,25,16777215,1593085144,0,22794b21,34573107440648199">99吃过！</d><d p="116.17200,1,25,16777215,1593085174,0,22794b21,34573123071770631">99又吃过！</d><d p="184.49200,1,25,16777215,1593085253,0,22794b21,34573164957138951">99吃过</d><d p="226.65200,1,25,16777215,1593085304,0,22794b21,34573191434207235">99感觉全都吃过啊</d><d p="59.99300,1,25,16777215,1593085322,0,f45d7dd6,34573201039687685">00吃过</d><d p="40.41900,1,25,16777215,1593085567,0,d74fcad8,34573329379622917">02吃过</d><d p="120.84500,1,25,16777215,1593085686,0,a04917a9,34573391579578371">吃过</d><d p="10.28000,1,25,16777215,1593085763,0,666bf909,34573432143740931">帅哥你谁啊</d><d p="81.30000,1,25,16777215,1593086116,0,4d3ed814,34573617263542275">06没吃过</d><d p="93.49900,1,25,16777215,1593086139,0,4d3ed814,34573629366730757">00吃过</d><d p="182.92600,1,25,16777215,1593086188,0,4d3ed814,34573655180050435">06吃过</d><d p="106.13200,1,25,16777215,1593086259,0,49205a6f,34573692040642567">哈哈哈哈哈哈哈哈哈哈哈</d><d p="106.34400,1,25,16777215,1593086351,0,5d82e962,34573740156649477">05吃过</d><d p="24.57800,1,25,16777215,1593086543,0,f63e784,34573841009213447">你不能再胖了，就要变油腻大叔了</d><d p="98.57900,1,25,16777215,1593087245,0,e364205,34574209232928775">01吃过</d><d p="127.81900,1,25,16777215,1593087310,0,e364205,34574243316367363">01吃过</d><d p="39.33900,1,25,16777215,1593087448,0,1f7ba5c3,34574315318411271">00吃过</d><d p="41.74500,1,25,16777215,1593087531,0,c2754b52,34574358940221447">00吃过</d><d p="54.16100,1,25,16777215,1593087552,0,c2754b52,34574369858519045">04吃过</d><d p="94.22700,1,25,16777215,1593087602,0,c2754b52,34574396207661061">04吃过</d><d p="119.70500,1,25,16777215,1593087615,0,75bf28e5,34574403075833859">我小时候没有这个，只有大皮哥</d><d p="116.53900,1,25,16777215,1593087630,0,c2754b52,34574410776576003">04吃过</d><d p="88.56400,1,25,16777215,1593087738,0,c581b104,34574467462070277">吧唧嘴差评</d><d p="79.53400,1,25,16777215,1593087828,0,3de37c93,34574514541559813">00吃过</d><d p="193.26200,1,25,16777215,1593088549,0,d4c51edf,34574892859392007">06吃过</d><d p="203.63900,1,25,16777215,1593088559,0,d4c51edf,34574898223906821">06吃过</d><d p="51.47100,1,25,16777215,1593088674,0,615f4b1a,34574958208745475">00吃过</d><d p="67.77900,1,25,16777215,1593088690,0,615f4b1a,34574966769319939">大家可能都是1900后的</d><d p="122.49900,1,25,16777215,1593088745,0,615f4b1a,34574995520225283">吃过呀</d><d p="43.92600,1,25,16777215,1593088780,0,cab6cd9f,34575013786943495">00吃过</d><d p="94.30600,1,25,16777215,1593088837,0,cab6cd9f,34575043643572227">00吃过</d><d p="243.19900,1,25,16777215,1593088852,0,615f4b1a,34575051432394757">老邪翻车了？</d><d p="116.96600,1,25,16777215,1593088866,0,cab6cd9f,34575058826428423">03吃过</d><d p="110.40200,5,25,15138834,1593088868,0,9a0e9f3d,34575060141867015">这破路也能开车？</d><d p="127.18600,1,25,16777215,1593088897,0,cab6cd9f,34575075439542275">03吃过</d><d p="15.79100,1,25,16777215,1593089238,0,504b7a02,34575253947547651">？？？？？</d><d p="109.34600,1,25,16777215,1593089331,0,504b7a02,34575303020380167">？？？？？？？？？？？？？</d><d p="41.47600,1,25,16777215,1593089371,0,ef15b13f,34575323730280455">02吃过</d><d p="51.68500,1,25,16777215,1593089424,0,f41966e9,34575351690035205">05吃过</d><d p="99.06300,1,25,16777215,1593089445,0,ef15b13f,34575362759327747">02的吃过</d><d p="122.95700,1,25,16777215,1593089469,0,ef15b13f,34575375203827717">02肯定吃过啊</d><d p="135.50400,1,25,16777215,1593089482,0,ef15b13f,34575381790457859">02的还是吃过</d><d p="70.54400,1,25,15138834,1593089499,0,f41966e9,34575390973362179">05吃过</d><d p="188.10200,1,25,16777215,1593089534,0,ef15b13f,34575409352802309">02吃过</d><d p="205.48300,1,25,16777215,1593089552,0,ef15b13f,34575418473316357">02吃过</d><d p="223.75000,1,25,16777215,1593089570,0,ef15b13f,34575428047863813">02吃过</d><d p="259.30800,1,25,16777215,1593089606,0,ef15b13f,34575446695215109">02吃过</d><d p="155.77100,1,25,16777215,1593089666,0,f41966e9,34575478332325893">05吃过</d><d p="106.06300,1,25,16777215,1593089720,0,258366ca,34575506677956615">00吃过</d><d p="94.16000,1,25,16777215,1593089979,0,9dacbfee,34575642538278917">00吃过</d><d p="162.17900,1,25,16777215,1593090164,0,724b7c9,34575739298775043">这个好吃！！</d><d p="176.10300,1,25,16777215,1593090308,0,6a2e7530,34575814816169989">99没见过</d><d p="108.10800,1,25,16777215,1593092777,0,aa88df8a,34577109657583623">97没吃过跳跳糖</d><d p="94.33900,1,25,16777215,1593093254,0,8a0a8434,34577359586721795">00吃過！小賣部有賣！</d><d p="218.91900,1,25,16777215,1593093384,0,8a0a8434,34577427655557123">00后吃過！！！</d><d p="47.55900,1,25,16777215,1593093534,0,7619b682,34577506521579527">00吃过</d><d p="96.89900,1,25,16777215,1593093595,0,7619b682,34577538064842757">00吃过</d><d p="71.74200,1,25,16777215,1593094118,0,533a36f5,34577812480851971">00</d><d p="116.71300,1,25,16777215,1593094166,0,533a36f5,34577837462650885">00</d><d p="140.86300,1,25,16777215,1593094194,0,533a36f5,34577852272738309">00</d><d p="295.76200,1,25,16777215,1593094210,0,a448a46e,34577860939743239">95后的我全都吃过</d><d p="61.71800,1,25,16777215,1593094355,0,35eb6b72,34577936688873479">魔法士</d><d p="170.83600,1,25,16777215,1593094464,0,35eb6b72,34577994105225223">00没吃过</d><d p="71.72000,1,25,16777215,1593094517,0,45e956ce,34578022008881155">大四了表示还在吃</d><d p="46.38100,1,25,16777215,1593094567,0,45e956ce,34578047740936195">97吃过</d><d p="93.20600,1,25,16777215,1593094610,0,45e956ce,34578070430547975">97吃过</d><d p="128.82600,1,25,16777215,1593094652,0,45e956ce,34578092327960579">吃过</d><d p="78.31200,1,25,16777215,1593095476,0,46965366,34578524781674501">求老邪色号hhhhhhhh</d><d p="51.92100,1,25,16777215,1593095540,0,e6a58923,34578558118526981">00吃过</d><d p="77.16800,1,25,16777215,1593095565,0,e6a58923,34578571348410375">之前还有调味包</d><d p="127.27200,1,25,16777215,1593095580,0,46965366,34578578846253061">小时候因为酸从来都没有完整吃完一袋（捂脸笑</d><d p="64.77400,1,25,16777215,1593096206,0,5aab8aff,34578907205206021">00吃过</d><d p="73.79600,1,25,16777215,1593096216,0,5aab8aff,34578912320684035">00没吃过</d><d p="121.38700,1,25,16777215,1593096263,0,5aab8aff,34578937289900039">00吃过</d><d p="47.14500,1,25,16777215,1593096534,0,a0a8308d,34579079137067013">80+</d><d p="81.88500,1,25,16777215,1593096574,0,a0a8308d,34579100432596995">80+</d><d p="116.66700,1,25,16777215,1593096625,0,e12bb278,34579127174430853">19吃过</d><d p="45.14800,1,25,16777215,1593096923,0,dd936da,34579282978668549">01年以前最爱</d><d p="99.78500,1,25,16777215,1593096977,0,dd936da,34579311622094853">01年以前最爱</d><d p="121.83500,1,25,16777215,1593096999,0,dd936da,34579323196801027">01年以前最爱</d><d p="38.66000,1,25,16777215,1593097011,0,99a277b8,34579329483538435">00吃过</d><d p="44.29700,1,25,16777215,1593097018,0,3e7311c,34579333024055301">05吃过</d><d p="142.02400,1,25,16777215,1593097020,0,dd936da,34579333813633031">01年以前最爱</d><d p="81.43900,1,25,16777215,1593097055,0,3e7311c,34579352495063045">05没吃过</d><d p="189.67400,1,25,16777215,1593097067,0,dd936da,34579358748246021">01已经吃到不爱吃</d><d p="93.88000,1,25,16777215,1593097084,0,99a277b8,34579367455096835">00吃过</d><d p="208.07700,1,25,16777215,1593097086,0,dd936da,34579368447574023">01年最爱奶片！！</d><d p="246.73300,1,25,16777215,1593097248,0,3e7311c,34579453367549955">05超喜欢吃</d><d p="16.01000,1,25,16777215,1593097441,0,1a7d5c0b,34579554808365061">胖了</d><d p="102.81800,1,25,16777215,1593097706,0,feec4e54,34579693617283075">05吃过</d><d p="121.75600,1,25,16777215,1593097725,0,feec4e54,34579703547822085">05吃过</d><d p="189.46000,1,25,16777215,1593097801,0,feec4e54,34579743387942915">05吃过</d><d p="209.25600,1,25,16777215,1593097821,0,feec4e54,34579753746825223">05吃过</d><d p="129.74000,1,25,16777215,1593098025,0,4e0ca3c1,34579860971585539">00的巨爱</d><d p="140.07500,1,25,16777215,1593098035,0,4e0ca3c1,34579866362839045">00吃过</d><d p="147.96000,1,25,16777215,1593098043,0,4e0ca3c1,34579870519394307">00吃过</d><d p="186.98900,1,25,16777215,1593098059,0,8b9612e1,34579878868156423">哦哦哦</d><d p="189.41300,1,25,16777215,1593098085,0,4e0ca3c1,34579892250607619">00吃过</d><d p="212.18500,1,25,16777215,1593098107,0,4e0ca3c1,34579904206995463">00吃过00吃够</d><d p="38.35900,1,25,16777215,1593098119,0,4fd3f3f1,34579910258327557">00吃过</d><d p="93.51900,1,25,16777215,1593098183,0,4fd3f3f1,34579943888781319">00吃过</d><d p="117.63900,1,25,16777215,1593098217,0,4fd3f3f1,34579961406291971">00吃过</d><d p="126.95900,1,25,16777215,1593098234,0,4fd3f3f1,34579970722365447">00爱吃</d><d p="124.99400,1,25,16777215,1593098326,0,37b9eca6,34580018510168067">90吃过</d><d p="128.74000,1,25,16707842,1593099989,0,9547b7a6,34580890622885891">90吃过</d><d p="162.14000,1,25,16707842,1593100027,0,9547b7a6,34580910817411077">90吃过</d><d p="25.25800,1,25,16777215,1593100283,0,de4e76e6,34581044649787397">帅哥你谁 这不是老邪</d><d p="38.55600,1,25,16777215,1593100413,0,d211ad0c,34581113148014599">00没吃过</d><d p="108.88100,1,25,16707842,1593100706,0,1377ebb4,34581266695716869">？？？？？？？？？？？？</d><d p="25.30000,1,25,16777215,1593100936,0,933a05ff,34581387311841283">减肥吧 还我帅哥</d><d p="46.76500,1,25,16777215,1593101257,0,664036d,34581555336708101">说得好</d><d p="15.38600,1,25,16777215,1593101293,0,fa8971a0,34581574449102851">你是不是胖了呀</d><d p="222.92200,1,25,16777215,1593101556,0,a2d9e8d4,34581712019128325">牙好白</d><d p="141.65800,1,25,16777215,1593102576,0,bb7afc5b,34582246830637061">04后吃过</d><d p="74.66500,1,25,16777215,1593102678,0,a6a87d4a,34582300254011399">00没吃过</d><d p="95.15000,1,25,16777215,1593102698,0,a6a87d4a,34582310871891975">00吃过</d><d p="108.42600,1,25,16777215,1593102711,0,a6a87d4a,34582317819232259">哈哈哈哈</d><d p="118.83800,1,25,16777215,1593102722,0,a6a87d4a,34582323308527623">00吃过</d><d p="130.78900,1,25,16777215,1593102733,0,a6a87d4a,34582329559089155">00吃过</d><d p="190.95500,1,25,16777215,1593102794,0,a6a87d4a,34582361211404291">00吃过</d><d p="207.23400,1,25,16777215,1593102810,0,a6a87d4a,34582369669218311">00吃过</d><d p="225.62200,1,25,16777215,1593102828,0,a6a87d4a,34582379266310149">00吃过</d><d p="255.62300,1,25,16777215,1593102858,0,a6a87d4a,34582395034796039">00吃过</d><d p="50.50400,1,25,16777215,1593102984,0,d31b6291,34582461132308487">80 吃过</d><d p="113.63400,1,25,16777215,1593103614,0,86a8f546,34582791126515715">啊开车吗</d><d p="46.18800,1,25,16777215,1593103909,0,f5f94d32,34582945645199367">00没吃过</d><d p="80.50000,1,25,16777215,1593104140,0,b8b3d8ce,34583066819690501">吃过</d><d p="69.35100,1,25,16777215,1593104248,0,adf9b0e,34583123585400839">00吃过</d><d p="95.12200,1,25,16777215,1593104282,0,adf9b0e,34583141194137603">00吃过</d><d p="224.77200,1,25,16777215,1593104320,0,b8b3d8ce,34583161348816899">这个好吃</d><d p="126.41900,1,25,16777215,1593104332,0,adf9b0e,34583167871483909">00吃过，就是萝卜条但是贼好吃</d><d p="159.42100,1,25,16777215,1593104378,0,adf9b0e,34583191751753735">00吃过，哈哈哈我都吃过</d><d p="17.27800,1,25,16777215,1593104688,0,4a62408a,34583354254295043">哈哈哈哈哈哈哈</d><d p="23.77800,1,25,16777215,1593104695,0,4a62408a,34583357712498695">邪 胖</d><d p="40.77800,1,25,16707842,1593104712,0,4a62408a,34583366600753159">中分邪 胖</d><d p="51.77800,1,25,16707842,1593104723,0,4a62408a,34583372494798851">98没吃过</d><d p="101.77800,1,25,16707842,1593104772,0,4a62408a,34583398477987847">现在超市也还有卖</d><d p="112.77800,1,25,16707842,1593104783,0,4a62408a,34583404289720325">98吃过</d><d p="126.77800,1,25,16707842,1593104798,0,4a62408a,34583411887177735">98吃过</d><d p="144.27800,1,25,16707842,1593104815,0,4a62408a,34583420781723655">哈哈哈哈哈哈哈</d><d p="153.27800,1,25,16707842,1593104824,0,4a62408a,34583425677000709">哈哈哈</d><d p="178.27700,1,25,16707842,1593104849,0,4a62408a,34583438656274435">98没吃过</d><d p="199.77800,1,25,16707842,1593104871,0,4a62408a,34583450079985667">白色不好吃</d><d p="40.37900,1,25,16777215,1593106531,0,ed7f30d9,34584320422182919">00吃过</d><d p="70.28000,1,25,16777215,1593106567,0,ed7f30d9,34584339197984771">00吃过</d><d p="95.66000,1,25,16777215,1593106598,0,ed7f30d9,34584355799564295">00吃过</d><d p="130.18000,1,25,16777215,1593106644,0,ed7f30d9,34584379789934597">00没见过</d><d p="159.70000,1,25,16777215,1593106678,0,ed7f30d9,34584397742080007">00没</d><d p="71.40100,1,25,16777215,1593107082,0,942843b2,34584609613152261">00吃过</d><d p="48.26000,1,25,16777215,1593108555,0,daac6da2,34585381590007813">90没吃过这个包装</d><d p="72.61900,1,25,16777215,1593108587,0,daac6da2,34585398585851909">90依然盲区</d><d p="131.06300,1,25,16777215,1593108724,0,df84f18b,34585470095589381">难吃</d><d p="250.93900,1,25,16777215,1593108857,0,df84f18b,34585539934945285">百流杯好吃</d><d p="153.27800,1,25,16777215,1593109669,0,a374cab9,34585965989199877">我记得里面还送玩具</d><d p="262.23700,1,25,16777215,1593109802,0,a374cab9,34586035313180679">这个我超爱吃！！</d><d p="95.63600,1,25,16777215,1593109906,0,f794a5c8,34586089847521283">90+吃过跳跳糖</d><d p="122.68700,1,25,16777215,1593109941,0,f794a5c8,34586108164046853">90吃过</d><d p="94.25400,1,25,16777215,1593110263,0,2f3260e7,34586277338152963">00吃过</d><d p="289.74900,1,25,16777215,1593114117,0,afc264b,34588297892724743">泡椒牛板筋</d><d p="51.68500,1,25,16777215,1593119283,0,de643359,34591006472536069">05吃过</d><d p="96.47400,1,25,16777215,1593119314,0,de643359,34591022650490883">05吃过</d><d p="12.70600,1,25,16777215,1593132814,0,5630f201,34598100658028549">你胖了</d><d p="45.76500,1,25,16777215,1593134928,0,c96497f7,34599208965636103">90吃过</d><d p="51.04000,1,25,16777215,1593134934,0,c96497f7,34599211718148101">主要是卡</d><d p="71.37500,1,25,16777215,1593134954,0,c96497f7,34599222394748935">90吃过</d><d p="95.47800,1,25,16777215,1593134978,0,c96497f7,34599235017506819">90吃过</d><d p="119.43200,1,25,16777215,1593135002,0,c96497f7,34599247571582981">90吃过</d><d p="129.13300,1,25,16777215,1593135012,0,c96497f7,34599252655603717">90吃过</d><d p="156.15400,1,25,16777215,1593135039,0,c96497f7,34599266832875523">90吃过</d><d p="181.07200,1,25,16777215,1593135064,0,c96497f7,34599279889219587">90吃过</d><d p="199.67900,1,25,16777215,1593135082,0,c96497f7,34599289675055111">90吃过</d><d p="7.90900,1,25,16777215,1593135259,0,1ae45bdf,34599382353969157">胖了老邪</d><d p="69.72000,1,25,16777215,1593135801,0,8b0f5f0c,34599666538512389">98吃过</d><d p="131.68400,1,25,16777215,1593135863,0,8b0f5f0c,34599699222102023">98吃过</d><d p="145.20900,1,25,41194,1593135877,0,8b0f5f0c,34599706100236293">98吃过</d><d p="171.00500,1,25,41194,1593135902,0,8b0f5f0c,34599719660421127">98没吃过</d><d p="192.58800,1,25,41194,1593135924,0,8b0f5f0c,34599730988187655">麦丽素不分年代</d><d p="241.61500,1,25,41194,1593135973,0,8b0f5f0c,34599756684066819">牙好白</d><d p="265.50900,1,25,41194,1593135997,0,8b0f5f0c,34599769232375815">昨天还在吃</d><d p="85.23900,1,25,16777215,1593137102,0,26805fea,34600348641918983">98没吃过</d><d p="7.04200,1,25,16777215,1593138024,0,bcf2937e,34600832089980931">来了来了</d><d p="178.09000,1,25,16777215,1593138543,0,9c184baa,34601104064905221">70后没吃过</d><d p="52.81100,1,25,16777215,1593138672,0,cfccdf99,34601171788234759">05表示当年吃的时候好小但留下的印象特深</d><d p="94.38400,1,25,16777215,1593138735,0,cfccdf99,34601204737114119">07吃过！儿时快乐糖！</d><d p="117.72500,1,25,16777215,1593138772,0,cfccdf99,34601224222277637">07吃过</d><d p="126.86600,1,25,16777215,1593138802,0,cfccdf99,34601239908450307">噗07我现在就在吃这个</d><d p="46.03900,1,25,16777215,1593138841,0,e99becde,34601260311117831">05吃过</d><d p="70.35900,1,25,16777215,1593138878,0,e99becde,34601279831408643">05没吃过</d><d p="188.73200,1,25,16777215,1593138893,0,cfccdf99,34601287385350147">07吃过！因为当时婚糖里有一堆，，，</d><d p="94.55900,1,25,16777215,1593138910,0,e99becde,34601296382132229">05吃过</d><d p="200.50100,1,25,16777215,1593138951,0,cfccdf99,34601318229737543">这玩意我同学经常买给她10后的弟弟吃哈哈哈</d><d p="225.62000,1,25,16777215,1593138985,0,cfccdf99,34601335892475911">07吃过！</d><d p="264.10800,1,25,16777215,1593139061,0,cfccdf99,34601375454724101">07小时候特爱吃不过现在我们大超市没卖的了</d><d p="91.52900,1,25,16777215,1593140198,0,7b76ffc8,34601971951337477">00 吃过</d><d p="38.66000,1,25,16777215,1593140476,0,610b6568,34602117405081603">00后吃过</d><d p="83.54000,1,25,15138834,1593140567,0,610b6568,34602165337587717">00没吃过</d><d p="96.70000,1,25,6830715,1593140606,0,610b6568,34602185749168133">00吃过</d><d p="47.45900,1,25,16777215,1593141156,0,e229f087,34602474114908163">05吃过</d><d p="76.61900,1,25,16777215,1593141197,0,e229f087,34602495608619013">05没吃过</d><d p="94.37900,1,25,16777215,1593141224,0,e229f087,34602509732937735">05吃过</d><d p="60.63700,1,25,16777215,1593142186,0,5b53ba4f,34603014219104259">现在超市也有卖小浣熊的啊</d><d p="223.87700,1,25,16777215,1593142367,0,5b53ba4f,34603108829495299">01表示大学超市里都还有卖</d><d p="129.22600,1,25,16777215,1593143231,0,5f0cc95,34603561729392647">我吃过</d><d p="45.19900,1,25,16777215,1593143577,0,16cc7b1d,34603743258345477">00吃过</d><d p="119.19900,1,25,16777215,1593143661,0,16cc7b1d,34603787183194117">00吃过</d><d p="287.30000,1,25,16777215,1593143750,0,77a9e2e0,34603834011549703">牛板筋</d><d p="203.57900,1,25,16777215,1593143752,0,16cc7b1d,34603835009269763">00吃过</d><d p="72.70000,1,25,16777215,1593143846,0,92c2bb22,34603884302827523">啊啊啊啊！！！我爱这个！！！</d><d p="111.03500,1,25,16777215,1593143884,0,92c2bb22,34603904412942339">？？？？？？？？</d><d p="128.67500,1,25,16777215,1593143902,0,92c2bb22,34603913652469763">！！！！无花果！！！！</d><d p="133.94300,1,25,16777215,1593143907,0,92c2bb22,34603916426477575">97吃过</d><d p="185.87700,1,25,16777215,1593143959,0,92c2bb22,34603943639646211">我超爱！</d><d p="205.51800,1,25,16777215,1593143979,0,92c2bb22,34603953919885315">！！！！我现在我在买</d><d p="117.03500,1,25,16777215,1593144443,0,5f5ab61e,34604197171691525">00后吃过</d><d p="71.61400,1,25,16777215,1593144760,0,2bd22d85,34604363333238791">00吃过</d><d p="95.57400,1,25,16777215,1593144794,0,2bd22d85,34604381511876611">00吃过</d><d p="182.71400,1,25,16777215,1593144891,0,2bd22d85,34604432132931591">00吃过</d><d p="204.17400,1,25,16777215,1593144920,0,2bd22d85,34604447530745863">00吃过</d><d p="222.49400,1,25,16777215,1593144959,0,2bd22d85,34604467978502147">00吃过</d><d p="224.09400,1,25,16777215,1593144987,0,2bd22d85,34604482508095493">初中小卖部卖得最火的零食</d><d p="253.61400,1,25,16777215,1593145025,0,2bd22d85,34604502541664259">00吃过</d><d p="107.56000,1,25,16777215,1593145811,0,ccf27609,34604914771492871">06吃过</d><d p="93.05900,1,25,16777215,1593146927,0,73cf0a97,34605499763654659">00吃过</d><d p="40.14300,1,25,16777215,1593148105,0,ae47a37d,34606117445173255">99没吃过</d><d p="70.13100,1,25,16777215,1593148141,0,ae47a37d,34606135983472647">00没吃过</d><d p="93.47600,1,25,16777215,1593148168,0,ae47a37d,34606150458540037">00吃过</d><d p="42.59000,1,25,16777215,1593148870,0,c996c37f,34606518194667527">00没吃过</d><d p="84.60100,1,25,16777215,1593148912,0,c996c37f,34606540218433541">00没吃过</d><d p="96.67800,1,25,16777215,1593148924,0,c996c37f,34606546545016835">00吃过</d><d p="121.20000,1,25,16777215,1593148948,0,c996c37f,34606559411568643">00吃过</d><d p="135.32000,1,25,16777215,1593148962,0,c996c37f,34606566810320899">00吃过</d><d p="161.94800,1,25,16777215,1593148989,0,c996c37f,34606580775256071">00吃过</d><d p="186.40800,1,25,16777215,1593149013,0,c996c37f,34606593584136197">00吃过</d><d p="203.77600,1,25,16777215,1593149031,0,c996c37f,34606602711990279">00吃过</d><d p="221.82900,1,25,16777215,1593149049,0,c996c37f,34606612213137415">00吃过</d><d p="255.16100,1,25,16777215,1593149082,0,c996c37f,34606629637849091">00吃过</d><d p="283.36900,1,25,16777215,1593149589,0,a7f69a,34606895367979015">烧烤专家</d><d p="69.26700,1,25,16777215,1593149893,0,524a5714,34607054702247943">05吃过</d><d p="101.15000,1,25,16777215,1593149926,0,524a5714,34607071899942915">05吃过</d><d p="161.48400,1,25,16777215,1593150136,0,d2333a72,34607181987315717">好吃！</d><d p="42.06000,1,25,16777215,1593151558,0,751e4cf3,34607927669030919">00没吃过</d><d p="116.26000,1,25,16777215,1593151608,0,83b13cc2,34607953893392389">04吃过</d><d p="95.61900,1,25,16777215,1593151615,0,751e4cf3,34607957496823813">00吃过</d><d p="183.26800,1,25,16777215,1593151693,0,83b13cc2,34607998613061637">04吃过</d><d p="201.60400,1,25,16777215,1593151720,0,83b13cc2,34608012606308359">04吃过</d><d p="222.69600,1,25,16777215,1593151748,0,83b13cc2,34608027147436037">04吃过</d><d p="38.90300,1,25,16777215,1593152302,0,298d690e,34608317619240965">00吃过</d><d p="73.22400,1,25,16777215,1593152344,0,298d690e,34608339659784195">00没吃过</d><d p="89.58400,1,25,16777215,1593152379,0,298d690e,34608358220627975">我觉得这吃没吃过取决于地区</d><d p="97.24400,1,25,16777215,1593152393,0,298d690e,34608365366673415">00吃过</d><d p="225.51700,1,25,16777215,1593152453,0,298d690e,34608396974948355">我吃的不辣</d><d p="19.63900,1,25,16777215,1593153793,0,d06e8b58,34609099256102915">05后来啦</d><d p="46.48400,1,25,16777215,1593153940,0,a94d0acd,34609176611651587">00吃过</d><d p="95.20700,1,25,16777215,1593153979,0,f08db959,34609197195198469">04吃过</d><d p="204.83900,1,25,16777215,1593154105,0,f08db959,34609263205154819">04吃过</d><d p="111.69800,1,25,16777215,1593154780,0,bae3294,34609617011474435">00吃过</d><d p="115.84300,1,25,16777215,1593154796,0,bae3294,34609625342935043">00吃过虾条哈哈</d><d p="13.28700,1,25,16777215,1593155026,0,55d2f3b4,34609746130501639">你胖了，</d><d p="84.25900,1,25,16777215,1593155373,0,9c3467be,34609927713456133">00没</d><d p="282.32800,1,25,16777215,1593155378,0,55d2f3b4,34609930218504197">星球杯</d><d p="100.42400,1,25,16777215,1593155389,0,9c3467be,34609936166551555">00吃过</d><d p="286.33300,1,25,16777215,1593155401,0,55d2f3b4,34609942520922119">功夫米线</d><d p="120.07500,1,25,16777215,1593155409,0,9c3467be,34609946476675075">00吃过</d><d p="136.36600,1,25,16777215,1593155425,0,9c3467be,34609955004219399">00没有</d><d p="40.50000,1,25,16777215,1593156183,0,69cbec50,34610352599072773">00吃过</d><d p="73.82000,1,25,16777215,1593156223,0,69cbec50,34610373721587715">00吃过</d><d p="94.46000,1,25,16777215,1593156253,0,69cbec50,34610389309194247">00又吃过</d><d p="42.59100,1,25,16777215,1593156536,0,a97da24b,34610537381232643">00吃过</d><d p="97.80300,1,25,16777215,1593156932,0,47563dad,34610745396166663">08吃过</d><d p="44.94000,1,25,16777215,1593157676,0,191fac9a,34611135227887619">05吃过</d><d p="46.32900,1,25,16777215,1593158465,0,b5876660,34611549087203333">00吃过</d><d p="78.93500,1,25,16777215,1593158498,0,b5876660,34611566167982083">00吃过！</d><d p="109.17900,1,25,16777215,1593158528,0,b5876660,34611582050762755">？？</d><d p="122.31600,1,25,16777215,1593158541,0,b5876660,34611588923654151">00吃过</d><d p="129.82100,1,25,16777215,1593158549,0,b5876660,34611592879931397">00吃过</d><d p="168.61200,1,25,16777215,1593158588,0,b5876660,34611613187702791">00没吃过</d><d p="223.43000,1,25,16777215,1593158642,0,b5876660,34611641938083847">00吃过</d><d p="254.71000,1,25,16777215,1593158674,0,b5876660,34611658360881157">00吃过</d><d p="42.87800,1,25,16777215,1593159632,0,37d45406,34612160914522117">97</d><d p="98.75800,1,25,16777215,1593159672,0,37d45406,34612181897576455">97</d><d p="103.97900,1,25,16777215,1593160387,0,2e8dfb9a,34612556572131331">05吃过</d><d p="119.58000,1,25,16777215,1593160413,0,2e8dfb9a,34612570088800263">05前两天还吃了</d><d p="181.90000,1,25,16777215,1593160483,0,2e8dfb9a,34612606808358917">05吃过</d><d p="185.14000,1,25,16777215,1593160494,0,2e8dfb9a,34612612682481667">伸腿瞪眼丸？</d><d p="200.05900,1,25,16777215,1593160515,0,2e8dfb9a,34612623757017091">05吃过</d><d p="97.10600,5,18,15138834,1593161882,0,e32dd078,34613340547317765">06吃过</d><d p="51.82000,1,25,16777215,1593162498,0,f962b8c,34613663453675523">98吃过，一块五一包，可以中奖再来一包</d><d p="80.13900,1,25,16777215,1593162535,0,f962b8c,34613682613256199">98的我没吃过</d><d p="97.53900,1,25,16777215,1593162559,0,f962b8c,34613695141642247">这个吃过</d><d p="127.89900,1,25,16777215,1593162625,0,f962b8c,34613730185052165">小时候这个里面有飞行棋，为了小玩具都会买这个，然后上课偷偷玩</d><d p="40.42500,1,25,16777215,1593162951,0,d6d94f02,34613901090357251">96吃过</d><d p="12.78400,1,25,16777215,1593165576,0,5df3f380,34615276983549959">卫龙</d><d p="43.73500,1,25,16777215,1593165618,0,5df3f380,34615299046113287">吃过</d><d p="55.65800,1,25,16777215,1593165630,0,5df3f380,34615305273081863">96</d><d p="72.73900,1,25,16777215,1593165647,0,5df3f380,34615314200133635">没有</d><d p="82.77800,1,25,16777215,1593165657,0,5df3f380,34615319470800899">96没吃过</d><d p="98.41300,1,25,16777215,1593165672,0,5df3f380,34615327676432387">吃过</d><d p="121.14100,1,25,16777215,1593165695,0,5df3f380,34615339583537219">96吃过</d><d p="165.82900,1,25,16777215,1593165740,0,5df3f380,34615363025502213">96吃过</d><d p="182.63200,1,25,16777215,1593165757,0,5df3f380,34615371837210627">哈哈哈真实</d><d p="223.53200,1,25,16777215,1593165809,0,5df3f380,34615399319339011">96吃过</d><d p="190.84000,1,25,16777215,1593166963,0,27e14c18,34616004423712773">00吃瓜</d><d p="84.75900,1,25,16777215,1593169145,0,3c91f9a7,34617148429041669">00吃过</d><d p="115.27600,1,25,16777215,1593169176,0,3c91f9a7,34617164332269575">02吃过</d><d p="132.93600,1,25,16777215,1593169193,0,3c91f9a7,34617173571796999">02吃过</d><d p="19.97300,1,25,16777215,1593169271,0,13d4428d,34617214254448647">你圆了</d><d p="75.03900,1,25,16777215,1593171038,0,6e8e221f,34618140672917509">00后吃过</d><d p="222.20800,1,25,16777215,1593172751,0,74d1c939,34619039078678531">默默啃黄瓜的我路过</d><d p="47.38600,1,25,16777215,1593173390,0,988ec55d,34619373742718981">好可爱啊</d><d p="96.85800,1,25,16777215,1593173483,0,988ec55d,34619422536630275">05表示现在小学门口都还有</d><d p="19.02100,1,25,16777215,1593174578,0,e2252bbc,34619996547055619">？</d><d p="102.14400,1,25,16777215,1593174661,0,e2252bbc,34620040347648003">05吃过</d><d p="134.02800,1,25,16777215,1593174693,0,e2252bbc,34620057066668035">05吃过</d><d p="183.64000,1,25,16777215,1593174761,0,e2252bbc,34620092468690947">！麦丽素！我的最爱！</d><d p="247.32300,1,25,16777215,1593174825,0,e2252bbc,34620126290509831">05吃过</d><d p="165.47100,1,25,16777215,1593177095,0,e4060832,34621316396482567">吃过</d><d p="282.47200,1,25,16777215,1593177212,0,e4060832,34621377859289093">哇，想看你</d><d p="93.99200,1,25,16777215,1593177495,0,205ce9f,34621526351806469">05吃过</d><d p="116.35600,1,25,16777215,1593177528,0,205ce9f,34621543593017347">05吃过</d><d p="57.54000,1,25,16777215,1593178222,0,1649f8bd,34621907221872645">00吃过</d><d p="99.71700,1,25,16777215,1593178273,0,1649f8bd,34621933961609219">00吃过</d><d p="5.30100,1,25,16777215,1593178273,0,dacd2872,34621934080098309">帅哥你谁？</d><d p="120.52000,1,25,16777215,1593178294,0,1649f8bd,34621944863653891">00吃过</d><d p="131.70100,1,25,16777215,1593178305,0,1649f8bd,34621950712610819">00吃过</d><d p="183.14000,1,25,16777215,1593178457,0,1649f8bd,34622030335180805">00吃过</d><d p="73.56000,1,25,16777215,1593179118,0,99134a69,34622377272279047">00没吃过</d><d p="94.94000,1,25,16777215,1593179145,0,99134a69,34622391337877507">00吃过</d><d p="202.11900,1,25,16777215,1593179265,0,99134a69,34622453877047303">这几个都吃过</d><d p="219.83900,1,25,16777215,1593179293,0,99134a69,34622468742709255">小时候特别喜欢，小米锅巴</d><d p="129.82900,1,25,16777215,1593181788,0,390c73d8,34623776763150339">小时候盖辣条味儿吃的</d><d p="51.13300,1,25,16777215,1593182359,0,139aad7,34624076046663683">99的没吃过....</d><d p="79.50600,1,25,16777215,1593182413,0,139aad7,34624104838987783">99的还是没吃过，都没听说过</d><d p="96.67900,1,25,16777215,1593182479,0,139aad7,34624139254300677">99的终于吃过了！！上初中才吃上的</d><d p="15.23600,1,25,16777215,1593182525,0,5648e1aa,34624163401957381">老公来了</d><d p="116.73300,1,25,16777215,1593182533,0,139aad7,34624167682768899">99的吃过！！大学时舍友分享的</d><d p="43.18000,1,25,16777215,1593182563,0,5648e1aa,34624182962094083">99吃过</d><d p="134.56800,1,25,16777215,1593182631,0,139aad7,34624219078721539">99的吃过</d><d p="161.96000,1,25,16777215,1593182728,0,139aad7,34624269903200263">99的没见过，父母小时候条件不好，没有零食</d><d p="182.52500,1,25,16777215,1593182756,0,139aad7,34624284246147077">吃过吃过</d><d p="48.83900,1,25,16777215,1593183597,0,40da833e,34624725102624771">00表示之前包装不这样</d><d p="41.89900,1,25,16777215,1593183943,0,b83c7cb6,34624906496835589">95后吃过</d><d p="46.31300,1,25,16777215,1593184008,0,214d840c,34624940624314371">声音和长相不符</d><d p="116.31900,1,25,16777215,1593184033,0,b83c7cb6,34624954016727047">刚买了一大包虾条</d><d p="183.23900,1,25,16777215,1593184114,0,b83c7cb6,34624996641341443">618刚买了麦丽素。。。</d><d p="99.77900,1,25,16777215,1593185278,0,e1d81db7,34625606506250245">00吃过</d><d p="168.91900,1,25,16777215,1593185353,0,e1d81db7,34625646213726211">好多都没吃过</d><d p="189.59900,1,25,16777215,1593185381,0,e1d81db7,34625660499525639">正道的光</d><d p="281.63700,1,25,16777215,1593185490,0,e1d81db7,34625717959393287">辣子牛肉</d><d p="11.52400,1,25,16777215,1593185921,0,cfca8172,34625943789633541">胖了好多啊</d><d p="44.74300,1,25,16777215,1593186685,0,e5edc6ba,34626344181039109">00后没吃过</d><d p="79.19600,1,25,16777215,1593186719,0,e5edc6ba,34626362239614981">00后还没吃过</d><d p="103.10600,1,25,16777215,1593186743,0,e5edc6ba,34626374782156803">00后吃过</d><d p="125.34700,1,25,16777215,1593186765,0,e5edc6ba,34626386444419075">00后吃过</d><d p="205.63700,1,25,16777215,1593186846,0,e5edc6ba,34626428534784005">00后吃过</d><d p="82.39900,1,25,16777215,1593186849,0,acd55db8,34626430566400005">99吃过 好吃！</d><d p="129.71000,1,25,16777215,1593186894,0,acd55db8,34626453880438787">99吃过</d><d p="176.27400,1,25,16777215,1593186941,0,acd55db8,34626478298628103">99吃过</d><d p="95.00100,1,25,16777215,1593188758,0,63063616,34627431349878791">02吃过</d><d p="116.29700,1,25,16777215,1593188790,0,63063616,34627447991304197">02吃过</d><d p="118.24900,1,25,16777215,1593189074,0,f858ab50,34627596911116293">00吃过</d><d p="183.52900,1,25,16777215,1593189151,0,f858ab50,34627637429665797">00吃过</d><d p="201.53400,1,25,16777215,1593189178,0,f858ab50,34627651385688069">00吃过</d><d p="219.79500,1,25,16777215,1593189203,0,f858ab50,34627664539025415">00吃过</d><d p="30.36200,1,25,16777215,1593189472,0,78626798,34627805623353351">你胖了老邪你胖了</d><d p="136.88400,1,25,16777215,1593189586,0,78626798,34627865282609159">05吃过</d><d p="212.96800,1,25,16777215,1593189662,0,78626798,34627905132167171">05表示可</d><d p="7.97900,1,25,16777215,1593189946,0,1008b7b,34628054182002695">怎么感觉好像胖了</d><d p="24.41100,1,25,16777215,1593191173,0,dc3fe37c,34628697390055431">鼻子很好看</d><d p="211.62000,1,25,16777215,1593193183,0,c43259c0,34629751175905283">爱了爱了</d><d p="43.88000,1,25,16777215,1593193720,0,649884d2,34630032545021957">01吃过</d><d p="83.80900,1,25,16777215,1593193781,0,649884d2,34630064653467651">00没吃过</d><d p="92.90900,1,25,16777215,1593193801,0,649884d2,34630074889142275">00吃过</d><d p="115.38900,1,25,16777215,1593193831,0,649884d2,34630090830118919">00吃过</d><d p="125.72900,1,25,16777215,1593193850,0,649884d2,34630100778483715">00吃过</d><d p="158.58900,1,25,16777215,1593193891,0,649884d2,34630122580475909">00吃过</d><d p="181.20900,1,25,16777215,1593193921,0,649884d2,34630137926385669">00吃过</d><d p="199.76900,1,25,16777215,1593193946,0,649884d2,34630151276331011">00吃过</d><d p="218.78900,1,25,16777215,1593193973,0,649884d2,34630165298937863">00吃过</d><d p="255.02900,1,25,16777215,1593194015,0,649884d2,34630187377754117">00吃过</d><d p="39.37900,1,25,16777215,1593195429,0,630848eb,34630928508125189">00吃过</d><d p="78.56000,1,25,16777215,1593195473,0,630848eb,34630951943798791">00吃过</d><d p="93.54000,1,25,16777215,1593195493,0,630848eb,34630962161123331">00吃过</d><d p="115.84000,1,25,16777215,1593195520,0,630848eb,34630976535527429">00吃过</d><d p="128.23900,1,25,16777215,1593195537,0,630848eb,34630985375547399">00吃过</d><d p="162.13900,1,25,16777215,1593195579,0,630848eb,34631007570755587">00吃过</d><d p="201.76000,1,25,16777215,1593195624,0,630848eb,34631031075635271">00吃过</d><d p="49.19500,1,25,16777215,1593216376,0,d477cbda,34641911006887941">05吃过</d><d p="44.47800,1,25,16777215,1593221330,0,36572a1a,34644508205907975">00吃过</d><d p="80.68300,1,25,16777215,1593221366,0,36572a1a,34644527190900739">00没吃过</d><d p="99.26000,1,25,16777215,1593221385,0,36572a1a,34644536935841797">00吃过</d><d p="124.78600,1,25,16777215,1593221410,0,36572a1a,34644550291030021">00吃过</d><d p="135.66000,1,25,16777215,1593221431,0,36572a1a,34644561216667651">无花味果</d><d p="170.80400,1,25,16777215,1593221467,0,36572a1a,34644580250419205">00没吃过</d><d p="186.56000,1,25,16777215,1593221483,0,36572a1a,34644588510576645">00吃过</d><d p="223.42100,1,25,16777215,1593221520,0,36572a1a,34644607844220933">00吃过</d><d p="255.46500,1,25,16777215,1593221531,0,36572a1a,34644613472976901">00吃过</d><d p="41.04000,1,25,16777215,1593225789,0,438c1b36,34646846358421511">00吃过！</d><d p="98.33900,1,25,16777215,1593228323,0,ee3286c0,34648174530396167">00吃过</d><d p="222.54000,1,25,16777215,1593228457,0,ee3286c0,34648244983693315">00+吃过</d><d p="42.55100,1,25,16777215,1593230213,0,a0d674fc,34649165737230339">90</d><d p="103.31600,1,25,16777215,1593230274,0,a0d674fc,34649197598212099">90吃过</d><d p="121.90600,1,25,16777215,1593230293,0,a0d674fc,34649207344201731">牛羊90没吃过，应该是北方零食</d><d p="289.26500,1,25,16777215,1593230460,0,a0d674fc,34649295119450119">小当家呢</d><d p="111.45400,1,25,16777215,1593230629,0,f196d206,34649383579942919">？？知识盲区</d><d p="185.34500,1,25,16777215,1593231693,0,f5d06ced,34649941378859015">这个我非常喜欢</d><d p="43.83700,1,25,16777215,1593233140,0,e4fe2ab3,34650700095946757">00没吃过</d><d p="73.12700,1,25,16777215,1593233179,0,e4fe2ab3,34650720659570691">00没吃过</d><d p="92.88200,1,25,16777215,1593233206,0,e4fe2ab3,34650734975778823">00吃过</d><d p="165.09600,1,25,16777215,1593233287,0,e4fe2ab3,34650777240207365">00没吃过</d><d p="103.59700,1,25,16777215,1593233503,0,7fc1c7fe,34650890290855941">05吃过。</d><d p="212.30900,1,25,16777215,1593233611,0,7fc1c7fe,34650947291971589">05吃过。</d><d p="43.43900,1,25,16777215,1593235120,0,addaf17f,34651738110164997">05吃过</d><d p="99.97900,1,25,16777215,1593235182,0,addaf17f,34651770561495043">05吃过</d><d p="201.55900,1,25,16777215,1593235299,0,addaf17f,34651832119721989">05现在还在吃</d><d p="53.53400,1,25,16777215,1593235556,0,499f06c7,34651967002771459">05吃过</d><d p="73.97400,1,25,16777215,1593239294,0,9c636a35,34653926519734277">98吃过</d><d p="57.11900,1,25,16777215,1593239567,0,344cc975,34654069841723397">00没有</d><d p="107.94000,1,25,16777215,1593239618,0,344cc975,34654096504389635">06没有</d><d p="91.14000,1,25,15772458,1593241147,0,f139acf4,34654898312183811">我觉得老邪只是想吃而已，和回忆关系不大</d><d p="33.50000,1,25,16777215,1593242394,0,350d744b,34655551825117189">还是不看真人比较习惯</d><d p="38.53800,1,25,16777215,1593244719,0,f4632461,34656771014918149">00没吃过</d><d p="69.69800,1,25,16777215,1593244756,0,f4632461,34656790236364803">00吃过</d><d p="93.25800,1,25,16777215,1593244788,0,f4632461,34656807091175431">00吃过</d><d p="127.55800,1,25,16777215,1593244835,0,f4632461,34656831477907459">00吃过</d><d p="141.07800,1,25,16777215,1593244874,0,f4632461,34656851967082503">我买的5毛一包</d><d p="153.75800,1,25,16777215,1593244891,0,f4632461,34656860949708805">哈哈哈哈哈哈哈哈</d><d p="157.49800,1,25,16777215,1593244900,0,f4632461,34656865921531911">00没吃过</d><d p="183.41800,1,25,16777215,1593244930,0,f4632461,34656881712562181">00吃过</d><d p="200.67800,1,25,16777215,1593244952,0,f4632461,34656893020930055">00吃过</d><d p="204.45800,1,25,16777215,1593244960,0,f4632461,34656897435959299">奶片糖</d><d p="219.07800,1,25,16777215,1593244983,0,f4632461,34656909079347205">00现在还在吃</d><d p="240.31800,1,25,16777215,1593245014,0,f4632461,34656925501095941">哈哈哈哈哈哈哈哈哈，神奇联动</d><d p="252.05800,1,25,16777215,1593245031,0,f4632461,34656934543491077">00没吃过</d><d p="253.45800,1,25,16777215,1593245044,0,f4632461,34656941313097731">有红油板筋吗？？？？</d><d p="89.87000,1,25,38979,1593245457,0,2076a801,34657157714018309">00后吃过！</d><d p="122.73200,1,25,38979,1593245490,0,2076a801,34657174871867397">我的最爱！</d><d p="27.08100,5,25,15138834,1593246311,0,fab7dd62,34657605355831299">06后报道</d><d p="32.98100,4,25,15138834,1593246339,0,fab7dd62,34657620043759621">06后报道</d><d p="37.50100,1,25,15138834,1593246354,0,fab7dd62,34657628058550275">06路过</d><d p="50.78100,1,25,15138834,1593246460,0,fab7dd62,34657683549716483">06后表示，吃的是干脆面，包装是凯甲勇士的内种，里面就有集卡的</d><d p="77.48100,1,25,15138834,1593246540,0,fab7dd62,34657725601808389">06后表示，这个吃过，包装不一样罢了，没听过这名字</d><d p="93.58100,1,25,15138834,1593246574,0,fab7dd62,34657743555526663">06后表示我弟都吃过</d><d p="105.02100,1,25,16707842,1593246592,0,fab7dd62,34657752638291975">？？？？？？</d><d p="106.94100,1,25,16707842,1593246600,0,fab7dd62,34657757093691395">什么？？？？？</d><d p="170.58100,1,25,16707842,1593246688,0,fab7dd62,34657803305484293">06后表示，吃过，包装不一样</d><d p="180.06100,1,25,15138834,1593246728,0,fab7dd62,34657823984451589">吃过，现在大超市还有买的</d><d p="188.44100,1,25,15138834,1593246751,0,fab7dd62,34657836351881221">邪少的兰花指</d><d p="199.96100,1,25,15138834,1593246768,0,fab7dd62,34657845302001671">吃过06</d><d p="218.36100,1,25,15138834,1593246789,0,fab7dd62,34657856159481861">06后表吃过</d><d p="227.50100,1,25,15138834,1593246811,0,fab7dd62,34657867863162885">06后表超好吃</d><d p="263.00100,1,25,15138834,1593246862,0,fab7dd62,34657894352289795">06后表吃过</d><d p="276.14100,1,25,15138834,1593246881,0,fab7dd62,34657904549691399">哈哈哈哈哈哈哈哈哈哈哈</d><d p="38.01400,1,25,16777215,1593248455,0,4930074,34658729635872773">10吃过</d><d p="65.43000,1,25,16777215,1593249200,0,f486dd81,34659120075767811">这东西不是现在也有吗？教超里</d><d p="46.35900,1,25,16777215,1593249574,0,ca8ba428,34659316512325637">00吃过</d><d p="75.88200,1,25,16777215,1593249604,0,ca8ba428,34659331983540231">00吃过</d><d p="102.52900,1,25,16777215,1593249631,0,ca8ba428,34659345946902531">大家都吃过吧</d><d p="124.42700,1,25,16777215,1593249653,0,ca8ba428,34659357432479747">对啊都是吃过的</d><d p="137.29100,1,25,16777215,1593249665,0,ca8ba428,34659364173250563">它是萝卜干</d><d p="160.94000,1,25,16777215,1593249689,0,ca8ba428,34659376586293255">吃过</d><d p="187.31900,1,25,16777215,1593249715,0,ca8ba428,34659390399709187">00吃过</d><d p="206.23100,1,25,16777215,1593249734,0,ca8ba428,34659400329199623">00吃过 喜欢</d><d p="223.63600,1,25,16777215,1593249815,0,ca8ba428,34659442457837571">吃过00</d><d p="253.55300,1,25,16777215,1593249845,0,ca8ba428,34659458155544583">00吃过</d><d p="92.70800,1,25,16777215,1593250776,0,8bcfb2e,34659946632052739">00吃过</d><d p="117.29000,1,25,16777215,1593250811,0,8bcfb2e,34659964699541509">00吃过</d><d p="126.51200,1,25,16777215,1593250828,0,8bcfb2e,34659973681643527">00吃过</d><d p="181.46600,1,25,16777215,1593250902,0,8bcfb2e,34660012344213507">00吃过，哇这个贼喜欢吃</d><d p="201.78300,1,25,16777215,1593250931,0,8bcfb2e,34660027757232131">吃过00</d><d p="201.78300,1,25,16777215,1593250944,0,8bcfb2e,34660034447671299">00吃过</d><d p="227.96300,1,25,16777215,1593250977,0,8bcfb2e,34660051758612485">00吃过</d><d p="23.30000,1,25,16777215,1593251898,0,76d27cb4,34660534901014533">老邪好胖</d><d p="79.22800,1,25,16777215,1593251954,0,76d27cb4,34660564219199493">00没吃过</d><d p="169.16800,1,25,16777215,1593252044,0,76d27cb4,34660611436576771">00没见过</d><d p="131.56100,1,25,16777215,1593253731,0,ef09cea6,34661495492050951">我喜欢！！！</d><d p="154.85700,1,25,16777215,1593253761,0,ef09cea6,34661511577731077">一口放嘴里</d><d p="171.03200,1,25,16777215,1593253777,0,ef09cea6,34661520067002375">99没吃过</d><d p="189.80000,1,25,16777215,1593253796,0,ef09cea6,34661529901596677">麦丽素！！！</d><d p="198.71100,1,25,16777215,1593253805,0,ef09cea6,34661534566187011">我的最爱！！！</d><d p="215.49900,1,25,16777215,1593253822,0,ef09cea6,34661543373701125">奶片！！！</d><d p="229.22500,1,25,16777215,1593253836,0,ef09cea6,34661550595244039">不喜欢这个！</d><d p="264.66200,1,25,16777215,1593253871,0,ef09cea6,34661569140883461">高级哈哈哈哈哈哈哈哈哈哈哈哈哈</d><d p="280.58400,1,25,16777215,1593253887,0,ef09cea6,34661577514287111">哈哈哈哈哈  你胖了</d><d p="87.01800,1,25,16777215,1593254612,0,e3a5bf67,34661957400788995">95表示没吃过牛羊</d><d p="182.65800,1,25,16777215,1593254714,0,e3a5bf67,34662011070054467">大爱麦丽素！！！</d><d p="281.24000,1,25,16777215,1593255005,0,786c0175,34662163502071811">臭干子</d><d p="46.99800,1,25,16777215,1593256287,0,5b0123ae,34662836035649543">00后吃过</d><d p="74.98600,1,25,16777215,1593256315,0,5b0123ae,34662850737209351">00后吃过</d><d p="32.30400,1,25,16777215,1593256638,0,885bd4e1,34663019860983813">感觉声音搭不上长相啊，刚开始以为是恶搞，以为不是本人呢哈哈哈</d><d p="269.19300,1,25,16777215,1593258060,0,6a6da665,34663765302050821">哈哈哈哈哈90后都吃过</d><d p="121.62600,1,25,16777215,1593261576,0,6e8589f4,34665609003794435">03来了</d><d p="45.39500,1,25,16777215,1593261714,0,16aa6266,34665681381752839">98吃过</d><d p="98.65600,1,25,16777215,1593261768,0,16aa6266,34665709281214469">98吃过</d><d p="131.69800,1,25,16777215,1593261801,0,16aa6266,34665726609457155">98吃过</d><d p="189.88600,1,25,16777215,1593261859,0,16aa6266,34665757101522947">98小时候很爱吃</d><d p="254.38600,1,25,16777215,1593261923,0,16aa6266,34665790946410503">确实</d><d p="264.62000,1,25,16777215,1593261934,0,16aa6266,34665796280516613">98吃过</d><d p="90.16600,1,25,16777215,1593262815,0,dba34186,34666258481807363">逐渐吃播</d><d p="73.89500,1,25,16777215,1593262974,0,f0030bef,34666341592465411">00没有</d><d p="71.26100,1,25,16777215,1593262975,0,3d042d14,34666342071140355">00后吃过</d><d p="124.88400,1,25,16777215,1593263025,0,f0030bef,34666368323813381">00吃过</d><d p="37.13900,1,25,16777215,1593263766,0,9ff46978,34666756709023751">00吃过</d><d p="125.41900,1,25,16777215,1593263865,0,9ff46978,34666809115279367">00吃过</d><d p="199.62000,1,25,16777215,1593263950,0,9ff46978,34666853206327303">00吃过</d><d p="250.23900,1,25,16777215,1593264007,0,9ff46978,34666883535339523">00吃过</d><d p="130.28900,1,25,16777215,1593266009,0,7f67cf4e,34667933002629125">刚刚是味咪</d><d p="119.36800,1,25,16777215,1593266463,0,7ed9bb53,34668170997923847">05吃过</d><d p="127.11900,1,25,16777215,1593266477,0,7ed9bb53,34668178237292549">05吃过</d><d p="67.13700,1,25,16777215,1593266654,0,b958cb02,34668271076114435">六丁目</d><d p="212.51400,1,25,16777215,1593266799,0,b958cb02,34668347265646595">怪不得你胖，该</d><d p="223.19500,1,25,16777215,1593266810,0,b958cb02,34668352880246787">唐僧肉</d><d p="284.55900,1,25,16777215,1593266871,0,b958cb02,34668385029062661">唐僧肉</d><d p="84.11500,1,25,16777215,1593267083,0,3abdee6,34668496221110275">95吃过</d><d p="145.95900,1,25,16777215,1593268923,0,a75b05f2,34669460484784135">00吃过</d><d p="90.21900,1,25,16777215,1593269025,0,41ccbecf,34669514454466567">95后没吃过</d><d p="127.69900,1,25,16777215,1593269086,0,41ccbecf,34669545978331141">98吃过，一直不喜欢，长大了才知道是萝卜做的，那怪我不喜欢哈哈哈哈</d><d p="200.46000,1,25,16777215,1593269172,0,41ccbecf,34669591361224709">现在的奶片好多种口味，都好好吃</d><d p="47.29700,1,25,16777215,1593269512,0,3ee44028,34669769561473031">05吃过。</d><d p="72.85700,1,25,16777215,1593269542,0,3ee44028,34669785001754629">05吃过。</d><d p="93.59700,1,25,16777215,1593269569,0,3ee44028,34669799524532229">05吃过。</d><d p="117.53700,1,25,16777215,1593269601,0,3ee44028,34669816304893957">05吃过</d><d p="128.15700,1,25,16777215,1593269615,0,3ee44028,34669823541116933">05全吃过。</d><d p="194.17400,1,25,16777215,1593271471,0,d783b552,34670796596051975">这动作好gay</d><d p="37.69100,1,25,16777215,1593272028,0,886af91e,34671088829464581">00吃过</d><d p="226.34500,1,25,16777215,1593272804,0,d783b552,34671495579435011">兰花指就很gay</d><d p="280.38200,1,25,16777215,1593273049,0,7982e6aa,34671624143765511">下一期不会都是空袋子了吧</d><d p="42.60800,1,25,16777215,1593277306,0,75ae2114,34673855776161799">07吃过</d><d p="77.12300,1,25,16777215,1593277346,0,75ae2114,34673876587249669">07没吃过</d><d p="99.12400,1,25,16777215,1593277368,0,75ae2114,34673888189743109">07经常吃</d><d p="123.62400,1,25,16777215,1593277392,0,75ae2114,34673900876988423">07没吃过</d><d p="208.15600,1,25,16777215,1593277477,0,75ae2114,34673945484460039">07最爱</d><d p="234.17500,1,25,16777215,1593278039,0,4d969ff5,34674239903629317">二阶堂红丸</d><d p="44.04000,1,25,16777215,1593300970,0,78e1cae0,34686262565666823">00吃过</d><d p="71.64000,1,25,16777215,1593301005,0,78e1cae0,34686280869085187">00还是吃过</d><d p="160.79900,1,25,16777215,1593301101,0,78e1cae0,34686331406254085">00没吃过</d><d p="45.61800,1,25,16777215,1593301802,0,f22387b0,34686698678386695">90没吃过</d><d p="70.29800,1,25,16777215,1593301832,0,f22387b0,34686714685947911">97没吃过</d><d p="95.45800,1,25,16777215,1593301864,0,f22387b0,34686731554914311">97吃过</d><d p="116.89800,1,25,16777215,1593301891,0,f22387b0,34686745355223047">吃过</d><d p="127.95800,1,25,16777215,1593301909,0,f22387b0,34686755052453891">97吃过，不好吃</d><d p="159.57800,1,25,16777215,1593301946,0,f22387b0,34686774253977605">97没吃过</d><d p="201.07800,1,25,16777215,1593301999,0,f22387b0,34686802094194695">97吃过，这个好吃的</d><d p="219.39800,1,25,16777215,1593302029,0,f22387b0,34686817950760963">97吃过，以前不是这个包装</d><d p="40.17000,1,25,16777215,1593308354,0,5197423d,34690133749399555">99吃过</d><d p="57.14200,1,25,16777215,1593313173,0,84d2d70c,34692660280164359">现在超市不还是有吗</d><d p="288.71100,1,25,16777215,1593313439,0,84d2d70c,34692799683624967">00后爱：卜卜星</d><d p="9.69600,1,25,16777215,1593314169,0,6a9b4501,34693182790303751">邪邪你又胖了</d><d p="48.69600,1,25,16777215,1593314208,0,6a9b4501,34693203302547461">90没吃过</d><d p="113.19600,1,25,16777215,1593314273,0,6a9b4501,34693237155299335">90吃过</d><d p="121.19600,1,25,16777215,1593314281,0,6a9b4501,34693241266765829">刺激，哈哈哈</d><d p="132.69600,1,25,16777215,1593314292,0,6a9b4501,34693247228444679">90吃过</d><d p="153.69500,1,25,16777215,1593314313,0,6a9b4501,34693258137305091">95后没吃过</d><d p="162.19600,1,25,16777215,1593314322,0,6a9b4501,34693262742650883">90吃过</d><d p="185.69600,1,25,16777215,1593314345,0,6a9b4501,34693274994212869">哈哈哈，对</d><d p="193.69500,1,25,16777215,1593314353,0,6a9b4501,34693279331647493">仙丹</d><d p="209.20300,1,25,16777215,1593314369,0,6a9b4501,34693287291387909">95后吃过</d><d p="229.19600,1,25,16777215,1593314389,0,6a9b4501,34693297890394117">95吃过，这个很好吃</d><d p="255.19600,1,25,16777215,1593314415,0,6a9b4501,34693311568543747">哈哈哈哈哈哈哈</d><d p="284.19600,1,25,16777215,1593314444,0,6a9b4501,34693326787575813">牛肉干</d><d p="282.48400,1,25,16777215,1593314486,0,6a9b4501,34693348682366981">臭干子，牛肉干(蛋白质大片片)</d><d p="288.49100,1,25,16777215,1593314492,0,6a9b4501,34693351843299333">唐僧肉</d><d p="44.01600,1,25,16777215,1593318360,0,1d7f37d1,34695379792953347">00吃过</d><d p="96.75100,1,25,16777215,1593318412,0,1d7f37d1,34695407439708163">00吃过</d><d p="119.83500,1,25,16777215,1593318435,0,1d7f37d1,34695419524022275">00吃过</d><d p="131.06300,1,25,16777215,1593318447,0,1d7f37d1,34695425422786567">00吃过</d><d p="173.94300,1,25,16777215,1593318490,0,1d7f37d1,34695448034803715">00没吃过</d><d p="186.57800,1,25,16777215,1593318502,0,1d7f37d1,34695454554849287">00吃过</d><d p="203.80900,1,25,16777215,1593318520,0,1d7f37d1,34695463577321477">00吃过</d><d p="223.59400,1,25,16777215,1593318539,0,1d7f37d1,34695473945116679">00吃过</d><d p="255.94000,1,25,16777215,1593318572,0,1d7f37d1,34695490904784899">00没吃过</d><d p="23.12200,1,25,16777215,1593319980,0,9258e94c,34696229270585349">老邪太好看了</d><d p="44.61400,1,25,16777215,1593320001,0,9258e94c,34696240565321735">老邪是不是该洗头了</d><d p="44.19700,1,25,16777215,1593320222,0,402d3d2b,34696355963731975">老邪用的什么牌子的牙膏</d><d p="120.20300,1,25,16777215,1593320343,0,a1246d94,34696419818340359">05吃过</d><d p="126.76300,1,25,16777215,1593320357,0,a1246d94,34696426884694021">05吃过</d><d p="257.16400,1,25,16777215,1593320504,0,a1246d94,34696504089247747">05吃过</d><d p="21.82000,1,25,16777215,1593321731,0,35255af1,34697147089682439">胖了</d><d p="42.72500,1,25,16777215,1593323163,0,20fa7f84,34697897895264263">00吃过</d><d p="72.92700,1,25,16777215,1593323187,0,20fa7f84,34697910478176263">00吃过</d><d p="107.08700,1,25,16777215,1593324391,0,2d210d4f,34698542051753991">00吃过</d><d p="41.90200,1,25,16777215,1593326210,0,66170875,34699495561232391">00吃过</d><d p="95.55200,1,25,16777215,1593326254,0,66170875,34699518834900995">00吃过</d><d p="82.45200,1,25,16777215,1593327240,0,8e90ccf6,34700035599892485">99盲区，没吃过</d><d p="97.86100,1,25,16777215,1593327255,0,8e90ccf6,34700043664490501">99吃过</d><d p="120.55400,1,25,16777215,1593327278,0,8e90ccf6,34700055613014023">99吃过</d><d p="130.71300,1,25,16777215,1593327288,0,8e90ccf6,34700060898885635">99吃过</d><d p="165.22900,1,25,16777215,1593327323,0,8e90ccf6,34700078989443077">99吃过！</d><d p="186.01900,1,25,16777215,1593327344,0,8e90ccf6,34700089897779203">99吃过</d><d p="221.19900,1,25,16777215,1593327379,0,8e90ccf6,34700108387844103">99现在还吃</d><d p="265.85300,1,25,16777215,1593327423,0,8e90ccf6,34700131792584711">99吃过</d><d p="60.18100,1,25,16777215,1593328854,0,b26d5f92,34700881851580419">00后吃过也是童年回忆</d><d p="44.43700,1,25,16777215,1593330953,0,f543a910,34701982560681989">00吃过</d><d p="15.13300,1,25,16777215,1593331753,0,2fda5ee9,34702401719500807">哈哈哈哈哈哈哈哈哈哈哈哈哈哈哈</d><d p="42.08300,1,25,16777215,1593331817,0,2fda5ee9,34702435320070147">00吃过</d><d p="67.78800,1,25,16777215,1593331843,0,2fda5ee9,34702448801611779">00吃过</d><d p="77.48100,1,25,16777215,1593331852,0,2fda5ee9,34702453887205381">这个好吃的！</d><d p="96.23300,1,25,16777215,1593331871,0,2fda5ee9,34702463710265347">00吃过N</d><d p="118.51100,1,25,16777215,1593331949,0,2fda5ee9,34702504661876743">吃过</d><d p="127.97500,1,25,16777215,1593331959,0,2fda5ee9,34702509629505539">吃过！</d><d p="150.22800,1,25,16777215,1593331981,0,2fda5ee9,34702521283379207">以前不是很喜欢吃这个，后来真香</d><d p="161.54000,1,25,16777215,1593331992,0,2fda5ee9,34702527227756547">00没吃过</d><d p="192.21900,1,25,16777215,1593332057,0,9b6718e5,34702561129791491">伸腿瞪眼丸</d><d p="50.15400,1,25,16777215,1593332259,0,582a67b2,34702667074240519">01吃过</d><d p="61.38400,1,25,16777215,1593333283,0,dbc9c2be,34703203742253059">00吃过</d><d p="50.28900,1,25,16777215,1593335729,0,b5a89403,34704486177964039">00吃过</d><d p="69.84900,1,25,16777215,1593335756,0,b5a89403,34704500301758469">00吃过！好吃的</d><d p="215.40900,1,25,16777215,1593335931,0,b5a89403,34704592108781573">这个超唉</d><d p="227.04900,1,25,16777215,1593335945,0,b5a89403,34704599709908999">好吃！</d><d p="93.09800,1,25,16777215,1593336341,0,e1ebf64f,34704806976684039">00盲区</d><d p="72.16900,1,25,16777215,1593337332,0,6286a818,34705326983872519">98没吃过</d><d p="40.94200,1,25,16777215,1593341857,0,fbc280b5,34707699110772741">90吃过</d><d p="72.76100,1,25,16777215,1593341889,0,fbc280b5,34707715781033989">90没吃过</d><d p="96.89200,1,25,16777215,1593341913,0,fbc280b5,34707728539058181">90吃过</d><d p="119.63300,1,25,16777215,1593341936,0,fbc280b5,34707740344451077">90吃过</d><d p="36.50400,1,25,16777215,1593341991,0,cb6c06d6,34707769158795271">97没吃过</d><d p="37.01900,1,25,16777215,1593342427,0,ccd92fa,34707997804986371">09吃过</d><d p="68.70000,1,25,16777215,1593342464,0,ccd92fa,34708017258168323">09没吃过</d><d p="92.68000,1,25,16777215,1593342493,0,ccd92fa,34708032514949127">09吃过</d><d p="114.94000,1,25,16777215,1593342534,0,ccd92fa,34708053987688455">09吃过</d><d p="130.26200,1,25,16777215,1593342550,0,ccd92fa,34708062281400327">09没吃过</d><d p="162.67300,1,25,16777215,1593342582,0,ccd92fa,34708079277768711">09没吃过</d><d p="184.59800,1,25,16777215,1593342605,0,ccd92fa,34708091073724421">09吃过</d><d p="203.92400,1,25,16777215,1593342624,0,ccd92fa,34708101208735747">09吃过</d><d p="223.34900,1,25,16777215,1593342643,0,ccd92fa,34708111393030149">09没吃过</d><d p="257.65300,1,25,16777215,1593342678,0,ccd92fa,34708129372962819">09没吃过</d><d p="100.20600,1,25,16777215,1593345744,0,22aca4eb,34709737301868547">00吃过</d><d p="43.90400,1,25,16777215,1593352791,0,14b4fd00,34713431539974151">00吃过</d><d p="77.78500,1,25,16777215,1593352824,0,14b4fd00,34713449243082819">00没吃过</d><d p="96.98000,1,25,16777215,1593352844,0,14b4fd00,34713459335102471">00吃过！！！</d><d p="119.22900,1,25,16777215,1593352866,0,14b4fd00,34713470974296069">00吃过</d><d p="130.34200,1,25,16777215,1593352877,0,14b4fd00,34713476796514307">00吃过</d><d p="171.22900,1,25,16777215,1593352918,0,14b4fd00,34713498247233539">00没吃过</d><d p="186.58200,1,25,16777215,1593352933,0,14b4fd00,34713506298724357">00吃过</d><d p="208.30800,1,25,16777215,1593352955,0,14b4fd00,34713517697269763">00吃过</d><d p="222.71100,1,25,16777215,1593352969,0,14b4fd00,34713525258551303">00吃过</d><d p="259.27500,1,25,16777215,1593353006,0,14b4fd00,34713544479473667">00吃过</d><d p="51.98900,1,25,16777215,1593353123,0,b2f76f58,34713605868879877">00没吃过</d><d p="119.60900,1,25,16777215,1593353163,0,b2f76f58,34713626728726535">00吃过</d><d p="142.89900,1,25,16777215,1593353200,0,b2f76f58,34713646386380803">00吃过</d><d p="205.38700,1,25,16777215,1593353263,0,b2f76f58,34713679393980419">00吃过</d><d p="225.66700,1,25,16777215,1593353284,0,b2f76f58,34713690224197639">00吃过</d><d p="77.47900,1,25,16777215,1593354688,0,bfb74883,34714426378027013">00没吃过</d><d p="129.91500,1,25,16777215,1593355526,0,be0eacef,34714865760731143">不是味咪吗</d><d p="111.61900,1,25,16777215,1593356732,0,1366549c,34715498041049095">你这动作??????！！！</d><d p="204.60500,1,25,16777215,1593358148,0,884f1516,34716240117235719">兰花指哈哈哈</d><d p="98.97300,1,25,16777215,1593359637,0,598ce050,34717021091921923">99吃过</d><d p="17.75400,1,25,16777215,1593360746,0,c4c52e92,34717602577121287">？？？？？</d><d p="43.43900,1,25,16777215,1593360772,0,c4c52e92,34717616014622723">？？？</d><d p="47.51200,1,25,16777215,1593360776,0,c4c52e92,34717618145329155">过分了</d><d p="118.49500,1,25,16777215,1593360847,0,c4c52e92,34717655415390211">好吃</d><d p="131.35700,1,25,16777215,1593360860,0,c4c52e92,34717662129422339">00吃过</d><d p="164.51900,1,25,16777215,1593360893,0,c4c52e92,34717679508520967">哈哈哈吃过</d><d p="92.84000,1,25,16777215,1593367490,0,399ee245,34721138422054915">05后也吃过</d><d p="116.11000,1,25,16777215,1593367513,0,399ee245,34721150488543239">05后也吃过</d><d p="39.37200,1,25,16777215,1593374242,0,1df7fdb,34724678313443331">80</d><d p="60.87300,1,25,16777215,1593374264,0,1df7fdb,34724689564139523">英雄卡 我卖了1000多块钱</d><d p="50.82400,1,25,16777215,1593391885,0,3c1813dc,34733928057143301">90吃过</d><d p="220.17900,1,25,16777215,1593392063,0,3c1813dc,34734021647269893">90吃过</d><d p="102.04800,1,25,16777215,1593392737,0,e952f3e,34734374703333381">00吃过！</d><d p="125.67900,1,25,16777215,1593392760,0,e952f3e,34734387072860165">我超喜欢吃！！！</d><d p="103.26400,1,25,16777215,1593394633,0,986e87e2,34735369211084803">00吃过</d><d p="122.14200,1,25,16777215,1593394652,0,986e87e2,34735379064553477">04吃过</d><d p="127.00800,1,25,16777215,1593397394,0,290956d4,34736816674308099">无敌</d><d p="42.55500,1,25,16777215,1593399822,0,c9ea0b8,34738089280143363">05</d><d p="21.36600,1,25,16777215,1593400024,0,fcaa0551,34738195601031173">开屏大脸</d><d p="82.35300,1,25,16777215,1593400085,0,fcaa0551,34738227571064837">没吃过哈哈哈哈</d><d p="97.04800,1,25,16777215,1593400100,0,fcaa0551,34738235289108485">00吃过！</d><d p="130.26100,1,25,16777215,1593400133,0,fcaa0551,34738252791414791">吃过！！！</d><d p="183.42700,1,25,16777215,1593400186,0,fcaa0551,34738280580251653">哇 这个看起来好好吃哈哈哈哈</d><d p="207.02600,1,25,16777215,1593400210,0,fcaa0551,34738293081374723">00吃过！！！</d><d p="51.61200,1,25,16777215,1593401096,0,e154b9b1,34738757190549509">02吃过</d><d p="48.43600,1,25,16777215,1593405571,0,3b33418e,34741103759458311">90吃过</d><d p="73.26600,1,25,16777215,1593405596,0,3b33418e,34741116753936387">90没有</d><d p="165.46000,1,25,16777215,1593405688,0,3b33418e,34741165100630023">没吃过</d><d p="94.57900,1,25,16777215,1593406653,0,6a439eb9,34741671178534919">04吃过</d><d p="117.43900,1,25,16777215,1593406684,0,6a439eb9,34741687240097795">04吃过</d><d p="124.91900,1,25,16777215,1593406697,0,6a439eb9,34741694051647491">04吃过</d><d p="13.01000,1,25,16777215,1593407262,0,ccbd183a,34741990105022469">老邪你好像胖了</d><d p="224.48200,1,25,16777215,1593407948,0,f5372fd2,34742349726220291">20后吃过</d><d p="65.39600,1,25,16777215,1593409372,0,a3055cc,34743096279826439">牙好白</d><d p="102.63000,1,25,16707842,1593411839,0,db4d8b69,34744389627543557">01吃过</d><d p="137.68000,1,25,16707842,1593411906,0,db4d8b69,34744425016983557">01吃过</d><d p="212.34400,1,25,16707842,1593411996,0,db4d8b69,34744472175640583">01   这是我的爱！！！</d><d p="72.06200,1,25,16777215,1593414079,0,fd246e7e,34745564143812613">98吃过</d><d p="201.08600,1,25,16777215,1593415242,0,64369cae,34746173834657797">不要停下来啊</d><d p="201.08600,1,25,16777215,1593415250,0,64369cae,34746177986494471">不要停下来啊</d><d p="45.62200,1,25,16777215,1593416559,0,7be6d789,34746864639148039">04吃过</d><d p="94.82200,1,25,16777215,1593416616,0,7be6d789,34746894350024709">04吃过</d><d p="119.84200,1,25,16777215,1593416648,0,7be6d789,34746911224758279">04吃过</d><d p="53.64600,1,25,16777215,1593417130,0,3e4315c4,34747163918991365">广东90后表示，我们的是小当家</d><d p="118.05400,1,25,16777215,1593417198,0,3e4315c4,34747199282216963">爆炸糖</d><d p="271.05400,1,25,16777215,1593417351,0,3e4315c4,34747279597371399">星球杯</d><d p="39.87900,1,25,16777215,1593417909,0,13e1c22c,34747572460978179">00吃过</d><d p="81.32000,1,25,16777215,1593417964,0,13e1c22c,34747601077665797">00没吃过</d><d p="94.42000,1,25,16777215,1593417983,0,13e1c22c,34747610987233287">00吃过</d><d p="221.38000,1,25,16777215,1593418123,0,13e1c22c,34747684243374087">00很爱吃</d><d p="15.02400,1,25,16777215,1593419013,0,d9149779,34748151312678919">胖了胖了</d><d p="23.81600,1,25,16777215,1593419022,0,d9149779,34748155919597575">胖了嘿</d><d p="282.18200,1,25,15138834,1593420905,0,91296d1b,34749143182213127">虾扯蛋</d><d p="139.00400,1,25,16777215,1593425527,0,69a1d1aa,34751566094270467">牙齒好白，介紹一下你用的牙膏!</d><d p="89.82000,1,25,16777215,1593426713,0,88e3c491,34752188220178437">吃过，但是不是这个包装了</d><d p="9.01900,1,25,16777215,1593427096,0,c4031d2b,34752388976345091">老邪胖了哈哈哈哈哈哈哈哈哈哈哈哈哈</d><d p="69.41700,1,25,16777215,1593427169,0,c4031d2b,34752427309137923">00后吃过</d><d p="89.53400,1,25,16777215,1593427224,0,c4031d2b,34752455871823875">老邪是不是该洗头了hhhhhhhhh</d><d p="108.91400,1,25,16777215,1593427256,0,c4031d2b,34752472726634499">？？？什么用途</d><d p="286.39400,1,25,16777215,1593427501,0,c4031d2b,34752601448251399">大长今，唐僧肉</d><d p="98.76600,5,25,13369971,1593428279,0,ccb067c8,34753009191223299">建议现在不要买跳跳糖 多看新闻</d><d p="53.03100,1,25,16777215,1593428632,0,91db200,34753194147446789">90吃过</d><d p="78.37400,1,25,16777215,1593428657,0,91db200,34753207431856135">95吃过</d><d p="45.65200,1,25,16777215,1593433269,0,896d6156,34755625215852551">00没吃过</d><d p="71.76500,1,25,16777215,1593433306,0,896d6156,34755644653305863">00没吃过</d><d p="94.63400,1,25,16777215,1593433344,0,896d6156,34755664595124229">00没吃过</d><d p="98.68700,1,25,16777215,1593433386,0,896d6156,34755686575898627">00吃过</d><d p="100.47900,1,25,16777215,1593433396,0,896d6156,34755691891130371">00吃过</d><d p="101.84400,1,25,16777215,1593433406,0,896d6156,34755697031250055">00吃过</d><d p="117.63100,1,25,16777215,1593433429,0,896d6156,34755709432758275">00吃过</d><d p="132.13700,1,25,16777215,1593433456,0,896d6156,34755723534008323">00吃过</d><d p="40.96200,1,25,16777215,1593436200,0,21755fa,34757162199678979">98没吃过</d><d p="79.46200,1,25,16777215,1593436239,0,21755fa,34757182388436997">98还是没吃过</d><d p="94.96200,1,25,16777215,1593436255,0,21755fa,34757190623428611">98吃过！</d><d p="116.96200,1,25,16777215,1593436277,0,21755fa,34757202294603783">98吃过</d><d p="134.46300,1,25,16777215,1593436294,0,21755fa,34757211320745987">98吃过</d><d p="161.46200,1,25,16777215,1593436321,0,21755fa,34757225540485127">98没吃过</d><d p="183.46300,1,25,16777215,1593436343,0,21755fa,34757237053849607">98吃过</d><d p="200.96300,1,25,16777215,1593436361,0,21755fa,34757246291279879">98吃过</d><d p="224.46300,1,25,16777215,1593436384,0,21755fa,34757258599989255">98这个好吃！</d><d p="253.46300,1,25,16777215,1593436413,0,21755fa,34757273781272579">98吃过</d><d p="40.25900,1,25,16777215,1593438845,0,dd36e427,34758548778909703">00吃过</d><d p="42.18000,1,25,16777215,1593439294,0,dd98d752,34758784322109443">00吃过</d><d p="68.97900,1,25,16777215,1593439363,0,dd98d752,34758820399939591">00吃过这个真的特别好吃我大腮帮就是这个还有辣条还有一众零食练出来的</d><d p="93.89900,1,25,16777215,1593439402,0,dd98d752,34758840860803077">00吃过 我觉得可能我上学早吧哈哈哈</d><d p="116.45900,1,25,16777215,1593439428,0,dd98d752,34758854460833795">00吃过</d><d p="125.53900,1,25,16777215,1593439440,0,dd98d752,34758860851904515">00吃过</d><d p="159.94000,1,25,16777215,1593439479,0,dd98d752,34758881054818309">00没见过</d><d p="180.49900,1,25,16777215,1593439507,0,dd98d752,34758895883780099">00吃过</d><d p="219.30000,1,25,16777215,1593439550,0,dd98d752,34758918245187587">00吃过</d><d p="250.54000,1,25,16777215,1593439585,0,dd98d752,34758936607850503">00没吃过</d><d p="42.63700,1,25,16777215,1593440336,0,696358d2,34759330641215491">00没吃过</d><d p="82.46600,1,25,16777215,1593440453,0,696358d2,34759391847645191">00没吃过，吃过类似的</d><d p="87.20500,1,25,16777215,1593440481,0,696358d2,34759406776221701">00没吃过，但吃过类似的</d><d p="98.25300,1,25,16777215,1593440497,0,696358d2,34759415046340611">00吃过</d><d p="116.17300,1,25,16777215,1593440564,0,696358d2,34759449957105671">00吃过</d><d p="130.04200,1,25,16777215,1593440586,0,696358d2,34759461767217157">00吃过</d><d p="162.46900,1,25,16777215,1593440623,0,696358d2,34759480870699013">好像吃过</d><d p="182.77500,1,25,16777215,1593440647,0,696358d2,34759493536448515">00吃过</d><d p="187.42600,1,25,16777215,1593440656,0,696358d2,34759498110861317">00吃过</d><d p="200.78300,1,25,16777215,1593440677,0,696358d2,34759509311225859">00吃过</d><d p="222.03000,1,25,16777215,1593440709,0,696358d2,34759525923815427">好像吃过</d><d p="69.78100,1,25,16777215,1593443632,0,e90d4aa7,34761058531409925">00吃过</d><d p="100.57900,1,25,16777215,1593444770,0,f123894d,34761655014916099">00</d><d p="167.74300,1,25,16777215,1593448498,0,765203ff,34763609646039045">95没见过</d><d p="144.40000,1,25,16777215,1593452184,0,7f6de3cb,34765542136479751">哈哈哈</d><d p="178.93700,1,25,16777215,1593452218,0,7f6de3cb,34765560166744069">哈哈哈哈</d><d p="226.36900,1,25,16777215,1593452266,0,7f6de3cb,34765585040015365">爱吃！！</d><d p="261.23600,1,25,16777215,1593452300,0,7f6de3cb,34765603347103751">哈哈哈哈 很少吃</d><d p="40.16300,1,25,16777215,1593455964,0,503e1f18,34767524314742787">06吃过</d><d p="99.63000,1,25,16777215,1593456047,0,503e1f18,34767567465742343">06吃过</d><d p="104.95000,1,25,16777215,1593456079,0,503e1f18,34767584319504387">你，，真的是</d><d p="115.56200,1,25,16777215,1593456109,0,503e1f18,34767600086941701">06吃过，现在很多盗版，味道都不一样。</d><d p="182.66400,1,25,16777215,1593456184,0,503e1f18,34767639435804677">06吃过</d><d p="199.80100,1,25,16777215,1593456222,0,503e1f18,34767659413798917">06吃过，蒙牛的，现在还有草莓味的</d><d p="248.60900,1,25,16777215,1593456309,0,503e1f18,34767704879529989">06吃过，每次在蘸酱的时候把饼干弄断</d><d p="54.03200,1,25,16777215,1593457273,0,be599d7d,34768210372853765"> 00吃过</d><d p="188.93700,1,25,16777215,1593457447,0,be599d7d,34768301623083015">00喜欢吃！</d><d p="209.78000,1,25,16777215,1593457520,0,be599d7d,34768339605651459">00爱奶片</d><d p="84.42000,1,25,16777215,1593459849,0,1e5f99f7,34769561122766851">90没吃过</d><d p="46.85400,1,25,16777215,1593481665,0,de5fec4f,34780998732349443">00吃过</d><d p="76.59400,1,25,16777215,1593481703,0,de5fec4f,34781018496434179">00没吃过</d><d p="107.78300,1,25,16777215,1593481734,0,de5fec4f,34781034713710595">00吃过</d><d p="129.47000,1,25,16777215,1593481767,0,de5fec4f,34781052250619911">00吃过</d><d p="178.81000,1,25,16777215,1593481793,0,de5fec4f,34781065795600389">00吃过</d><d p="199.45600,1,25,16777215,1593481812,0,de5fec4f,34781076113588229">00吃过</d><d p="221.77600,1,25,16777215,1593481837,0,de5fec4f,34781089212399623">00吃过</d><d p="52.80000,1,25,16777215,1593490803,0,d64e3bb4,34785789720657927">95后吃过</d><d p="22.67100,1,25,15772458,1593505629,0,ec58144f,34793563003289671">哈哈哈哈哈哈哈</d><d p="100.90200,1,25,16707842,1593506703,0,c9d7c902,34794126077067267">????</d><d p="126.56500,1,25,16777215,1593506754,0,c9d7c902,34794152613380101">这个酸酸的，03吃过</d><d p="43.50000,1,25,16777215,1593507321,0,2d678e05,34794449904599047">00吃过</d><d p="39.87900,1,25,16777215,1593515211,0,63b1b91c,34798586747158531"> 00吃过</d><d p="45.17900,1,25,16777215,1593515991,0,55c590f3,34798995262930949">吃过</d><d p="221.80000,1,25,16777215,1593516006,0,7a778fb0,34799003447066631">99吃过</d><d p="221.80000,1,25,16777215,1593516023,0,7a778fb0,34799012127178759">99吃过</d><d p="162.99800,1,25,16777215,1593516196,0,dd68413b,34799103022989319">00全吃过</d><d p="42.87600,1,25,16777215,1593516287,0,f6e53a68,34799150892580867">05吃过</d><d p="37.88800,1,25,16777215,1593516297,0,b39d8070,34799155947765765">01吃过</d><d p="276.19800,5,25,15138834,1593516328,0,dd68413b,34799172407263235">00全吃过，哈哈哈哈</d><d p="97.00100,1,25,16777215,1593516341,0,f6e53a68,34799179271766023">05吃过</d><d p="119.37700,1,25,16777215,1593516364,0,f6e53a68,34799191012671495">05吃过</d><d p="185.04400,1,25,16777215,1593516431,0,f6e53a68,34799226389004295">05吃过</d><d p="204.10600,1,25,16777215,1593516449,0,f6e53a68,34799235433496579">05吃过</d><d p="270.04700,1,25,16777215,1593516517,0,f6e53a68,34799271060439043">巧克力糊糊哈哈哈哈哈哈</d><d p="207.85900,1,25,16777215,1593516869,0,689607eb,34799455698944005">不会含它，直接嚼碎</d><d p="75.40000,1,25,16777215,1593517093,0,b0609f2e,34799573319286787">00吃过!！</d><d p="47.10000,1,25,16777215,1593517792,0,a0b1f05a,34799939953360899">05吃过</d><d p="94.49900,1,25,16777215,1593517853,0,a0b1f05a,34799971856809987">05吃过</d><d p="118.49900,1,25,16777215,1593517888,0,a0b1f05a,34799990225764355">05吃过</d><d p="134.45900,1,25,16777215,1593517919,0,a0b1f05a,34800006269501443">05吃过</d><d p="184.46000,1,25,16777215,1593517977,0,a0b1f05a,34800036554997763">05吃过</d><d p="54.01900,1,25,16777215,1593519328,0,2c0208b1,34800744946204743">80吃过</d><d p="117.21900,1,25,16777215,1593524752,0,37d1ceed,34803588763484165">05c天天吃的！</d><d p="53.73700,1,25,16777215,1593525369,0,16a1bc15,34803912449458179">97没有</d><d p="70.05700,1,25,16777215,1593525393,0,16a1bc15,34803925046525955">97没有</d><d p="97.21700,1,25,16777215,1593525433,0,16a1bc15,34803945726541831">97的吃过</d><d p="52.04000,1,25,16777215,1593525466,0,3cb14d9c,34803963294908423">00没吃过</d><d p="69.42000,1,25,16777215,1593525498,0,3cb14d9c,34803980021792775">00没吃过</d><d p="98.10000,1,25,16777215,1593525537,0,3cb14d9c,34804000279756807">00吃过</d><d p="116.44000,1,25,16777215,1593525562,0,3cb14d9c,34804013208698885">00吃过</d><d p="126.46000,1,25,16777215,1593525579,0,3cb14d9c,34804022446129157">00吃过</d><d p="157.92000,1,25,16777215,1593525619,0,3cb14d9c,34804043510448135">00没吃过</d><d p="179.89900,1,25,16777215,1593525649,0,3cb14d9c,34804058810744837">00吃过</d><d p="200.01900,1,25,16777215,1593525676,0,3cb14d9c,34804073221324803">00吃过</d><d p="219.69900,1,25,16777215,1593525705,0,3cb14d9c,34804088664227845">00没吃过</d><d p="250.41900,1,25,16777215,1593525743,0,3cb14d9c,34804108338135107">00吃过</d><d p="76.82300,1,25,16777215,1593525969,0,6364487b,34804226779512837">00吃过</d><d p="101.91500,1,25,16777215,1593525994,0,6364487b,34804239800205319">00的最爱</d><d p="39.37900,1,25,16777215,1593526512,0,74e9400e,34804511379292165">90吃过，但没见过这个包装哎</d><d p="204.79900,1,25,16777215,1593526514,0,34cde671,34804512726712327">怪味花生，老板丹</d><d p="71.92000,1,25,15138834,1593526556,0,74e9400e,34804534821781507">90没吃过</d><d p="95.60600,1,25,15138834,1593526899,0,74e9400e,34804714626875399">这个跟年龄无关，应该都吃过吧</d><d p="103.18600,1,25,15138834,1593526928,0,74e9400e,34804729604734979">哎呀糖中可乐这个比喻好</d><d p="117.10600,1,25,15138834,1593526946,0,74e9400e,34804739138387973">90吃过</d><d p="136.88600,1,25,15138834,1593526980,0,74e9400e,34804757128282115">90吃过，不喜欢</d><d p="160.78600,1,25,15138834,1593527014,0,74e9400e,34804774620102727">90甚至没见过</d><d p="182.76600,1,25,15138834,1593527058,0,74e9400e,34804797884858373">90吃过，不过感觉挺齁的哈哈哈</d><d p="202.24600,1,25,15138834,1593527087,0,74e9400e,34804813069287429">哎呀我可喜欢这个了！！</d><d p="227.12600,1,25,15138834,1593527123,0,74e9400e,34804832135020547">这什么公主吃法哈哈哈哈哈哈</d><d p="75.21400,1,25,16777215,1593528267,0,64c30fa5,34805431430283271">95没吃过</d><d p="73.50000,1,25,16777215,1593528351,0,197459ab,34805475616751621">00后表示昨天晚上刚吃过</d><d p="117.58500,1,25,16777215,1593528594,0,4e189619,34805603298705415">00吃过</d><d p="125.19500,1,25,16777215,1593528611,0,4e189619,34805612165464069">05吃过</d><d p="200.65600,1,25,16777215,1593528693,0,4e189619,34805654790078471">06吃过</d><d p="37.54000,1,25,16777215,1593528986,0,26140ef7,34805808383918087">吃过</d><d p="93.46000,1,25,16777215,1593529051,0,26140ef7,34805842590040069">00吃过</d><d p="52.27900,1,25,16777215,1593529389,0,ab1316b6,34806019772645379">00吃过</d><d p="46.60600,1,25,16777215,1593529529,0,fa67af42,34806093331300355">90吃过</d><d p="79.58800,1,25,16777215,1593529562,0,fa67af42,34806110639620101">90没吃过</d><d p="133.23600,1,25,16777215,1593529616,0,fa67af42,34806138757709827">90吃过</d><d p="102.52000,1,25,16777215,1593529647,0,77ce5610,34806155408048131">90后吃过</d><d p="44.73900,1,25,16777215,1593531171,0,b7ee0242,34806954025025539">00吃过</d><d p="117.30000,1,25,16777215,1593531253,0,b7ee0242,34806997209055235">00吃过</d><d p="51.52700,1,25,16777215,1593531387,0,66bc404f,34807067564310533">吃过  00后</d><d p="102.84800,1,25,16777215,1593531439,0,66bc404f,34807094539452423">吃过</d><d p="135.76500,1,25,16777215,1593531472,0,66bc404f,34807111750254597">吃过</d><d p="169.89400,1,25,16777215,1593532104,0,396e3627,34807443316801541">我妈还真吃过</d><d p="50.89900,1,25,16777215,1593532124,0,1975ea72,34807454029578247">95没吃过</d><d p="265.55900,1,25,16777215,1593532350,0,1975ea72,34807572419575811">3岁时吃的？</d><d p="189.23100,1,25,16777215,1593532680,0,ef229223,34807745118470147">04吃过！仔仔雪梅肉哈哈哈哈</d><d p="214.32500,1,25,16777215,1593534319,0,93847e80,34808604454289415">现在有卖的</d><d p="50.98000,1,25,16777215,1593534458,0,7f298298,34808677410013189">超市现在还有卖的啊</d><d p="71.46000,1,25,16777215,1593534493,0,7f298298,34808695872290823">00真的吃过啊</d><d p="94.65900,1,25,16777215,1593534531,0,7f298298,34808715583422469">超市现在还有卖的+1</d><d p="162.72900,1,25,16777215,1593534609,0,7f298298,34808756774109191">00小时候超市有卖的，吃过，还有那种湿的</d><d p="202.09400,1,25,16777215,1593534659,0,7f298298,34808782687567877">还有口哨糖</d><d p="206.99000,1,25,16777215,1593534664,0,7f298298,34808785639309317">口哨糖</d><d p="211.69400,1,25,16777215,1593534681,0,7f298298,34808794467794951">口哨糖，酸奶片更好吃</d><d p="249.28900,1,25,16777215,1593534727,0,7f298298,34808818543624195">现在超市还有卖，两块钱</d><d p="44.79800,1,25,16777215,1593535298,0,74aab01c,34809118200430599">00 我吃的时候不是这样</d><d p="75.09600,1,25,16777215,1593535329,0,74aab01c,34809134071676935">00没有</d><d p="96.87000,1,25,16777215,1593535351,0,74aab01c,34809145484378119">00吃过</d><d p="119.00000,1,25,16777215,1593535373,0,74aab01c,34809157063278597">必吃</d><d p="130.05600,1,25,16777215,1593535384,0,74aab01c,34809162856136709">00吃过</d><d p="156.72200,1,25,16777215,1593536289,0,35ad22a0,34809637374001157">最适合上课偷吃的零食</d><d p="54.99600,1,25,16777215,1593536624,0,1a8e7a0f,34809813263712261">小浣熊现在不都有嘛！</d><d p="76.57000,1,25,16777215,1593536646,0,1a8e7a0f,34809824575225861">00吃过</d><d p="130.93900,1,25,16777215,1593536700,0,1a8e7a0f,34809853060841479">这个超好吃！</d><d p="180.95700,1,25,16777215,1593536750,0,1a8e7a0f,34809879306698757">这个真没吃过</d><d p="194.65900,1,25,16777215,1593540932,0,fec410a9,34812071910047747">甜死了，我一般一颗都吃不掉</d><d p="41.27900,1,25,16777215,1593561422,0,4846ab8c,34822814540759047">85后的童年回忆，集各种卡</d><d p="101.59500,1,25,16777215,1593561861,0,6a631cc5,34823044682219525">00吃过</d><d p="139.36100,1,25,16777215,1593561899,0,6a631cc5,34823064354029573">00后吃过</d><d p="146.56700,1,25,16777215,1593561906,0,6a631cc5,34823068106358791">现在一块</d><d p="53.86200,1,25,16777215,1593562076,0,2892c3a,34823157354332165">80吃过</d><d p="81.36200,1,25,16777215,1593562104,0,2892c3a,34823171738697731">没吃过</d><d p="103.86300,1,25,16777215,1593562126,0,2892c3a,34823183516303363">80吃过</d><d p="129.86200,1,25,16777215,1593562152,0,2892c3a,34823197196550151">80小时候经常吃</d><d p="43.08000,1,25,16777215,1593564500,0,df45117c,34824428169723911">zara？？</d><d p="144.75900,1,25,16777215,1593565301,0,4f2afa97,34824848145383427">现在贵了555</d><d p="166.02700,1,25,16777215,1593566914,0,8718f93a,34825693881696263">97没吃过</d><d p="71.17900,1,25,16777215,1593570367,0,613a1f28,34827504210935815">05吃过</d><d p="77.41900,1,25,16777215,1593570379,0,613a1f28,34827510556393479">94吃过</d><d p="127.66000,1,25,16777215,1593570441,0,613a1f28,34827543075356675">94吃过</d><d p="147.94000,1,25,16777215,1593570465,0,613a1f28,34827555358375941">呵呵哈哈</d><d p="187.25900,1,25,16777215,1593570508,0,613a1f28,34827578198982661">哈哈哈哈哈</d><d p="201.83900,1,25,16777215,1593570527,0,613a1f28,34827588295196679">94吃过</d><d p="94.16500,1,25,16777215,1593572418,0,8742417b,34828579271868421">00吃过</d><d p="87.70000,1,25,16777215,1593576303,0,15a92510,34830616324734979">02吃过</d><d p="54.44000,1,25,15138834,1593576609,0,9c2cc67,34830776658296835">09，吃过</d><d p="95.02000,1,25,15138834,1593576671,0,9c2cc67,34830809048285191">09，吃过</d><d p="38.06000,1,25,16777215,1593576883,0,dfe795fb,34830920574828551">00，吃过</d><d p="93.69900,1,25,16777215,1593576945,0,dfe795fb,34830953053945861">00，吃过</d><d p="41.63600,1,25,16777215,1593577715,0,9a133e98,34831356811280391">95吃过</d><d p="78.13600,1,25,16777215,1593577752,0,9a133e98,34831375958278151">95没吃过</d><d p="98.63500,1,25,16777215,1593577772,0,9a133e98,34831386644840455">95吃过</d><d p="119.63500,1,25,16777215,1593577793,0,9a133e98,34831397668519941">95吃过</d><d p="128.63400,1,25,16777215,1593577802,0,9a133e98,34831402344644611">95吃过</d><d p="173.63600,1,25,16777215,1593577847,0,9a133e98,34831425829076995">95吃过</d><d p="185.63600,1,25,16777215,1593577859,0,9a133e98,34831432094842885">95吃过</d><d p="203.13600,1,25,16777215,1593577877,0,9a133e98,34831441347477509">95吃过</d><d p="221.63500,1,25,16777215,1593577895,0,9a133e98,34831451156905989">95吃过</d><d p="39.29900,1,25,16777215,1593578037,0,cf76b10a,34831525230936071">00吃过</d><d p="68.88000,1,25,16777215,1593578073,0,cf76b10a,34831544115265541">00没吃过</d><d p="92.86000,1,25,16777215,1593578102,0,cf76b10a,34831559529332741">00吃过</d><d p="115.47900,1,25,16777215,1593578128,0,cf76b10a,34831573426110471">都吃过</d><d p="125.66000,1,25,16777215,1593578142,0,cf76b10a,34831580732063749">00吃过</d><d p="157.89900,1,25,16777215,1593578178,0,cf76b10a,34831599408250885">00没有</d><d p="201.03900,1,25,16777215,1593578226,0,cf76b10a,34831624721399815">00吃过</d><d p="218.85900,1,25,16777215,1593578252,0,cf76b10a,34831638164668419">哇哇哇小时候超爱吃</d><d p="249.16000,1,25,16777215,1593578286,0,cf76b10a,34831656241594371">00吃过</d><d p="233.03900,1,25,16777215,1593579027,0,417a7abf,34832044649349123">喝口水吧</d><d p="236.49900,1,25,16777215,1593583802,0,c3d5795d,34834547978797059">老邪好帅</d><d p="140.34900,1,25,16777215,1593584377,0,6dd8cd08,34834849235206147">真的是萝卜丝？我不信</d><d p="88.70500,1,25,16777215,1593584411,0,7a69b2ed,34834867277529095">牛羊配不是腰果吗</d><d p="174.56800,1,25,16777215,1593584429,0,6dd8cd08,34834876650225671">对对对！我想起来了00吃过</d><d p="213.08300,1,25,16777215,1593585319,0,890fcfd1,34835343545466885">吃播的奶片教学吗？哈哈</d><d p="38.70000,1,25,16777215,1593586232,0,cd72471,34835821805174787">02</d><d p="42.27100,1,25,16777215,1593588724,0,444c94fe,34837128552644613">01吃过</d><d p="128.95100,1,25,16777215,1593588796,0,444c94fe,34837166087995397">这个超好吃，那时候卖的是五毛一包，也有一毛一包的</d><d p="264.03500,1,25,16777215,1593588871,0,444c94fe,34837205709488135">哈哈哈这个吃过</d><d p="38.61600,1,25,16777215,1593589181,0,8348c972,34837368144920579">00后的我吃过</d><d p="8.71700,1,25,16777215,1593589581,0,a7c10c07,34837577681338373">好帅好帅</d><d p="17.54700,1,25,16777215,1593589590,0,a7c10c07,34837582290878469">你是谁</d><d p="38.66000,1,25,16777215,1593589727,0,de5d93d2,34837654254125127">00吃过</d><d p="95.08000,1,25,16777215,1593589790,0,de5d93d2,34837687650222085">00吃过</d><d p="120.10800,1,25,16777215,1593589818,0,de5d93d2,34837702009946119">00吃过</d><d p="202.43700,1,25,16777215,1593589883,0,de5d93d2,34837736148959237">00吃过</d><d p="225.01700,1,25,16777215,1593589913,0,de5d93d2,34837751778508805">00吃过</d><d p="84.97900,1,25,16777215,1593591875,0,8b26d836,34838780440477703">00没吃过</d><d p="103.29800,1,25,16777215,1593591887,0,8b26d836,34838786825256965">00吃过</d><d p="132.81400,1,25,16777215,1593591907,0,8b26d836,34838797144293383">00吃过</d><d p="193.15500,1,25,16777215,1593591947,0,8b26d836,34838818265235463">00吃过</d><d p="133.59700,1,25,16777215,1593593353,0,de5cbbdc,34839555692036101">98吃过！</d><d p="100.02100,1,25,16777215,1593594530,0,a6d93263,34840172454477831">05后吃过</d><d p="124.76900,1,25,16777215,1593594555,0,a6d93263,34840185455771653">05后吃过</d><d p="130.88200,1,25,16777215,1593594561,0,a6d93263,34840188647112709">05后没吃过</d><d p="96.14700,1,25,16777215,1593594567,0,22d80999,34840191805947911">00吃过</d><d p="47.08000,1,25,16777215,1593594734,0,9bc8c614,34840279577001991">这和我脑子里的老邪不一样</d><d p="68.78400,1,25,16777215,1593594756,0,9bc8c614,34840290984984579">画面和声音怎么就是对不齐</d><d p="286.95000,1,25,16777215,1593594786,0,22d80999,34840306703663109">摇摇果冻，旺仔牌的</d><d p="54.79200,1,25,16777215,1593595317,0,9ea93491,34840585088008199">00没吃过</d><d p="42.85600,1,25,16777215,1593595326,0,1d0d6b9f,34840590104920067">00吃过</d><d p="112.92900,1,25,16777215,1593595397,0,1d0d6b9f,34840626905743363">？？？</d><d p="137.33500,1,25,16777215,1593595399,0,9ea93491,34840628369031175">00没吃过</d><d p="129.00400,1,25,16777215,1593595413,0,1d0d6b9f,34840635259224069">00吃过</d><d p="166.63500,1,25,16777215,1593595429,0,9ea93491,34840643729096711">00没吃过</d><d p="163.27900,1,25,16777215,1593595432,0,1d0d6b9f,34840645635932165">00没吃过</d><d p="102.04700,1,25,16777215,1593595455,0,b3efb978,34840657320214535">00后吃过</d><d p="43.78900,1,25,16777215,1593595462,0,ba7f87bd,34840661274918917">00吃过</d><d p="106.15200,1,25,16776960,1593595484,0,b3efb978,34840672832323591">？？？？？？？</d><d p="229.49400,1,25,16777215,1593595502,0,9ea93491,34840682097541123">00没吃过</d><d p="131.11800,1,25,16777215,1593595550,0,ba7f87bd,34840707097165831">00吃过</d><d p="167.17800,1,25,16777215,1593595586,0,ba7f87bd,34840725984116743">00没吃过</d><d p="193.05600,1,25,16777215,1593595611,0,ba7f87bd,34840739550068743">00出过</d><d p="204.93300,1,25,16777215,1593595623,0,ba7f87bd,34840745759211523">00吃过</d><d p="225.53300,1,25,16777215,1593595644,0,ba7f87bd,34840756574748679">00吃过</d><d p="265.86900,1,25,16777215,1593595684,0,ba7f87bd,34840777722429447">00吃过</d><d p="96.47100,1,25,16777215,1593596248,0,a7c10c07,34841073303420931">老邪也太帅了叭！！</d><d p="39.62000,1,25,16777215,1593600911,0,630fb006,34843517909991431">00吃过</d><d p="92.53900,1,25,16777215,1593600969,0,630fb006,34843548255780869">00吃过</d><d p="126.58000,1,25,16777215,1593601008,0,630fb006,34843569070538755">00吃过</d><d p="44.79600,1,25,16777215,1593601747,0,ab882f06,34843956461174791">90吃过</d><d p="75.08800,1,25,16777215,1593601778,0,ab882f06,34843972341858311">90没吃过</d><d p="97.05600,1,25,16777215,1593601800,0,ab882f06,34843983871475719">90吃过</d><d p="119.49700,1,25,16777215,1593601822,0,ab882f06,34843995644362757">90吃过</d><d p="129.73600,1,25,16777215,1593601832,0,ab882f06,34844000998391815">90吃过</d><d p="163.50700,1,25,16777215,1593601866,0,ab882f06,34844018713559045">90没吃过</d><d p="187.31700,1,25,16777215,1593601937,0,ab882f06,34844056068030469">90吃过</d><d p="206.39400,1,25,16777215,1593601956,0,ab882f06,34844066022686725">90吃过</d><d p="228.53000,1,25,16777215,1593601978,0,ab882f06,34844077617840135">90没吃过</d><d p="265.48300,1,25,16777215,1593602015,0,ab882f06,34844097000767491">90没吃过</d><d p="13.44600,1,25,16777215,1593602335,0,b67b1b73,34844264674361351">推荐大家铁板烧</d></i>